Workbook

Sheet Project Information
B2: =INDEX(Translations!$D:$ZZ,MATCH(1001,Translations!$A:$A,0),MATCH($C$4,Translations!$D$1:$ZZ$1,0))
B4: =INDEX(Translations!$D:$ZZ,MATCH(1002,Translations!$A:$A,0),MATCH($C$4,Translations!$D$1:$ZZ$1,0)) | C4: TR
B6: =INDEX(Translations!$D:$ZZ,MATCH(1003,Translations!$A:$A,0),MATCH($C$4,Translations!$D$1:$ZZ$1,0)) | C6: Ufuk Enerji AŞ
B7: =INDEX(Translations!$D:$ZZ,MATCH(1004,Translations!$A:$A,0),MATCH($C$4,Translations!$D$1:$ZZ$1,0)) | C7: S4 Dönüşüm
B8: =INDEX(Translations!$D:$ZZ,MATCH(1005,Translations!$A:$A,0),MATCH($C$4,Translations!$D$1:$ZZ$1,0)) | C8: 46156.374
B10: =INDEX(Translations!$D:$ZZ,MATCH(1006,Translations!$A:$A,0),MATCH($C$4,Translations!$D$1:$ZZ$1,0)) | C10: Konfeksiyon
B11: =INDEX(Translations!$D:$ZZ,MATCH(1007,Translations!$A:$A,0),MATCH($C$4,Translations!$D$1:$ZZ$1,0)) | C11: Conversion
B12: =INDEX(Translations!$D:$ZZ,MATCH(1008,Translations!$A:$A,0),MATCH($C$4,Translations!$D$1:$ZZ$1,0)) | C12: SAP S/4HANA Private Cloud
B14: =INDEX(Translations!$D:$ZZ,MATCH(1009,Translations!$A:$A,0),MATCH($C$4,Translations!$D$1:$ZZ$1,0)) | C14: Ufuk Turcan
B15: =INDEX(Translations!$D:$ZZ,MATCH(1010,Translations!$A:$A,0),MATCH($C$4,Translations!$D$1:$ZZ$1,0)) | C15: V1
B17: =INDEX(Translations!$D:$ZZ,MATCH(1011,Translations!$A:$A,0),MATCH($C$4,Translations!$D$1:$ZZ$1,0)) | C17: Dikkat

Sheet Scope
A1: =INDEX(Translations!$D:$ZZ, MATCH(1,Translations!$A:$A,0), MATCH('Project Information'!$C$4,Translations!$D$1:$ZZ$1,0))
A4: =INDEX(Translations!$D:$ZZ, MATCH(4,Translations!$A:$A,0), MATCH('Project Information'!$C$4,Translations!$D$1:$ZZ$1,0))
A5: =INDEX(Translations!$D:$ZZ, MATCH(5,Translations!$A:$A,0), MATCH('Project Information'!$C$4,Translations!$D$1:$ZZ$1,0)) | B5: =INDEX(Translations!$D:$ZZ, MATCH(6,Translations!$A:$A,0), MATCH('Project Information'!$C$4,Translations!$D$1:$ZZ$1,0))
A6: =INDEX(Translations!$D:$ZZ, MATCH(7,Translations!$A:$A,0), MATCH('Project Information'!$C$4,Translations!$D$1:$ZZ$1,0)) | B6: =INDEX(Translations!$D:$ZZ, MATCH(8,Translations!$A:$A,0), MATCH('Project Information'!$C$4,Translations!$D$1:$ZZ$1,0))
A7: =INDEX(Translations!$D:$ZZ, MATCH(9,Translations!$A:$A,0), MATCH('Project Information'!$C$4,Translations!$D$1:$ZZ$1,0)) | B7: =INDEX(Translations!$D:$ZZ, MATCH(10,Translations!$A:$A,0), MATCH('Project Information'!$C$4,Translations!$D$1:$ZZ$1,0))
A8: =INDEX(Translations!$D:$ZZ, MATCH(11,Translations!$A:$A,0), MATCH('Project Information'!$C$4,Translations!$D$1:$ZZ$1,0)) | B8: =INDEX(Translations!$D:$ZZ, MATCH(12,Translations!$A:$A,0), MATCH('Project Information'!$C$4,Translations!$D$1:$ZZ$1,0))
A9: =INDEX(Translations!$D:$ZZ, MATCH(13,Translations!$A:$A,0), MATCH('Project Information'!$C$4,Translations!$D$1:$ZZ$1,0)) | B9: =SUM($H$13:$H$59) | J9: =IF($B$9<=40,"S",IF($B$9<=70,"M",IF($B$9<=100,"L","XL")))
A10: =INDEX(Translations!$D:$ZZ, MATCH(14,Translations!$A:$A,0), MATCH('Project Information'!$C$4,Translations!$D$1:$ZZ$1,0)) | B10: =IF($J$9="S",INDEX(Translations!$D:$ZZ,MATCH(5,Translations!$A:$A,0),MATCH('Project Information'!$C$4,Translations!$D$1:$ZZ$1,0)),IF($J$9="M",INDEX(Translations!$D:$ZZ,MATCH(7,Translations!$A:$A,0),MATCH('Project Information'!$C$4,Translations!$D$1:$ZZ$1,0)),IF($J$9="L",INDEX(Translations!$D:$ZZ,MATCH(9,Translations!$A:$A,0),MATCH('Project Information'!$C$4,Translations!$D$1:$ZZ$1,0)),INDEX(Translations!$D:$ZZ,MATCH(11,Translations!$A:$A,0),MATCH('Project Information'!$C$4,Translations!$D$1:$ZZ$1,0)))))
A11: =INDEX(Translations!$D:$ZZ, MATCH(15,Translations!$A:$A,0), MATCH('Project Information'!$C$4,Translations!$D$1:$ZZ$1,0))
A12: =INDEX(Translations!$D:$ZZ, MATCH(16,Translations!$A:$A,0), MATCH('Project Information'!$C$4,Translations!$D$1:$ZZ$1,0)) | B12: =INDEX(Translations!$D:$ZZ, MATCH(17,Translations!$A:$A,0), MATCH('Project Information'!$C$4,Translations!$D$1:$ZZ$1,0)) | C12: =INDEX(Translations!$D:$ZZ, MATCH(18,Translations!$A:$A,0), MATCH('Project Information'!$C$4,Translations!$D$1:$ZZ$1,0)) | D12: =INDEX(Translations!$D:$ZZ, MATCH(19,Translations!$A:$A,0), MATCH('Project Information'!$C$4,Translations!$D$1:$ZZ$1,0)) | E12: =INDEX(Translations!$D:$ZZ, MATCH(20,Translations!$A:$A,0), MATCH('Project Information'!$C$4,Translations!$D$1:$ZZ$1,0)) | F12: =INDEX(Translations!$D:$ZZ, MATCH(21,Translations!$A:$A,0), MATCH('Project Information'!$C$4,Translations!$D$1:$ZZ$1,0)) | G12: =INDEX(Translations!$D:$ZZ, MATCH(22,Translations!$A:$A,0), MATCH('Project Information'!$C$4,Translations!$D$1:$ZZ$1,0)) | H12: =INDEX(Translations!$D:$ZZ, MATCH(23,Translations!$A:$A,0), MATCH('Project Information'!$C$4,Translations!$D$1:$ZZ$1,0)) | I12: =INDEX(Translations!$D:$ZZ, MATCH(24,Translations!$A:$A,0), MATCH('Project Information'!$C$4,Translations!$D$1:$ZZ$1,0)) | K12: Applicable?
A13: 1 | B13: =INDEX(Translations!$D:$ZZ, MATCH(25,Translations!$A:$A,0), MATCH('Project Information'!$C$4,Translations!$D$1:$ZZ$1,0)) | C13: =INDEX(Translations!$D:$ZZ, MATCH(26,Translations!$A:$A,0), MATCH('Project Information'!$C$4,Translations!$D$1:$ZZ$1,0)) | D13: =INDEX(Translations!$D:$ZZ, MATCH(27,Translations!$A:$A,0), MATCH('Project Information'!$C$4,Translations!$D$1:$ZZ$1,0)) | E13: 5 | G13: 2 | H13: =IF(OR(TRIM(F13)="Evet",TRIM(F13)="Yes"),E13,IF(G13="","",E13*G13)) | K13: =IFERROR(AND(OR(INDEX('Question Restrictions'!$D:$D,MATCH($B13,'Question Restrictions'!$C:$C,0))="All",ISNUMBER(SEARCH('Project Information'!$C$10,INDEX('Question Restrictions'!$D:$D,MATCH($B13,'Question Restrictions'!$C:$C,0))))),OR(INDEX('Question Restrictions'!$E:$E,MATCH($B13,'Question Restrictions'!$C:$C,0))="All",ISNUMBER(SEARCH('Project Information'!$C$11,INDEX('Question Restrictions'!$E:$E,MATCH($B13,'Question Restrictions'!$C:$C,0))))),OR(INDEX('Question Restrictions'!$F:$F,MATCH($B13,'Question Restrictions'!$C:$C,0))="All",ISNUMBER(SEARCH('Project Information'!$C$12,INDEX('Question Restrictions'!$F:$F,MATCH($B13,'Question Restrictions'!$C:$C,0))))),INDEX('Question Restrictions'!$G:$G,MATCH($B13,'Question Restrictions'!$C:$C,0))="Yes"),TRUE())
A14: 2 | B14: =INDEX(Translations!$D:$ZZ, MATCH(164,Translations!$A:$A,0), MATCH('Project Information'!$C$4,Translations!$D$1:$ZZ$1,0)) | C14: =INDEX(Translations!$D:$ZZ, MATCH(165,Translations!$A:$A,0), MATCH('Project Information'!$C$4,Translations!$D$1:$ZZ$1,0)) | D14: =INDEX(Translations!$D:$ZZ, MATCH(27,Translations!$A:$A,0), MATCH('Project Information'!$C$4,Translations!$D$1:$ZZ$1,0)) | H14: =IF(OR(TRIM(F14)="Evet",TRIM(F14)="Yes"),E14,IF(G14="","",E14*G14)) | K14: =IFERROR(AND(OR(INDEX('Question Restrictions'!$D:$D,MATCH($B14,'Question Restrictions'!$C:$C,0))="All",ISNUMBER(SEARCH('Project Information'!$C$10,INDEX('Question Restrictions'!$D:$D,MATCH($B14,'Question Restrictions'!$C:$C,0))))),OR(INDEX('Question Restrictions'!$E:$E,MATCH($B14,'Question Restrictions'!$C:$C,0))="All",ISNUMBER(SEARCH('Project Information'!$C$11,INDEX('Question Restrictions'!$E:$E,MATCH($B14,'Question Restrictions'!$C:$C,0))))),OR(INDEX('Question Restrictions'!$F:$F,MATCH($B14,'Question Restrictions'!$C:$C,0))="All",ISNUMBER(SEARCH('Project Information'!$C$12,INDEX('Question Restrictions'!$F:$F,MATCH($B14,'Question Restrictions'!$C:$C,0))))),INDEX('Question Restrictions'!$G:$G,MATCH($B14,'Question Restrictions'!$C:$C,0))="Yes"),TRUE())
A15: 3 | B15: =INDEX(Translations!$D:$ZZ, MATCH(30,Translations!$A:$A,0), MATCH('Project Information'!$C$4,Translations!$D$1:$ZZ$1,0)) | C15: =INDEX(Translations!$D:$ZZ, MATCH(31,Translations!$A:$A,0), MATCH('Project Information'!$C$4,Translations!$D$1:$ZZ$1,0)) | D15: =INDEX(Translations!$D:$ZZ, MATCH(27,Translations!$A:$A,0), MATCH('Project Information'!$C$4,Translations!$D$1:$ZZ$1,0)) | E15: 5 | H15: =IF(OR(TRIM(F15)="Evet",TRIM(F15)="Yes"),E15,IF(G15="","",E15*G15)) | K15: =IFERROR(AND(OR(INDEX('Question Restrictions'!$D:$D,MATCH($B15,'Question Restrictions'!$C:$C,0))="All",ISNUMBER(SEARCH('Project Information'!$C$10,INDEX('Question Restrictions'!$D:$D,MATCH($B15,'Question Restrictions'!$C:$C,0))))),OR(INDEX('Question Restrictions'!$E:$E,MATCH($B15,'Question Restrictions'!$C:$C,0))="All",ISNUMBER(SEARCH('Project Information'!$C$11,INDEX('Question Restrictions'!$E:$E,MATCH($B15,'Question Restrictions'!$C:$C,0))))),OR(INDEX('Question Restrictions'!$F:$F,MATCH($B15,'Question Restrictions'!$C:$C,0))="All",ISNUMBER(SEARCH('Project Information'!$C$12,INDEX('Question Restrictions'!$F:$F,MATCH($B15,'Question Restrictions'!$C:$C,0))))),INDEX('Question Restrictions'!$G:$G,MATCH($B15,'Question Restrictions'!$C:$C,0))="Yes"),TRUE())
A16: 4 | B16: =INDEX(Translations!$D:$ZZ, MATCH(167,Translations!$A:$A,0), MATCH('Project Information'!$C$4,Translations!$D$1:$ZZ$1,0)) | C16: =INDEX(Translations!$D:$ZZ, MATCH(168,Translations!$A:$A,0), MATCH('Project Information'!$C$4,Translations!$D$1:$ZZ$1,0)) | D16: =INDEX(Translations!$D:$ZZ, MATCH(27,Translations!$A:$A,0), MATCH('Project Information'!$C$4,Translations!$D$1:$ZZ$1,0)) | H16: =IF(OR(TRIM(F16)="Evet",TRIM(F16)="Yes"),E16,IF(G16="","",E16*G16)) | K16: =IFERROR(AND(OR(INDEX('Question Restrictions'!$D:$D,MATCH($B16,'Question Restrictions'!$C:$C,0))="All",ISNUMBER(SEARCH('Project Information'!$C$10,INDEX('Question Restrictions'!$D:$D,MATCH($B16,'Question Restrictions'!$C:$C,0))))),OR(INDEX('Question Restrictions'!$E:$E,MATCH($B16,'Question Restrictions'!$C:$C,0))="All",ISNUMBER(SEARCH('Project Information'!$C$11,INDEX('Question Restrictions'!$E:$E,MATCH($B16,'Question Restrictions'!$C:$C,0))))),OR(INDEX('Question Restrictions'!$F:$F,MATCH($B16,'Question Restrictions'!$C:$C,0))="All",ISNUMBER(SEARCH('Project Information'!$C$12,INDEX('Question Restrictions'!$F:$F,MATCH($B16,'Question Restrictions'!$C:$C,0))))),INDEX('Question Restrictions'!$G:$G,MATCH($B16,'Question Restrictions'!$C:$C,0))="Yes"),TRUE())
A17: 5 | B17: =INDEX(Translations!$D:$ZZ, MATCH(28,Translations!$A:$A,0), MATCH('Project Information'!$C$4,Translations!$D$1:$ZZ$1,0)) | C17: =INDEX(Translations!$D:$ZZ, MATCH(29,Translations!$A:$A,0), MATCH('Project Information'!$C$4,Translations!$D$1:$ZZ$1,0)) | D17: =INDEX(Translations!$D:$ZZ, MATCH(27,Translations!$A:$A,0), MATCH('Project Information'!$C$4,Translations!$D$1:$ZZ$1,0)) | E17: 5 | H17: =IF(OR(TRIM(F17)="Evet",TRIM(F17)="Yes"),E17,IF(G17="","",E17*G17)) | K17: =IFERROR(AND(OR(INDEX('Question Restrictions'!$D:$D,MATCH($B17,'Question Restrictions'!$C:$C,0))="All",ISNUMBER(SEARCH('Project Information'!$C$10,INDEX('Question Restrictions'!$D:$D,MATCH($B17,'Question Restrictions'!$C:$C,0))))),OR(INDEX('Question Restrictions'!$E:$E,MATCH($B17,'Question Restrictions'!$C:$C,0))="All",ISNUMBER(SEARCH('Project Information'!$C$11,INDEX('Question Restrictions'!$E:$E,MATCH($B17,'Question Restrictions'!$C:$C,0))))),OR(INDEX('Question Restrictions'!$F:$F,MATCH($B17,'Question Restrictions'!$C:$C,0))="All",ISNUMBER(SEARCH('Project Information'!$C$12,INDEX('Question Restrictions'!$F:$F,MATCH($B17,'Question Restrictions'!$C:$C,0))))),INDEX('Question Restrictions'!$G:$G,MATCH($B17,'Question Restrictions'!$C:$C,0))="Yes"),TRUE())
A18: 6 | B18: =INDEX(Translations!$D:$ZZ, MATCH(44,Translations!$A:$A,0), MATCH('Project Information'!$C$4,Translations!$D$1:$ZZ$1,0)) | C18: =INDEX(Translations!$D:$ZZ, MATCH(45,Translations!$A:$A,0), MATCH('Project Information'!$C$4,Translations!$D$1:$ZZ$1,0)) | D18: =INDEX(Translations!$D:$ZZ, MATCH(27,Translations!$A:$A,0), MATCH('Project Information'!$C$4,Translations!$D$1:$ZZ$1,0)) | E18: 5 | H18: =IF(OR(TRIM(F18)="Evet",TRIM(F18)="Yes"),E18,IF(G18="","",E18*G18)) | K18: =IFERROR(AND(OR(INDEX('Question Restrictions'!$D:$D,MATCH($B18,'Question Restrictions'!$C:$C,0))="All",ISNUMBER(SEARCH('Project Information'!$C$10,INDEX('Question Restrictions'!$D:$D,MATCH($B18,'Question Restrictions'!$C:$C,0))))),OR(INDEX('Question Restrictions'!$E:$E,MATCH($B18,'Question Restrictions'!$C:$C,0))="All",ISNUMBER(SEARCH('Project Information'!$C$11,INDEX('Question Restrictions'!$E:$E,MATCH($B18,'Question Restrictions'!$C:$C,0))))),OR(INDEX('Question Restrictions'!$F:$F,MATCH($B18,'Question Restrictions'!$C:$C,0))="All",ISNUMBER(SEARCH('Project Information'!$C$12,INDEX('Question Restrictions'!$F:$F,MATCH($B18,'Question Restrictions'!$C:$C,0))))),INDEX('Question Restrictions'!$G:$G,MATCH($B18,'Question Restrictions'!$C:$C,0))="Yes"),TRUE())
A19: 7 | B19: =INDEX(Translations!$D:$ZZ, MATCH(32,Translations!$A:$A,0), MATCH('Project Information'!$C$4,Translations!$D$1:$ZZ$1,0)) | C19: =INDEX(Translations!$D:$ZZ, MATCH(33,Translations!$A:$A,0), MATCH('Project Information'!$C$4,Translations!$D$1:$ZZ$1,0)) | D19: =INDEX(Translations!$D:$ZZ, MATCH(34,Translations!$A:$A,0), MATCH('Project Information'!$C$4,Translations!$D$1:$ZZ$1,0)) | E19: 15 | H19: =IF(OR(TRIM(F19)="Evet",TRIM(F19)="Yes"),E19,IF(G19="","",E19*G19)) | K19: =IFERROR(AND(OR(INDEX('Question Restrictions'!$D:$D,MATCH($B19,'Question Restrictions'!$C:$C,0))="All",ISNUMBER(SEARCH('Project Information'!$C$10,INDEX('Question Restrictions'!$D:$D,MATCH($B19,'Question Restrictions'!$C:$C,0))))),OR(INDEX('Question Restrictions'!$E:$E,MATCH($B19,'Question Restrictions'!$C:$C,0))="All",ISNUMBER(SEARCH('Project Information'!$C$11,INDEX('Question Restrictions'!$E:$E,MATCH($B19,'Question Restrictions'!$C:$C,0))))),OR(INDEX('Question Restrictions'!$F:$F,MATCH($B19,'Question Restrictions'!$C:$C,0))="All",ISNUMBER(SEARCH('Project Information'!$C$12,INDEX('Question Restrictions'!$F:$F,MATCH($B19,'Question Restrictions'!$C:$C,0))))),INDEX('Question Restrictions'!$G:$G,MATCH($B19,'Question Restrictions'!$C:$C,0))="Yes"),TRUE())
A20: 8 | B20: =INDEX(Translations!$D:$ZZ, MATCH(35,Translations!$A:$A,0), MATCH('Project Information'!$C$4,Translations!$D$1:$ZZ$1,0)) | C20: =INDEX(Translations!$D:$ZZ, MATCH(36,Translations!$A:$A,0), MATCH('Project Information'!$C$4,Translations!$D$1:$ZZ$1,0)) | D20: =INDEX(Translations!$D:$ZZ, MATCH(34,Translations!$A:$A,0), MATCH('Project Information'!$C$4,Translations!$D$1:$ZZ$1,0)) | E20: 20 | H20: =IF(OR(TRIM(F20)="Evet",TRIM(F20)="Yes"),E20,IF(G20="","",E20*G20)) | K20: =IFERROR(AND(OR(INDEX('Question Restrictions'!$D:$D,MATCH($B20,'Question Restrictions'!$C:$C,0))="All",ISNUMBER(SEARCH('Project Information'!$C$10,INDEX('Question Restrictions'!$D:$D,MATCH($B20,'Question Restrictions'!$C:$C,0))))),OR(INDEX('Question Restrictions'!$E:$E,MATCH($B20,'Question Restrictions'!$C:$C,0))="All",ISNUMBER(SEARCH('Project Information'!$C$11,INDEX('Question Restrictions'!$E:$E,MATCH($B20,'Question Restrictions'!$C:$C,0))))),OR(INDEX('Question Restrictions'!$F:$F,MATCH($B20,'Question Restrictions'!$C:$C,0))="All",ISNUMBER(SEARCH('Project Information'!$C$12,INDEX('Question Restrictions'!$F:$F,MATCH($B20,'Question Restrictions'!$C:$C,0))))),INDEX('Question Restrictions'!$G:$G,MATCH($B20,'Question Restrictions'!$C:$C,0))="Yes"),TRUE())
A21: 9 | B21: =INDEX(Translations!$D:$ZZ, MATCH(37,Translations!$A:$A,0), MATCH('Project Information'!$C$4,Translations!$D$1:$ZZ$1,0)) | C21: =INDEX(Translations!$D:$ZZ, MATCH(38,Translations!$A:$A,0), MATCH('Project Information'!$C$4,Translations!$D$1:$ZZ$1,0)) | D21: =INDEX(Translations!$D:$ZZ, MATCH(34,Translations!$A:$A,0), MATCH('Project Information'!$C$4,Translations!$D$1:$ZZ$1,0)) | E21: 30 | H21: =IF(OR(TRIM(F21)="Evet",TRIM(F21)="Yes"),E21,IF(G21="","",E21*G21)) | K21: =IFERROR(AND(OR(INDEX('Question Restrictions'!$D:$D,MATCH($B21,'Question Restrictions'!$C:$C,0))="All",ISNUMBER(SEARCH('Project Information'!$C$10,INDEX('Question Restrictions'!$D:$D,MATCH($B21,'Question Restrictions'!$C:$C,0))))),OR(INDEX('Question Restrictions'!$E:$E,MATCH($B21,'Question Restrictions'!$C:$C,0))="All",ISNUMBER(SEARCH('Project Information'!$C$11,INDEX('Question Restrictions'!$E:$E,MATCH($B21,'Question Restrictions'!$C:$C,0))))),OR(INDEX('Question Restrictions'!$F:$F,MATCH($B21,'Question Restrictions'!$C:$C,0))="All",ISNUMBER(SEARCH('Project Information'!$C$12,INDEX('Question Restrictions'!$F:$F,MATCH($B21,'Question Restrictions'!$C:$C,0))))),INDEX('Question Restrictions'!$G:$G,MATCH($B21,'Question Restrictions'!$C:$C,0))="Yes"),TRUE())
A22: 10 | B22: =INDEX(Translations!$D:$ZZ, MATCH(40,Translations!$A:$A,0), MATCH('Project Information'!$C$4,Translations!$D$1:$ZZ$1,0)) | C22: =INDEX(Translations!$D:$ZZ, MATCH(41,Translations!$A:$A,0), MATCH('Project Information'!$C$4,Translations!$D$1:$ZZ$1,0)) | D22: =INDEX(Translations!$D:$ZZ, MATCH(34,Translations!$A:$A,0), MATCH('Project Information'!$C$4,Translations!$D$1:$ZZ$1,0)) | E22: 15 | H22: =IF(OR(TRIM(F22)="Evet",TRIM(F22)="Yes"),E22,IF(G22="","",E22*G22)) | K22: =IFERROR(AND(OR(INDEX('Question Restrictions'!$D:$D,MATCH($B22,'Question Restrictions'!$C:$C,0))="All",ISNUMBER(SEARCH('Project Information'!$C$10,INDEX('Question Restrictions'!$D:$D,MATCH($B22,'Question Restrictions'!$C:$C,0))))),OR(INDEX('Question Restrictions'!$E:$E,MATCH($B22,'Question Restrictions'!$C:$C,0))="All",ISNUMBER(SEARCH('Project Information'!$C$11,INDEX('Question Restrictions'!$E:$E,MATCH($B22,'Question Restrictions'!$C:$C,0))))),OR(INDEX('Question Restrictions'!$F:$F,MATCH($B22,'Question Restrictions'!$C:$C,0))="All",ISNUMBER(SEARCH('Project Information'!$C$12,INDEX('Question Restrictions'!$F:$F,MATCH($B22,'Question Restrictions'!$C:$C,0))))),INDEX('Question Restrictions'!$G:$G,MATCH($B22,'Question Restrictions'!$C:$C,0))="Yes"),TRUE())
A23: 11 | B23: =INDEX(Translations!$D:$ZZ, MATCH(46,Translations!$A:$A,0), MATCH('Project Information'!$C$4,Translations!$D$1:$ZZ$1,0)) | C23: =INDEX(Translations!$D:$ZZ, MATCH(47,Translations!$A:$A,0), MATCH('Project Information'!$C$4,Translations!$D$1:$ZZ$1,0)) | D23: =INDEX(Translations!$D:$ZZ, MATCH(34,Translations!$A:$A,0), MATCH('Project Information'!$C$4,Translations!$D$1:$ZZ$1,0)) | E23: 5 | H23: =IF(OR(TRIM(F23)="Evet",TRIM(F23)="Yes"),E23,IF(G23="","",E23*G23)) | K23: =IFERROR(AND(OR(INDEX('Question Restrictions'!$D:$D,MATCH($B23,'Question Restrictions'!$C:$C,0))="All",ISNUMBER(SEARCH('Project Information'!$C$10,INDEX('Question Restrictions'!$D:$D,MATCH($B23,'Question Restrictions'!$C:$C,0))))),OR(INDEX('Question Restrictions'!$E:$E,MATCH($B23,'Question Restrictions'!$C:$C,0))="All",ISNUMBER(SEARCH('Project Information'!$C$11,INDEX('Question Restrictions'!$E:$E,MATCH($B23,'Question Restrictions'!$C:$C,0))))),OR(INDEX('Question Restrictions'!$F:$F,MATCH($B23,'Question Restrictions'!$C:$C,0))="All",ISNUMBER(SEARCH('Project Information'!$C$12,INDEX('Question Restrictions'!$F:$F,MATCH($B23,'Question Restrictions'!$C:$C,0))))),INDEX('Question Restrictions'!$G:$G,MATCH($B23,'Question Restrictions'!$C:$C,0))="Yes"),TRUE())
A24: 12 | B24: =INDEX(Translations!$D:$ZZ, MATCH(253,Translations!$A:$A,0), MATCH('Project Information'!$C$4,Translations!$D$1:$ZZ$1,0)) | C24: =INDEX(Translations!$D:$ZZ, MATCH(254,Translations!$A:$A,0), MATCH('Project Information'!$C$4,Translations!$D$1:$ZZ$1,0)) | D24: =INDEX(Translations!$D:$ZZ, MATCH(172,Translations!$A:$A,0), MATCH('Project Information'!$C$4,Translations!$D$1:$ZZ$1,0)) | H24: =IF(OR(TRIM(F24)="Evet",TRIM(F24)="Yes"),E24,IF(G24="","",E24*G24)) | K24: =IFERROR(AND(OR(INDEX('Question Restrictions'!$D:$D,MATCH($B24,'Question Restrictions'!$C:$C,0))="All",ISNUMBER(SEARCH('Project Information'!$C$10,INDEX('Question Restrictions'!$D:$D,MATCH($B24,'Question Restrictions'!$C:$C,0))))),OR(INDEX('Question Restrictions'!$E:$E,MATCH($B24,'Question Restrictions'!$C:$C,0))="All",ISNUMBER(SEARCH('Project Information'!$C$11,INDEX('Question Restrictions'!$E:$E,MATCH($B24,'Question Restrictions'!$C:$C,0))))),OR(INDEX('Question Restrictions'!$F:$F,MATCH($B24,'Question Restrictions'!$C:$C,0))="All",ISNUMBER(SEARCH('Project Information'!$C$12,INDEX('Question Restrictions'!$F:$F,MATCH($B24,'Question Restrictions'!$C:$C,0))))),INDEX('Question Restrictions'!$G:$G,MATCH($B24,'Question Restrictions'!$C:$C,0))="Yes"),TRUE())
A25: 13 | B25: =INDEX(Translations!$D:$ZZ, MATCH(257,Translations!$A:$A,0), MATCH('Project Information'!$C$4,Translations!$D$1:$ZZ$1,0)) | C25: =INDEX(Translations!$D:$ZZ, MATCH(258,Translations!$A:$A,0), MATCH('Project Information'!$C$4,Translations!$D$1:$ZZ$1,0)) | D25: =INDEX(Translations!$D:$ZZ, MATCH(172,Translations!$A:$A,0), MATCH('Project Information'!$C$4,Translations!$D$1:$ZZ$1,0)) | H25: =IF(OR(TRIM(F25)="Evet",TRIM(F25)="Yes"),E25,IF(G25="","",E25*G25)) | K25: =IFERROR(AND(OR(INDEX('Question Restrictions'!$D:$D,MATCH($B25,'Question Restrictions'!$C:$C,0))="All",ISNUMBER(SEARCH('Project Information'!$C$10,INDEX('Question Restrictions'!$D:$D,MATCH($B25,'Question Restrictions'!$C:$C,0))))),OR(INDEX('Question Restrictions'!$E:$E,MATCH($B25,'Question Restrictions'!$C:$C,0))="All",ISNUMBER(SEARCH('Project Information'!$C$11,INDEX('Question Restrictions'!$E:$E,MATCH($B25,'Question Restrictions'!$C:$C,0))))),OR(INDEX('Question Restrictions'!$F:$F,MATCH($B25,'Question Restrictions'!$C:$C,0))="All",ISNUMBER(SEARCH('Project Information'!$C$12,INDEX('Question Restrictions'!$F:$F,MATCH($B25,'Question Restrictions'!$C:$C,0))))),INDEX('Question Restrictions'!$G:$G,MATCH($B25,'Question Restrictions'!$C:$C,0))="Yes"),TRUE())
A26: 14 | B26: =INDEX(Translations!$D:$ZZ, MATCH(259,Translations!$A:$A,0), MATCH('Project Information'!$C$4,Translations!$D$1:$ZZ$1,0)) | C26: =INDEX(Translations!$D:$ZZ, MATCH(260,Translations!$A:$A,0), MATCH('Project Information'!$C$4,Translations!$D$1:$ZZ$1,0)) | D26: =INDEX(Translations!$D:$ZZ, MATCH(172,Translations!$A:$A,0), MATCH('Project Information'!$C$4,Translations!$D$1:$ZZ$1,0)) | H26: =IF(OR(TRIM(F26)="Evet",TRIM(F26)="Yes"),E26,IF(G26="","",E26*G26)) | K26: =IFERROR(AND(OR(INDEX('Question Restrictions'!$D:$D,MATCH($B26,'Question Restrictions'!$C:$C,0))="All",ISNUMBER(SEARCH('Project Information'!$C$10,INDEX('Question Restrictions'!$D:$D,MATCH($B26,'Question Restrictions'!$C:$C,0))))),OR(INDEX('Question Restrictions'!$E:$E,MATCH($B26,'Question Restrictions'!$C:$C,0))="All",ISNUMBER(SEARCH('Project Information'!$C$11,INDEX('Question Restrictions'!$E:$E,MATCH($B26,'Question Restrictions'!$C:$C,0))))),OR(INDEX('Question Restrictions'!$F:$F,MATCH($B26,'Question Restrictions'!$C:$C,0))="All",ISNUMBER(SEARCH('Project Information'!$C$12,INDEX('Question Restrictions'!$F:$F,MATCH($B26,'Question Restrictions'!$C:$C,0))))),INDEX('Question Restrictions'!$G:$G,MATCH($B26,'Question Restrictions'!$C:$C,0))="Yes"),TRUE())
A27: 15 | B27: =INDEX(Translations!$D:$ZZ, MATCH(261,Translations!$A:$A,0), MATCH('Project Information'!$C$4,Translations!$D$1:$ZZ$1,0)) | C27: =INDEX(Translations!$D:$ZZ, MATCH(262,Translations!$A:$A,0), MATCH('Project Information'!$C$4,Translations!$D$1:$ZZ$1,0)) | D27: =INDEX(Translations!$D:$ZZ, MATCH(172,Translations!$A:$A,0), MATCH('Project Information'!$C$4,Translations!$D$1:$ZZ$1,0)) | H27: =IF(OR(TRIM(F27)="Evet",TRIM(F27)="Yes"),E27,IF(G27="","",E27*G27)) | K27: =IFERROR(AND(OR(INDEX('Question Restrictions'!$D:$D,MATCH($B27,'Question Restrictions'!$C:$C,0))="All",ISNUMBER(SEARCH('Project Information'!$C$10,INDEX('Question Restrictions'!$D:$D,MATCH($B27,'Question Restrictions'!$C:$C,0))))),OR(INDEX('Question Restrictions'!$E:$E,MATCH($B27,'Question Restrictions'!$C:$C,0))="All",ISNUMBER(SEARCH('Project Information'!$C$11,INDEX('Question Restrictions'!$E:$E,MATCH($B27,'Question Restrictions'!$C:$C,0))))),OR(INDEX('Question Restrictions'!$F:$F,MATCH($B27,'Question Restrictions'!$C:$C,0))="All",ISNUMBER(SEARCH('Project Information'!$C$12,INDEX('Question Restrictions'!$F:$F,MATCH($B27,'Question Restrictions'!$C:$C,0))))),INDEX('Question Restrictions'!$G:$G,MATCH($B27,'Question Restrictions'!$C:$C,0))="Yes"),TRUE())
A28: 16 | B28: =INDEX(Translations!$D:$ZZ, MATCH(265,Translations!$A:$A,0), MATCH('Project Information'!$C$4,Translations!$D$1:$ZZ$1,0)) | C28: =INDEX(Translations!$D:$ZZ, MATCH(266,Translations!$A:$A,0), MATCH('Project Information'!$C$4,Translations!$D$1:$ZZ$1,0)) | D28: =INDEX(Translations!$D:$ZZ, MATCH(172,Translations!$A:$A,0), MATCH('Project Information'!$C$4,Translations!$D$1:$ZZ$1,0)) | H28: =IF(OR(TRIM(F28)="Evet",TRIM(F28)="Yes"),E28,IF(G28="","",E28*G28)) | K28: =IFERROR(AND(OR(INDEX('Question Restrictions'!$D:$D,MATCH($B28,'Question Restrictions'!$C:$C,0))="All",ISNUMBER(SEARCH('Project Information'!$C$10,INDEX('Question Restrictions'!$D:$D,MATCH($B28,'Question Restrictions'!$C:$C,0))))),OR(INDEX('Question Restrictions'!$E:$E,MATCH($B28,'Question Restrictions'!$C:$C,0))="All",ISNUMBER(SEARCH('Project Information'!$C$11,INDEX('Question Restrictions'!$E:$E,MATCH($B28,'Question Restrictions'!$C:$C,0))))),OR(INDEX('Question Restrictions'!$F:$F,MATCH($B28,'Question Restrictions'!$C:$C,0))="All",ISNUMBER(SEARCH('Project Information'!$C$12,INDEX('Question Restrictions'!$F:$F,MATCH($B28,'Question Restrictions'!$C:$C,0))))),INDEX('Question Restrictions'!$G:$G,MATCH($B28,'Question Restrictions'!$C:$C,0))="Yes"),TRUE())
A29: 17 | B29: =INDEX(Translations!$D:$ZZ, MATCH(185,Translations!$A:$A,0), MATCH('Project Information'!$C$4,Translations!$D$1:$ZZ$1,0)) | C29: =INDEX(Translations!$D:$ZZ, MATCH(186,Translations!$A:$A,0), MATCH('Project Information'!$C$4,Translations!$D$1:$ZZ$1,0)) | D29: =INDEX(Translations!$D:$ZZ, MATCH(27,Translations!$A:$A,0), MATCH('Project Information'!$C$4,Translations!$D$1:$ZZ$1,0)) | H29: =IF(OR(TRIM(F29)="Evet",TRIM(F29)="Yes"),E29,IF(G29="","",E29*G29)) | K29: =IFERROR(AND(OR(INDEX('Question Restrictions'!$D:$D,MATCH($B29,'Question Restrictions'!$C:$C,0))="All",ISNUMBER(SEARCH('Project Information'!$C$10,INDEX('Question Restrictions'!$D:$D,MATCH($B29,'Question Restrictions'!$C:$C,0))))),OR(INDEX('Question Restrictions'!$E:$E,MATCH($B29,'Question Restrictions'!$C:$C,0))="All",ISNUMBER(SEARCH('Project Information'!$C$11,INDEX('Question Restrictions'!$E:$E,MATCH($B29,'Question Restrictions'!$C:$C,0))))),OR(INDEX('Question Restrictions'!$F:$F,MATCH($B29,'Question Restrictions'!$C:$C,0))="All",ISNUMBER(SEARCH('Project Information'!$C$12,INDEX('Question Restrictions'!$F:$F,MATCH($B29,'Question Restrictions'!$C:$C,0))))),INDEX('Question Restrictions'!$G:$G,MATCH($B29,'Question Restrictions'!$C:$C,0))="Yes"),TRUE())
A30: 18 | B30: =INDEX(Translations!$D:$ZZ, MATCH(187,Translations!$A:$A,0), MATCH('Project Information'!$C$4,Translations!$D$1:$ZZ$1,0)) | C30: =INDEX(Translations!$D:$ZZ, MATCH(188,Translations!$A:$A,0), MATCH('Project Information'!$C$4,Translations!$D$1:$ZZ$1,0)) | D30: =INDEX(Translations!$D:$ZZ, MATCH(27,Translations!$A:$A,0), MATCH('Project Information'!$C$4,Translations!$D$1:$ZZ$1,0)) | H30: =IF(OR(TRIM(F30)="Evet",TRIM(F30)="Yes"),E30,IF(G30="","",E30*G30)) | K30: =IFERROR(AND(OR(INDEX('Question Restrictions'!$D:$D,MATCH($B30,'Question Restrictions'!$C:$C,0))="All",ISNUMBER(SEARCH('Project Information'!$C$10,INDEX('Question Restrictions'!$D:$D,MATCH($B30,'Question Restrictions'!$C:$C,0))))),OR(INDEX('Question Restrictions'!$E:$E,MATCH($B30,'Question Restrictions'!$C:$C,0))="All",ISNUMBER(SEARCH('Project Information'!$C$11,INDEX('Question Restrictions'!$E:$E,MATCH($B30,'Question Restrictions'!$C:$C,0))))),OR(INDEX('Question Restrictions'!$F:$F,MATCH($B30,'Question Restrictions'!$C:$C,0))="All",ISNUMBER(SEARCH('Project Information'!$C$12,INDEX('Question Restrictions'!$F:$F,MATCH($B30,'Question Restrictions'!$C:$C,0))))),INDEX('Question Restrictions'!$G:$G,MATCH($B30,'Question Restrictions'!$C:$C,0))="Yes"),TRUE())
A31: 19 | B31: =INDEX(Translations!$D:$ZZ, MATCH(183,Translations!$A:$A,0), MATCH('Project Information'!$C$4,Translations!$D$1:$ZZ$1,0)) | C31: =INDEX(Translations!$D:$ZZ, MATCH(184,Translations!$A:$A,0), MATCH('Project Information'!$C$4,Translations!$D$1:$ZZ$1,0)) | D31: =INDEX(Translations!$D:$ZZ, MATCH(172,Translations!$A:$A,0), MATCH('Project Information'!$C$4,Translations!$D$1:$ZZ$1,0)) | H31: =IF(OR(TRIM(F31)="Evet",TRIM(F31)="Yes"),E31,IF(G31="","",E31*G31)) | K31: =IFERROR(AND(OR(INDEX('Question Restrictions'!$D:$D,MATCH($B31,'Question Restrictions'!$C:$C,0))="All",ISNUMBER(SEARCH('Project Information'!$C$10,INDEX('Question Restrictions'!$D:$D,MATCH($B31,'Question Restrictions'!$C:$C,0))))),OR(INDEX('Question Restrictions'!$E:$E,MATCH($B31,'Question Restrictions'!$C:$C,0))="All",ISNUMBER(SEARCH('Project Information'!$C$11,INDEX('Question Restrictions'!$E:$E,MATCH($B31,'Question Restrictions'!$C:$C,0))))),OR(INDEX('Question Restrictions'!$F:$F,MATCH($B31,'Question Restrictions'!$C:$C,0))="All",ISNUMBER(SEARCH('Project Information'!$C$12,INDEX('Question Restrictions'!$F:$F,MATCH($B31,'Question Restrictions'!$C:$C,0))))),INDEX('Question Restrictions'!$G:$G,MATCH($B31,'Question Restrictions'!$C:$C,0))="Yes"),TRUE())
A32: 20 | B32: =INDEX(Translations!$D:$ZZ, MATCH(193,Translations!$A:$A,0), MATCH('Project Information'!$C$4,Translations!$D$1:$ZZ$1,0)) | C32: =INDEX(Translations!$D:$ZZ, MATCH(194,Translations!$A:$A,0), MATCH('Project Information'!$C$4,Translations!$D$1:$ZZ$1,0)) | D32: =INDEX(Translations!$D:$ZZ, MATCH(172,Translations!$A:$A,0), MATCH('Project Information'!$C$4,Translations!$D$1:$ZZ$1,0)) | H32: =IF(OR(TRIM(F32)="Evet",TRIM(F32)="Yes"),E32,IF(G32="","",E32*G32)) | K32: =IFERROR(AND(OR(INDEX('Question Restrictions'!$D:$D,MATCH($B32,'Question Restrictions'!$C:$C,0))="All",ISNUMBER(SEARCH('Project Information'!$C$10,INDEX('Question Restrictions'!$D:$D,MATCH($B32,'Question Restrictions'!$C:$C,0))))),OR(INDEX('Question Restrictions'!$E:$E,MATCH($B32,'Question Restrictions'!$C:$C,0))="All",ISNUMBER(SEARCH('Project Information'!$C$11,INDEX('Question Restrictions'!$E:$E,MATCH($B32,'Question Restrictions'!$C:$C,0))))),OR(INDEX('Question Restrictions'!$F:$F,MATCH($B32,'Question Restrictions'!$C:$C,0))="All",ISNUMBER(SEARCH('Project Information'!$C$12,INDEX('Question Restrictions'!$F:$F,MATCH($B32,'Question Restrictions'!$C:$C,0))))),INDEX('Question Restrictions'!$G:$G,MATCH($B32,'Question Restrictions'!$C:$C,0))="Yes"),TRUE())
A33: 21 | B33: =INDEX(Translations!$D:$ZZ, MATCH(181,Translations!$A:$A,0), MATCH('Project Information'!$C$4,Translations!$D$1:$ZZ$1,0)) | C33: =INDEX(Translations!$D:$ZZ, MATCH(182,Translations!$A:$A,0), MATCH('Project Information'!$C$4,Translations!$D$1:$ZZ$1,0)) | D33: =INDEX(Translations!$D:$ZZ, MATCH(27,Translations!$A:$A,0), MATCH('Project Information'!$C$4,Translations!$D$1:$ZZ$1,0)) | H33: =IF(OR(TRIM(F33)="Evet",TRIM(F33)="Yes"),E33,IF(G33="","",E33*G33)) | K33: =IFERROR(AND(OR(INDEX('Question Restrictions'!$D:$D,MATCH($B33,'Question Restrictions'!$C:$C,0))="All",ISNUMBER(SEARCH('Project Information'!$C$10,INDEX('Question Restrictions'!$D:$D,MATCH($B33,'Question Restrictions'!$C:$C,0))))),OR(INDEX('Question Restrictions'!$E:$E,MATCH($B33,'Question Restrictions'!$C:$C,0))="All",ISNUMBER(SEARCH('Project Information'!$C$11,INDEX('Question Restrictions'!$E:$E,MATCH($B33,'Question Restrictions'!$C:$C,0))))),OR(INDEX('Question Restrictions'!$F:$F,MATCH($B33,'Question Restrictions'!$C:$C,0))="All",ISNUMBER(SEARCH('Project Information'!$C$12,INDEX('Question Restrictions'!$F:$F,MATCH($B33,'Question Restrictions'!$C:$C,0))))),INDEX('Question Restrictions'!$G:$G,MATCH($B33,'Question Restrictions'!$C:$C,0))="Yes"),TRUE())
A34: 22 | B34: =INDEX(Translations!$D:$ZZ, MATCH(177,Translations!$A:$A,0), MATCH('Project Information'!$C$4,Translations!$D$1:$ZZ$1,0)) | C34: =INDEX(Translations!$D:$ZZ, MATCH(178,Translations!$A:$A,0), MATCH('Project Information'!$C$4,Translations!$D$1:$ZZ$1,0)) | D34: =INDEX(Translations!$D:$ZZ, MATCH(27,Translations!$A:$A,0), MATCH('Project Information'!$C$4,Translations!$D$1:$ZZ$1,0)) | H34: =IF(OR(TRIM(F34)="Evet",TRIM(F34)="Yes"),E34,IF(G34="","",E34*G34)) | K34: =IFERROR(AND(OR(INDEX('Question Restrictions'!$D:$D,MATCH($B34,'Question Restrictions'!$C:$C,0))="All",ISNUMBER(SEARCH('Project Information'!$C$10,INDEX('Question Restrictions'!$D:$D,MATCH($B34,'Question Restrictions'!$C:$C,0))))),OR(INDEX('Question Restrictions'!$E:$E,MATCH($B34,'Question Restrictions'!$C:$C,0))="All",ISNUMBER(SEARCH('Project Information'!$C$11,INDEX('Question Restrictions'!$E:$E,MATCH($B34,'Question Restrictions'!$C:$C,0))))),OR(INDEX('Question Restrictions'!$F:$F,MATCH($B34,'Question Restrictions'!$C:$C,0))="All",ISNUMBER(SEARCH('Project Information'!$C$12,INDEX('Question Restrictions'!$F:$F,MATCH($B34,'Question Restrictions'!$C:$C,0))))),INDEX('Question Restrictions'!$G:$G,MATCH($B34,'Question Restrictions'!$C:$C,0))="Yes"),TRUE())
A35: 23 | B35: =INDEX(Translations!$D:$ZZ, MATCH(179,Translations!$A:$A,0), MATCH('Project Information'!$C$4,Translations!$D$1:$ZZ$1,0)) | C35: =INDEX(Translations!$D:$ZZ, MATCH(180,Translations!$A:$A,0), MATCH('Project Information'!$C$4,Translations!$D$1:$ZZ$1,0)) | D35: =INDEX(Translations!$D:$ZZ, MATCH(172,Translations!$A:$A,0), MATCH('Project Information'!$C$4,Translations!$D$1:$ZZ$1,0)) | H35: =IF(OR(TRIM(F35)="Evet",TRIM(F35)="Yes"),E35,IF(G35="","",E35*G35)) | K35: =IFERROR(AND(OR(INDEX('Question Restrictions'!$D:$D,MATCH($B35,'Question Restrictions'!$C:$C,0))="All",ISNUMBER(SEARCH('Project Information'!$C$10,INDEX('Question Restrictions'!$D:$D,MATCH($B35,'Question Restrictions'!$C:$C,0))))),OR(INDEX('Question Restrictions'!$E:$E,MATCH($B35,'Question Restrictions'!$C:$C,0))="All",ISNUMBER(SEARCH('Project Information'!$C$11,INDEX('Question Restrictions'!$E:$E,MATCH($B35,'Question Restrictions'!$C:$C,0))))),OR(INDEX('Question Restrictions'!$F:$F,MATCH($B35,'Question Restrictions'!$C:$C,0))="All",ISNUMBER(SEARCH('Project Information'!$C$12,INDEX('Question Restrictions'!$F:$F,MATCH($B35,'Question Restrictions'!$C:$C,0))))),INDEX('Question Restrictions'!$G:$G,MATCH($B35,'Question Restrictions'!$C:$C,0))="Yes"),TRUE())
A36: 24 | B36: =INDEX(Translations!$D:$ZZ, MATCH(189,Translations!$A:$A,0), MATCH('Project Information'!$C$4,Translations!$D$1:$ZZ$1,0)) | C36: =INDEX(Translations!$D:$ZZ, MATCH(190,Translations!$A:$A,0), MATCH('Project Information'!$C$4,Translations!$D$1:$ZZ$1,0)) | D36: =INDEX(Translations!$D:$ZZ, MATCH(172,Translations!$A:$A,0), MATCH('Project Information'!$C$4,Translations!$D$1:$ZZ$1,0)) | H36: =IF(OR(TRIM(F36)="Evet",TRIM(F36)="Yes"),E36,IF(G36="","",E36*G36)) | K36: =IFERROR(AND(OR(INDEX('Question Restrictions'!$D:$D,MATCH($B36,'Question Restrictions'!$C:$C,0))="All",ISNUMBER(SEARCH('Project Information'!$C$10,INDEX('Question Restrictions'!$D:$D,MATCH($B36,'Question Restrictions'!$C:$C,0))))),OR(INDEX('Question Restrictions'!$E:$E,MATCH($B36,'Question Restrictions'!$C:$C,0))="All",ISNUMBER(SEARCH('Project Information'!$C$11,INDEX('Question Restrictions'!$E:$E,MATCH($B36,'Question Restrictions'!$C:$C,0))))),OR(INDEX('Question Restrictions'!$F:$F,MATCH($B36,'Question Restrictions'!$C:$C,0))="All",ISNUMBER(SEARCH('Project Information'!$C$12,INDEX('Question Restrictions'!$F:$F,MATCH($B36,'Question Restrictions'!$C:$C,0))))),INDEX('Question Restrictions'!$G:$G,MATCH($B36,'Question Restrictions'!$C:$C,0))="Yes"),TRUE())
A37: 25 | B37: =INDEX(Translations!$D:$ZZ, MATCH(191,Translations!$A:$A,0), MATCH('Project Information'!$C$4,Translations!$D$1:$ZZ$1,0)) | C37: =INDEX(Translations!$D:$ZZ, MATCH(192,Translations!$A:$A,0), MATCH('Project Information'!$C$4,Translations!$D$1:$ZZ$1,0)) | D37: =INDEX(Translations!$D:$ZZ, MATCH(27,Translations!$A:$A,0), MATCH('Project Information'!$C$4,Translations!$D$1:$ZZ$1,0)) | H37: =IF(OR(TRIM(F37)="Evet",TRIM(F37)="Yes"),E37,IF(G37="","",E37*G37)) | K37: =IFERROR(AND(OR(INDEX('Question Restrictions'!$D:$D,MATCH($B37,'Question Restrictions'!$C:$C,0))="All",ISNUMBER(SEARCH('Project Information'!$C$10,INDEX('Question Restrictions'!$D:$D,MATCH($B37,'Question Restrictions'!$C:$C,0))))),OR(INDEX('Question Restrictions'!$E:$E,MATCH($B37,'Question Restrictions'!$C:$C,0))="All",ISNUMBER(SEARCH('Project Information'!$C$11,INDEX('Question Restrictions'!$E:$E,MATCH($B37,'Question Restrictions'!$C:$C,0))))),OR(INDEX('Question Restrictions'!$F:$F,MATCH($B37,'Question Restrictions'!$C:$C,0))="All",ISNUMBER(SEARCH('Project Information'!$C$12,INDEX('Question Restrictions'!$F:$F,MATCH($B37,'Question Restrictions'!$C:$C,0))))),INDEX('Question Restrictions'!$G:$G,MATCH($B37,'Question Restrictions'!$C:$C,0))="Yes"),TRUE())
A38: 26 | B38: =INDEX(Translations!$D:$ZZ, MATCH(195,Translations!$A:$A,0), MATCH('Project Information'!$C$4,Translations!$D$1:$ZZ$1,0)) | C38: =INDEX(Translations!$D:$ZZ, MATCH(196,Translations!$A:$A,0), MATCH('Project Information'!$C$4,Translations!$D$1:$ZZ$1,0)) | D38: =INDEX(Translations!$D:$ZZ, MATCH(172,Translations!$A:$A,0), MATCH('Project Information'!$C$4,Translations!$D$1:$ZZ$1,0)) | H38: =IF(OR(TRIM(F38)="Evet",TRIM(F38)="Yes"),E38,IF(G38="","",E38*G38)) | K38: =IFERROR(AND(OR(INDEX('Question Restrictions'!$D:$D,MATCH($B38,'Question Restrictions'!$C:$C,0))="All",ISNUMBER(SEARCH('Project Information'!$C$10,INDEX('Question Restrictions'!$D:$D,MATCH($B38,'Question Restrictions'!$C:$C,0))))),OR(INDEX('Question Restrictions'!$E:$E,MATCH($B38,'Question Restrictions'!$C:$C,0))="All",ISNUMBER(SEARCH('Project Information'!$C$11,INDEX('Question Restrictions'!$E:$E,MATCH($B38,'Question Restrictions'!$C:$C,0))))),OR(INDEX('Question Restrictions'!$F:$F,MATCH($B38,'Question Restrictions'!$C:$C,0))="All",ISNUMBER(SEARCH('Project Information'!$C$12,INDEX('Question Restrictions'!$F:$F,MATCH($B38,'Question Restrictions'!$C:$C,0))))),INDEX('Question Restrictions'!$G:$G,MATCH($B38,'Question Restrictions'!$C:$C,0))="Yes"),TRUE())
A39: 27 | B39: =INDEX(Translations!$D:$ZZ, MATCH(197,Translations!$A:$A,0), MATCH('Project Information'!$C$4,Translations!$D$1:$ZZ$1,0)) | C39: =INDEX(Translations!$D:$ZZ, MATCH(198,Translations!$A:$A,0), MATCH('Project Information'!$C$4,Translations!$D$1:$ZZ$1,0)) | D39: =INDEX(Translations!$D:$ZZ, MATCH(172,Translations!$A:$A,0), MATCH('Project Information'!$C$4,Translations!$D$1:$ZZ$1,0)) | H39: =IF(OR(TRIM(F39)="Evet",TRIM(F39)="Yes"),E39,IF(G39="","",E39*G39)) | K39: =IFERROR(AND(OR(INDEX('Question Restrictions'!$D:$D,MATCH($B39,'Question Restrictions'!$C:$C,0))="All",ISNUMBER(SEARCH('Project Information'!$C$10,INDEX('Question Restrictions'!$D:$D,MATCH($B39,'Question Restrictions'!$C:$C,0))))),OR(INDEX('Question Restrictions'!$E:$E,MATCH($B39,'Question Restrictions'!$C:$C,0))="All",ISNUMBER(SEARCH('Project Information'!$C$11,INDEX('Question Restrictions'!$E:$E,MATCH($B39,'Question Restrictions'!$C:$C,0))))),OR(INDEX('Question Restrictions'!$F:$F,MATCH($B39,'Question Restrictions'!$C:$C,0))="All",ISNUMBER(SEARCH('Project Information'!$C$12,INDEX('Question Restrictions'!$F:$F,MATCH($B39,'Question Restrictions'!$C:$C,0))))),INDEX('Question Restrictions'!$G:$G,MATCH($B39,'Question Restrictions'!$C:$C,0))="Yes"),TRUE())
A40: 28 | B40: =INDEX(Translations!$D:$ZZ, MATCH(199,Translations!$A:$A,0), MATCH('Project Information'!$C$4,Translations!$D$1:$ZZ$1,0)) | C40: =INDEX(Translations!$D:$ZZ, MATCH(200,Translations!$A:$A,0), MATCH('Project Information'!$C$4,Translations!$D$1:$ZZ$1,0)) | D40: =INDEX(Translations!$D:$ZZ, MATCH(172,Translations!$A:$A,0), MATCH('Project Information'!$C$4,Translations!$D$1:$ZZ$1,0)) | H40: =IF(OR(TRIM(F40)="Evet",TRIM(F40)="Yes"),E40,IF(G40="","",E40*G40)) | K40: =IFERROR(AND(OR(INDEX('Question Restrictions'!$D:$D,MATCH($B40,'Question Restrictions'!$C:$C,0))="All",ISNUMBER(SEARCH('Project Information'!$C$10,INDEX('Question Restrictions'!$D:$D,MATCH($B40,'Question Restrictions'!$C:$C,0))))),OR(INDEX('Question Restrictions'!$E:$E,MATCH($B40,'Question Restrictions'!$C:$C,0))="All",ISNUMBER(SEARCH('Project Information'!$C$11,INDEX('Question Restrictions'!$E:$E,MATCH($B40,'Question Restrictions'!$C:$C,0))))),OR(INDEX('Question Restrictions'!$F:$F,MATCH($B40,'Question Restrictions'!$C:$C,0))="All",ISNUMBER(SEARCH('Project Information'!$C$12,INDEX('Question Restrictions'!$F:$F,MATCH($B40,'Question Restrictions'!$C:$C,0))))),INDEX('Question Restrictions'!$G:$G,MATCH($B40,'Question Restrictions'!$C:$C,0))="Yes"),TRUE())
A41: 29 | B41: =INDEX(Translations!$D:$ZZ, MATCH(255,Translations!$A:$A,0), MATCH('Project Information'!$C$4,Translations!$D$1:$ZZ$1,0)) | C41: =INDEX(Translations!$D:$ZZ, MATCH(256,Translations!$A:$A,0), MATCH('Project Information'!$C$4,Translations!$D$1:$ZZ$1,0)) | D41: =INDEX(Translations!$D:$ZZ, MATCH(172,Translations!$A:$A,0), MATCH('Project Information'!$C$4,Translations!$D$1:$ZZ$1,0)) | H41: =IF(OR(TRIM(F41)="Evet",TRIM(F41)="Yes"),E41,IF(G41="","",E41*G41)) | K41: =IFERROR(AND(OR(INDEX('Question Restrictions'!$D:$D,MATCH($B41,'Question Restrictions'!$C:$C,0))="All",ISNUMBER(SEARCH('Project Information'!$C$10,INDEX('Question Restrictions'!$D:$D,MATCH($B41,'Question Restrictions'!$C:$C,0))))),OR(INDEX('Question Restrictions'!$E:$E,MATCH($B41,'Question Restrictions'!$C:$C,0))="All",ISNUMBER(SEARCH('Project Information'!$C$11,INDEX('Question Restrictions'!$E:$E,MATCH($B41,'Question Restrictions'!$C:$C,0))))),OR(INDEX('Question Restrictions'!$F:$F,MATCH($B41,'Question Restrictions'!$C:$C,0))="All",ISNUMBER(SEARCH('Project Information'!$C$12,INDEX('Question Restrictions'!$F:$F,MATCH($B41,'Question Restrictions'!$C:$C,0))))),INDEX('Question Restrictions'!$G:$G,MATCH($B41,'Question Restrictions'!$C:$C,0))="Yes"),TRUE())
A42: 30 | B42: =INDEX(Translations!$D:$ZZ, MATCH(203,Translations!$A:$A,0), MATCH('Project Information'!$C$4,Translations!$D$1:$ZZ$1,0)) | C42: =INDEX(Translations!$D:$ZZ, MATCH(204,Translations!$A:$A,0), MATCH('Project Information'!$C$4,Translations!$D$1:$ZZ$1,0)) | D42: =INDEX(Translations!$D:$ZZ, MATCH(172,Translations!$A:$A,0), MATCH('Project Information'!$C$4,Translations!$D$1:$ZZ$1,0)) | H42: =IF(OR(TRIM(F42)="Evet",TRIM(F42)="Yes"),E42,IF(G42="","",E42*G42)) | K42: =IFERROR(AND(OR(INDEX('Question Restrictions'!$D:$D,MATCH($B42,'Question Restrictions'!$C:$C,0))="All",ISNUMBER(SEARCH('Project Information'!$C$10,INDEX('Question Restrictions'!$D:$D,MATCH($B42,'Question Restrictions'!$C:$C,0))))),OR(INDEX('Question Restrictions'!$E:$E,MATCH($B42,'Question Restrictions'!$C:$C,0))="All",ISNUMBER(SEARCH('Project Information'!$C$11,INDEX('Question Restrictions'!$E:$E,MATCH($B42,'Question Restrictions'!$C:$C,0))))),OR(INDEX('Question Restrictions'!$F:$F,MATCH($B42,'Question Restrictions'!$C:$C,0))="All",ISNUMBER(SEARCH('Project Information'!$C$12,INDEX('Question Restrictions'!$F:$F,MATCH($B42,'Question Restrictions'!$C:$C,0))))),INDEX('Question Restrictions'!$G:$G,MATCH($B42,'Question Restrictions'!$C:$C,0))="Yes"),TRUE())
A43: 31 | B43: =INDEX(Translations!$D:$ZZ, MATCH(217,Translations!$A:$A,0), MATCH('Project Information'!$C$4,Translations!$D$1:$ZZ$1,0)) | C43: =INDEX(Translations!$D:$ZZ, MATCH(218,Translations!$A:$A,0), MATCH('Project Information'!$C$4,Translations!$D$1:$ZZ$1,0)) | D43: =INDEX(Translations!$D:$ZZ, MATCH(172,Translations!$A:$A,0), MATCH('Project Information'!$C$4,Translations!$D$1:$ZZ$1,0)) | H43: =IF(OR(TRIM(F43)="Evet",TRIM(F43)="Yes"),E43,IF(G43="","",E43*G43)) | K43: =IFERROR(AND(OR(INDEX('Question Restrictions'!$D:$D,MATCH($B43,'Question Restrictions'!$C:$C,0))="All",ISNUMBER(SEARCH('Project Information'!$C$10,INDEX('Question Restrictions'!$D:$D,MATCH($B43,'Question Restrictions'!$C:$C,0))))),OR(INDEX('Question Restrictions'!$E:$E,MATCH($B43,'Question Restrictions'!$C:$C,0))="All",ISNUMBER(SEARCH('Project Information'!$C$11,INDEX('Question Restrictions'!$E:$E,MATCH($B43,'Question Restrictions'!$C:$C,0))))),OR(INDEX('Question Restrictions'!$F:$F,MATCH($B43,'Question Restrictions'!$C:$C,0))="All",ISNUMBER(SEARCH('Project Information'!$C$12,INDEX('Question Restrictions'!$F:$F,MATCH($B43,'Question Restrictions'!$C:$C,0))))),INDEX('Question Restrictions'!$G:$G,MATCH($B43,'Question Restrictions'!$C:$C,0))="Yes"),TRUE())
A44: 32 | B44: =INDEX(Translations!$D:$ZZ, MATCH(219,Translations!$A:$A,0), MATCH('Project Information'!$C$4,Translations!$D$1:$ZZ$1,0)) | C44: =INDEX(Translations!$D:$ZZ, MATCH(220,Translations!$A:$A,0), MATCH('Project Information'!$C$4,Translations!$D$1:$ZZ$1,0)) | D44: =INDEX(Translations!$D:$ZZ, MATCH(172,Translations!$A:$A,0), MATCH('Project Information'!$C$4,Translations!$D$1:$ZZ$1,0)) | H44: =IF(OR(TRIM(F44)="Evet",TRIM(F44)="Yes"),E44,IF(G44="","",E44*G44)) | K44: =IFERROR(AND(OR(INDEX('Question Restrictions'!$D:$D,MATCH($B44,'Question Restrictions'!$C:$C,0))="All",ISNUMBER(SEARCH('Project Information'!$C$10,INDEX('Question Restrictions'!$D:$D,MATCH($B44,'Question Restrictions'!$C:$C,0))))),OR(INDEX('Question Restrictions'!$E:$E,MATCH($B44,'Question Restrictions'!$C:$C,0))="All",ISNUMBER(SEARCH('Project Information'!$C$11,INDEX('Question Restrictions'!$E:$E,MATCH($B44,'Question Restrictions'!$C:$C,0))))),OR(INDEX('Question Restrictions'!$F:$F,MATCH($B44,'Question Restrictions'!$C:$C,0))="All",ISNUMBER(SEARCH('Project Information'!$C$12,INDEX('Question Restrictions'!$F:$F,MATCH($B44,'Question Restrictions'!$C:$C,0))))),INDEX('Question Restrictions'!$G:$G,MATCH($B44,'Question Restrictions'!$C:$C,0))="Yes"),TRUE())
A45: 33 | B45: =INDEX(Translations!$D:$ZZ, MATCH(221,Translations!$A:$A,0), MATCH('Project Information'!$C$4,Translations!$D$1:$ZZ$1,0)) | C45: =INDEX(Translations!$D:$ZZ, MATCH(220,Translations!$A:$A,0), MATCH('Project Information'!$C$4,Translations!$D$1:$ZZ$1,0)) | D45: =INDEX(Translations!$D:$ZZ, MATCH(172,Translations!$A:$A,0), MATCH('Project Information'!$C$4,Translations!$D$1:$ZZ$1,0)) | H45: =IF(OR(TRIM(F45)="Evet",TRIM(F45)="Yes"),E45,IF(G45="","",E45*G45)) | K45: =IFERROR(AND(OR(INDEX('Question Restrictions'!$D:$D,MATCH($B45,'Question Restrictions'!$C:$C,0))="All",ISNUMBER(SEARCH('Project Information'!$C$10,INDEX('Question Restrictions'!$D:$D,MATCH($B45,'Question Restrictions'!$C:$C,0))))),OR(INDEX('Question Restrictions'!$E:$E,MATCH($B45,'Question Restrictions'!$C:$C,0))="All",ISNUMBER(SEARCH('Project Information'!$C$11,INDEX('Question Restrictions'!$E:$E,MATCH($B45,'Question Restrictions'!$C:$C,0))))),OR(INDEX('Question Restrictions'!$F:$F,MATCH($B45,'Question Restrictions'!$C:$C,0))="All",ISNUMBER(SEARCH('Project Information'!$C$12,INDEX('Question Restrictions'!$F:$F,MATCH($B45,'Question Restrictions'!$C:$C,0))))),INDEX('Question Restrictions'!$G:$G,MATCH($B45,'Question Restrictions'!$C:$C,0))="Yes"),TRUE())
A46: 34 | B46: =INDEX(Translations!$D:$ZZ, MATCH(222,Translations!$A:$A,0), MATCH('Project Information'!$C$4,Translations!$D$1:$ZZ$1,0)) | C46: =INDEX(Translations!$D:$ZZ, MATCH(223,Translations!$A:$A,0), MATCH('Project Information'!$C$4,Translations!$D$1:$ZZ$1,0)) | D46: =INDEX(Translations!$D:$ZZ, MATCH(27,Translations!$A:$A,0), MATCH('Project Information'!$C$4,Translations!$D$1:$ZZ$1,0)) | H46: =IF(OR(TRIM(F46)="Evet",TRIM(F46)="Yes"),E46,IF(G46="","",E46*G46)) | K46: =IFERROR(AND(OR(INDEX('Question Restrictions'!$D:$D,MATCH($B46,'Question Restrictions'!$C:$C,0))="All",ISNUMBER(SEARCH('Project Information'!$C$10,INDEX('Question Restrictions'!$D:$D,MATCH($B46,'Question Restrictions'!$C:$C,0))))),OR(INDEX('Question Restrictions'!$E:$E,MATCH($B46,'Question Restrictions'!$C:$C,0))="All",ISNUMBER(SEARCH('Project Information'!$C$11,INDEX('Question Restrictions'!$E:$E,MATCH($B46,'Question Restrictions'!$C:$C,0))))),OR(INDEX('Question Restrictions'!$F:$F,MATCH($B46,'Question Restrictions'!$C:$C,0))="All",ISNUMBER(SEARCH('Project Information'!$C$12,INDEX('Question Restrictions'!$F:$F,MATCH($B46,'Question Restrictions'!$C:$C,0))))),INDEX('Question Restrictions'!$G:$G,MATCH($B46,'Question Restrictions'!$C:$C,0))="Yes"),TRUE())
A47: 35 | B47: =INDEX(Translations!$D:$ZZ, MATCH(234,Translations!$A:$A,0), MATCH('Project Information'!$C$4,Translations!$D$1:$ZZ$1,0)) | C47: =INDEX(Translations!$D:$ZZ, MATCH(194,Translations!$A:$A,0), MATCH('Project Information'!$C$4,Translations!$D$1:$ZZ$1,0)) | D47: =INDEX(Translations!$D:$ZZ, MATCH(172,Translations!$A:$A,0), MATCH('Project Information'!$C$4,Translations!$D$1:$ZZ$1,0)) | H47: =IF(OR(TRIM(F47)="Evet",TRIM(F47)="Yes"),E47,IF(G47="","",E47*G47)) | K47: =IFERROR(AND(OR(INDEX('Question Restrictions'!$D:$D,MATCH($B47,'Question Restrictions'!$C:$C,0))="All",ISNUMBER(SEARCH('Project Information'!$C$10,INDEX('Question Restrictions'!$D:$D,MATCH($B47,'Question Restrictions'!$C:$C,0))))),OR(INDEX('Question Restrictions'!$E:$E,MATCH($B47,'Question Restrictions'!$C:$C,0))="All",ISNUMBER(SEARCH('Project Information'!$C$11,INDEX('Question Restrictions'!$E:$E,MATCH($B47,'Question Restrictions'!$C:$C,0))))),OR(INDEX('Question Restrictions'!$F:$F,MATCH($B47,'Question Restrictions'!$C:$C,0))="All",ISNUMBER(SEARCH('Project Information'!$C$12,INDEX('Question Restrictions'!$F:$F,MATCH($B47,'Question Restrictions'!$C:$C,0))))),INDEX('Question Restrictions'!$G:$G,MATCH($B47,'Question Restrictions'!$C:$C,0))="Yes"),TRUE())
A48: 36 | B48: =INDEX(Translations!$D:$ZZ, MATCH(244,Translations!$A:$A,0), MATCH('Project Information'!$C$4,Translations!$D$1:$ZZ$1,0)) | C48: =INDEX(Translations!$D:$ZZ, MATCH(245,Translations!$A:$A,0), MATCH('Project Information'!$C$4,Translations!$D$1:$ZZ$1,0)) | D48: =INDEX(Translations!$D:$ZZ, MATCH(172,Translations!$A:$A,0), MATCH('Project Information'!$C$4,Translations!$D$1:$ZZ$1,0)) | H48: =IF(OR(TRIM(F48)="Evet",TRIM(F48)="Yes"),E48,IF(G48="","",E48*G48)) | K48: =IFERROR(AND(OR(INDEX('Question Restrictions'!$D:$D,MATCH($B48,'Question Restrictions'!$C:$C,0))="All",ISNUMBER(SEARCH('Project Information'!$C$10,INDEX('Question Restrictions'!$D:$D,MATCH($B48,'Question Restrictions'!$C:$C,0))))),OR(INDEX('Question Restrictions'!$E:$E,MATCH($B48,'Question Restrictions'!$C:$C,0))="All",ISNUMBER(SEARCH('Project Information'!$C$11,INDEX('Question Restrictions'!$E:$E,MATCH($B48,'Question Restrictions'!$C:$C,0))))),OR(INDEX('Question Restrictions'!$F:$F,MATCH($B48,'Question Restrictions'!$C:$C,0))="All",ISNUMBER(SEARCH('Project Information'!$C$12,INDEX('Question Restrictions'!$F:$F,MATCH($B48,'Question Restrictions'!$C:$C,0))))),INDEX('Question Restrictions'!$G:$G,MATCH($B48,'Question Restrictions'!$C:$C,0))="Yes"),TRUE())
A49: 37 | B49: =INDEX(Translations!$D:$ZZ, MATCH(263,Translations!$A:$A,0), MATCH('Project Information'!$C$4,Translations!$D$1:$ZZ$1,0)) | C49: =INDEX(Translations!$D:$ZZ, MATCH(264,Translations!$A:$A,0), MATCH('Project Information'!$C$4,Translations!$D$1:$ZZ$1,0)) | D49: =INDEX(Translations!$D:$ZZ, MATCH(172,Translations!$A:$A,0), MATCH('Project Information'!$C$4,Translations!$D$1:$ZZ$1,0)) | H49: =IF(OR(TRIM(F49)="Evet",TRIM(F49)="Yes"),E49,IF(G49="","",E49*G49)) | K49: =IFERROR(AND(OR(INDEX('Question Restrictions'!$D:$D,MATCH($B49,'Question Restrictions'!$C:$C,0))="All",ISNUMBER(SEARCH('Project Information'!$C$10,INDEX('Question Restrictions'!$D:$D,MATCH($B49,'Question Restrictions'!$C:$C,0))))),OR(INDEX('Question Restrictions'!$E:$E,MATCH($B49,'Question Restrictions'!$C:$C,0))="All",ISNUMBER(SEARCH('Project Information'!$C$11,INDEX('Question Restrictions'!$E:$E,MATCH($B49,'Question Restrictions'!$C:$C,0))))),OR(INDEX('Question Restrictions'!$F:$F,MATCH($B49,'Question Restrictions'!$C:$C,0))="All",ISNUMBER(SEARCH('Project Information'!$C$12,INDEX('Question Restrictions'!$F:$F,MATCH($B49,'Question Restrictions'!$C:$C,0))))),INDEX('Question Restrictions'!$G:$G,MATCH($B49,'Question Restrictions'!$C:$C,0))="Yes"),TRUE())
A50: 38 | B50: =INDEX(Translations!$D:$ZZ, MATCH(1025,Translations!$A:$A,0), MATCH('Project Information'!$C$4,Translations!$D$1:$ZZ$1,0)) | C50: =INDEX(Translations!$D:$ZZ, MATCH(1026,Translations!$A:$A,0), MATCH('Project Information'!$C$4,Translations!$D$1:$ZZ$1,0)) | D50: =INDEX(Translations!$D:$ZZ, MATCH(34,Translations!$A:$A,0), MATCH('Project Information'!$C$4,Translations!$D$1:$ZZ$1,0)) | E50: 10 | F50: Evet | H50: =IF(OR(TRIM(F50)="Evet",TRIM(F50)="Yes"),E50,IF(G50="","",E50*G50)) | K50: =IFERROR(AND(OR(INDEX('Question Restrictions'!$D:$D,MATCH($B50,'Question Restrictions'!$C:$C,0))="All",ISNUMBER(SEARCH('Project Information'!$C$10,INDEX('Question Restrictions'!$D:$D,MATCH($B50,'Question Restrictions'!$C:$C,0))))),OR(INDEX('Question Restrictions'!$E:$E,MATCH($B50,'Question Restrictions'!$C:$C,0))="All",ISNUMBER(SEARCH('Project Information'!$C$11,INDEX('Question Restrictions'!$E:$E,MATCH($B50,'Question Restrictions'!$C:$C,0))))),OR(INDEX('Question Restrictions'!$F:$F,MATCH($B50,'Question Restrictions'!$C:$C,0))="All",ISNUMBER(SEARCH('Project Information'!$C$12,INDEX('Question Restrictions'!$F:$F,MATCH($B50,'Question Restrictions'!$C:$C,0))))),INDEX('Question Restrictions'!$G:$G,MATCH($B50,'Question Restrictions'!$C:$C,0))="Yes"),TRUE())
A51: 39 | B51: =INDEX(Translations!$D:$ZZ, MATCH(1027,Translations!$A:$A,0), MATCH('Project Information'!$C$4,Translations!$D$1:$ZZ$1,0)) | C51: =INDEX(Translations!$D:$ZZ, MATCH(1028,Translations!$A:$A,0), MATCH('Project Information'!$C$4,Translations!$D$1:$ZZ$1,0)) | D51: =INDEX(Translations!$D:$ZZ, MATCH(34,Translations!$A:$A,0), MATCH('Project Information'!$C$4,Translations!$D$1:$ZZ$1,0)) | E51: 5 | F51: Hayır | H51: =IF(OR(TRIM(F51)="Evet",TRIM(F51)="Yes"),E51,IF(G51="","",E51*G51)) | K51: =IFERROR(AND(OR(INDEX('Question Restrictions'!$D:$D,MATCH($B51,'Question Restrictions'!$C:$C,0))="All",ISNUMBER(SEARCH('Project Information'!$C$10,INDEX('Question Restrictions'!$D:$D,MATCH($B51,'Question Restrictions'!$C:$C,0))))),OR(INDEX('Question Restrictions'!$E:$E,MATCH($B51,'Question Restrictions'!$C:$C,0))="All",ISNUMBER(SEARCH('Project Information'!$C$11,INDEX('Question Restrictions'!$E:$E,MATCH($B51,'Question Restrictions'!$C:$C,0))))),OR(INDEX('Question Restrictions'!$F:$F,MATCH($B51,'Question Restrictions'!$C:$C,0))="All",ISNUMBER(SEARCH('Project Information'!$C$12,INDEX('Question Restrictions'!$F:$F,MATCH($B51,'Question Restrictions'!$C:$C,0))))),INDEX('Question Restrictions'!$G:$G,MATCH($B51,'Question Restrictions'!$C:$C,0))="Yes"),TRUE())
A52: 40 | B52: =INDEX(Translations!$D:$ZZ, MATCH(1029,Translations!$A:$A,0), MATCH('Project Information'!$C$4,Translations!$D$1:$ZZ$1,0)) | C52: =INDEX(Translations!$D:$ZZ, MATCH(1030,Translations!$A:$A,0), MATCH('Project Information'!$C$4,Translations!$D$1:$ZZ$1,0)) | D52: =INDEX(Translations!$D:$ZZ, MATCH(27,Translations!$A:$A,0), MATCH('Project Information'!$C$4,Translations!$D$1:$ZZ$1,0)) | E52: 5 | G52: 2 | H52: =IF(OR(TRIM(F52)="Evet",TRIM(F52)="Yes"),E52,IF(G52="","",E52*G52)) | K52: =IFERROR(AND(OR(INDEX('Question Restrictions'!$D:$D,MATCH($B52,'Question Restrictions'!$C:$C,0))="All",ISNUMBER(SEARCH('Project Information'!$C$10,INDEX('Question Restrictions'!$D:$D,MATCH($B52,'Question Restrictions'!$C:$C,0))))),OR(INDEX('Question Restrictions'!$E:$E,MATCH($B52,'Question Restrictions'!$C:$C,0))="All",ISNUMBER(SEARCH('Project Information'!$C$11,INDEX('Question Restrictions'!$E:$E,MATCH($B52,'Question Restrictions'!$C:$C,0))))),OR(INDEX('Question Restrictions'!$F:$F,MATCH($B52,'Question Restrictions'!$C:$C,0))="All",ISNUMBER(SEARCH('Project Information'!$C$12,INDEX('Question Restrictions'!$F:$F,MATCH($B52,'Question Restrictions'!$C:$C,0))))),INDEX('Question Restrictions'!$G:$G,MATCH($B52,'Question Restrictions'!$C:$C,0))="Yes"),TRUE())
A53: 41 | B53: =INDEX(Translations!$D:$ZZ, MATCH(1031,Translations!$A:$A,0), MATCH('Project Information'!$C$4,Translations!$D$1:$ZZ$1,0)) | C53: =INDEX(Translations!$D:$ZZ, MATCH(1032,Translations!$A:$A,0), MATCH('Project Information'!$C$4,Translations!$D$1:$ZZ$1,0)) | D53: =INDEX(Translations!$D:$ZZ, MATCH(34,Translations!$A:$A,0), MATCH('Project Information'!$C$4,Translations!$D$1:$ZZ$1,0)) | E53: 10 | F53: Evet | H53: =IF(OR(TRIM(F53)="Evet",TRIM(F53)="Yes"),E53,IF(G53="","",E53*G53)) | K53: =IFERROR(AND(OR(INDEX('Question Restrictions'!$D:$D,MATCH($B53,'Question Restrictions'!$C:$C,0))="All",ISNUMBER(SEARCH('Project Information'!$C$10,INDEX('Question Restrictions'!$D:$D,MATCH($B53,'Question Restrictions'!$C:$C,0))))),OR(INDEX('Question Restrictions'!$E:$E,MATCH($B53,'Question Restrictions'!$C:$C,0))="All",ISNUMBER(SEARCH('Project Information'!$C$11,INDEX('Question Restrictions'!$E:$E,MATCH($B53,'Question Restrictions'!$C:$C,0))))),OR(INDEX('Question Restrictions'!$F:$F,MATCH($B53,'Question Restrictions'!$C:$C,0))="All",ISNUMBER(SEARCH('Project Information'!$C$12,INDEX('Question Restrictions'!$F:$F,MATCH($B53,'Question Restrictions'!$C:$C,0))))),INDEX('Question Restrictions'!$G:$G,MATCH($B53,'Question Restrictions'!$C:$C,0))="Yes"),TRUE())
A54: 42 | B54: =INDEX(Translations!$D:$ZZ, MATCH(1033,Translations!$A:$A,0), MATCH('Project Information'!$C$4,Translations!$D$1:$ZZ$1,0)) | C54: =INDEX(Translations!$D:$ZZ, MATCH(1034,Translations!$A:$A,0), MATCH('Project Information'!$C$4,Translations!$D$1:$ZZ$1,0)) | D54: =INDEX(Translations!$D:$ZZ, MATCH(34,Translations!$A:$A,0), MATCH('Project Information'!$C$4,Translations!$D$1:$ZZ$1,0)) | E54: 20 | F54: Evet | H54: =IF(OR(TRIM(F54)="Evet",TRIM(F54)="Yes"),E54,IF(G54="","",E54*G54)) | K54: =IFERROR(AND(OR(INDEX('Question Restrictions'!$D:$D,MATCH($B54,'Question Restrictions'!$C:$C,0))="All",ISNUMBER(SEARCH('Project Information'!$C$10,INDEX('Question Restrictions'!$D:$D,MATCH($B54,'Question Restrictions'!$C:$C,0))))),OR(INDEX('Question Restrictions'!$E:$E,MATCH($B54,'Question Restrictions'!$C:$C,0))="All",ISNUMBER(SEARCH('Project Information'!$C$11,INDEX('Question Restrictions'!$E:$E,MATCH($B54,'Question Restrictions'!$C:$C,0))))),OR(INDEX('Question Restrictions'!$F:$F,MATCH($B54,'Question Restrictions'!$C:$C,0))="All",ISNUMBER(SEARCH('Project Information'!$C$12,INDEX('Question Restrictions'!$F:$F,MATCH($B54,'Question Restrictions'!$C:$C,0))))),INDEX('Question Restrictions'!$G:$G,MATCH($B54,'Question Restrictions'!$C:$C,0))="Yes"),TRUE())
A55: 43 | B55: =INDEX(Translations!$D:$ZZ, MATCH(1035,Translations!$A:$A,0), MATCH('Project Information'!$C$4,Translations!$D$1:$ZZ$1,0)) | C55: =INDEX(Translations!$D:$ZZ, MATCH(1036,Translations!$A:$A,0), MATCH('Project Information'!$C$4,Translations!$D$1:$ZZ$1,0)) | D55: =INDEX(Translations!$D:$ZZ, MATCH(34,Translations!$A:$A,0), MATCH('Project Information'!$C$4,Translations!$D$1:$ZZ$1,0)) | E55: 15 | F55: Evet | H55: =IF(OR(TRIM(F55)="Evet",TRIM(F55)="Yes"),E55,IF(G55="","",E55*G55)) | K55: =IFERROR(AND(OR(INDEX('Question Restrictions'!$D:$D,MATCH($B55,'Question Restrictions'!$C:$C,0))="All",ISNUMBER(SEARCH('Project Information'!$C$10,INDEX('Question Restrictions'!$D:$D,MATCH($B55,'Question Restrictions'!$C:$C,0))))),OR(INDEX('Question Restrictions'!$E:$E,MATCH($B55,'Question Restrictions'!$C:$C,0))="All",ISNUMBER(SEARCH('Project Information'!$C$11,INDEX('Question Restrictions'!$E:$E,MATCH($B55,'Question Restrictions'!$C:$C,0))))),OR(INDEX('Question Restrictions'!$F:$F,MATCH($B55,'Question Restrictions'!$C:$C,0))="All",ISNUMBER(SEARCH('Project Information'!$C$12,INDEX('Question Restrictions'!$F:$F,MATCH($B55,'Question Restrictions'!$C:$C,0))))),INDEX('Question Restrictions'!$G:$G,MATCH($B55,'Question Restrictions'!$C:$C,0))="Yes"),TRUE())
A56: 44 | B56: =INDEX(Translations!$D:$ZZ, MATCH(1037,Translations!$A:$A,0), MATCH('Project Information'!$C$4,Translations!$D$1:$ZZ$1,0)) | C56: =INDEX(Translations!$D:$ZZ, MATCH(1038,Translations!$A:$A,0), MATCH('Project Information'!$C$4,Translations!$D$1:$ZZ$1,0)) | D56: =INDEX(Translations!$D:$ZZ, MATCH(34,Translations!$A:$A,0), MATCH('Project Information'!$C$4,Translations!$D$1:$ZZ$1,0)) | E56: 10 | F56: Evet | H56: =IF(OR(TRIM(F56)="Evet",TRIM(F56)="Yes"),E56,IF(G56="","",E56*G56)) | K56: =IFERROR(AND(OR(INDEX('Question Restrictions'!$D:$D,MATCH($B56,'Question Restrictions'!$C:$C,0))="All",ISNUMBER(SEARCH('Project Information'!$C$10,INDEX('Question Restrictions'!$D:$D,MATCH($B56,'Question Restrictions'!$C:$C,0))))),OR(INDEX('Question Restrictions'!$E:$E,MATCH($B56,'Question Restrictions'!$C:$C,0))="All",ISNUMBER(SEARCH('Project Information'!$C$11,INDEX('Question Restrictions'!$E:$E,MATCH($B56,'Question Restrictions'!$C:$C,0))))),OR(INDEX('Question Restrictions'!$F:$F,MATCH($B56,'Question Restrictions'!$C:$C,0))="All",ISNUMBER(SEARCH('Project Information'!$C$12,INDEX('Question Restrictions'!$F:$F,MATCH($B56,'Question Restrictions'!$C:$C,0))))),INDEX('Question Restrictions'!$G:$G,MATCH($B56,'Question Restrictions'!$C:$C,0))="Yes"),TRUE())
A57: 45 | B57: =INDEX(Translations!$D:$ZZ, MATCH(1039,Translations!$A:$A,0), MATCH('Project Information'!$C$4,Translations!$D$1:$ZZ$1,0)) | C57: =INDEX(Translations!$D:$ZZ, MATCH(1040,Translations!$A:$A,0), MATCH('Project Information'!$C$4,Translations!$D$1:$ZZ$1,0)) | D57: =INDEX(Translations!$D:$ZZ, MATCH(27,Translations!$A:$A,0), MATCH('Project Information'!$C$4,Translations!$D$1:$ZZ$1,0)) | E57: 5 | G57: 3 | H57: =IF(OR(TRIM(F57)="Evet",TRIM(F57)="Yes"),E57,IF(G57="","",E57*G57)) | K57: =IFERROR(AND(OR(INDEX('Question Restrictions'!$D:$D,MATCH($B57,'Question Restrictions'!$C:$C,0))="All",ISNUMBER(SEARCH('Project Information'!$C$10,INDEX('Question Restrictions'!$D:$D,MATCH($B57,'Question Restrictions'!$C:$C,0))))),OR(INDEX('Question Restrictions'!$E:$E,MATCH($B57,'Question Restrictions'!$C:$C,0))="All",ISNUMBER(SEARCH('Project Information'!$C$11,INDEX('Question Restrictions'!$E:$E,MATCH($B57,'Question Restrictions'!$C:$C,0))))),OR(INDEX('Question Restrictions'!$F:$F,MATCH($B57,'Question Restrictions'!$C:$C,0))="All",ISNUMBER(SEARCH('Project Information'!$C$12,INDEX('Question Restrictions'!$F:$F,MATCH($B57,'Question Restrictions'!$C:$C,0))))),INDEX('Question Restrictions'!$G:$G,MATCH($B57,'Question Restrictions'!$C:$C,0))="Yes"),TRUE())
A58: 46 | B58: =INDEX(Translations!$D:$ZZ, MATCH(1041,Translations!$A:$A,0), MATCH('Project Information'!$C$4,Translations!$D$1:$ZZ$1,0)) | C58: =INDEX(Translations!$D:$ZZ, MATCH(1042,Translations!$A:$A,0), MATCH('Project Information'!$C$4,Translations!$D$1:$ZZ$1,0)) | D58: =INDEX(Translations!$D:$ZZ, MATCH(34,Translations!$A:$A,0), MATCH('Project Information'!$C$4,Translations!$D$1:$ZZ$1,0)) | E58: 10 | F58: Hayır | H58: =IF(OR(TRIM(F58)="Evet",TRIM(F58)="Yes"),E58,IF(G58="","",E58*G58)) | K58: =IFERROR(AND(OR(INDEX('Question Restrictions'!$D:$D,MATCH($B58,'Question Restrictions'!$C:$C,0))="All",ISNUMBER(SEARCH('Project Information'!$C$10,INDEX('Question Restrictions'!$D:$D,MATCH($B58,'Question Restrictions'!$C:$C,0))))),OR(INDEX('Question Restrictions'!$E:$E,MATCH($B58,'Question Restrictions'!$C:$C,0))="All",ISNUMBER(SEARCH('Project Information'!$C$11,INDEX('Question Restrictions'!$E:$E,MATCH($B58,'Question Restrictions'!$C:$C,0))))),OR(INDEX('Question Restrictions'!$F:$F,MATCH($B58,'Question Restrictions'!$C:$C,0))="All",ISNUMBER(SEARCH('Project Information'!$C$12,INDEX('Question Restrictions'!$F:$F,MATCH($B58,'Question Restrictions'!$C:$C,0))))),INDEX('Question Restrictions'!$G:$G,MATCH($B58,'Question Restrictions'!$C:$C,0))="Yes"),TRUE())
A59: 47 | B59: =INDEX(Translations!$D:$ZZ, MATCH(1043,Translations!$A:$A,0), MATCH('Project Information'!$C$4,Translations!$D$1:$ZZ$1,0)) | C59: =INDEX(Translations!$D:$ZZ, MATCH(1044,Translations!$A:$A,0), MATCH('Project Information'!$C$4,Translations!$D$1:$ZZ$1,0)) | D59: =INDEX(Translations!$D:$ZZ, MATCH(34,Translations!$A:$A,0), MATCH('Project Information'!$C$4,Translations!$D$1:$ZZ$1,0)) | E59: 5 | F59: Hayır | H59: =IF(OR(TRIM(F59)="Evet",TRIM(F59)="Yes"),E59,IF(G59="","",E59*G59)) | K59: =IFERROR(AND(OR(INDEX('Question Restrictions'!$D:$D,MATCH($B59,'Question Restrictions'!$C:$C,0))="All",ISNUMBER(SEARCH('Project Information'!$C$10,INDEX('Question Restrictions'!$D:$D,MATCH($B59,'Question Restrictions'!$C:$C,0))))),OR(INDEX('Question Restrictions'!$E:$E,MATCH($B59,'Question Restrictions'!$C:$C,0))="All",ISNUMBER(SEARCH('Project Information'!$C$11,INDEX('Question Restrictions'!$E:$E,MATCH($B59,'Question Restrictions'!$C:$C,0))))),OR(INDEX('Question Restrictions'!$F:$F,MATCH($B59,'Question Restrictions'!$C:$C,0))="All",ISNUMBER(SEARCH('Project Information'!$C$12,INDEX('Question Restrictions'!$F:$F,MATCH($B59,'Question Restrictions'!$C:$C,0))))),INDEX('Question Restrictions'!$G:$G,MATCH($B59,'Question Restrictions'!$C:$C,0))="Yes"),TRUE())

Sheet Development
A1: =INDEX(Translations!$D:$ZZ, MATCH(1022,Translations!$A:$A,0), MATCH('Project Information'!$C$4,Translations!$D$1:$ZZ$1,0))
A3: =INDEX(Translations!$D:$ZZ, MATCH(15,Translations!$A:$A,0), MATCH('Project Information'!$C$4,Translations!$D$1:$ZZ$1,0))
A4: =INDEX(Translations!$D:$ZZ, MATCH(4,Translations!$A:$A,0), MATCH('Project Information'!$C$4,Translations!$D$1:$ZZ$1,0))
A5: =INDEX(Translations!$D:$ZZ, MATCH(5,Translations!$A:$A,0), MATCH('Project Information'!$C$4,Translations!$D$1:$ZZ$1,0)) | B5: =INDEX(Translations!$D:$ZZ, MATCH(6,Translations!$A:$A,0), MATCH('Project Information'!$C$4,Translations!$D$1:$ZZ$1,0))
A6: =INDEX(Translations!$D:$ZZ, MATCH(7,Translations!$A:$A,0), MATCH('Project Information'!$C$4,Translations!$D$1:$ZZ$1,0)) | B6: =INDEX(Translations!$D:$ZZ, MATCH(8,Translations!$A:$A,0), MATCH('Project Information'!$C$4,Translations!$D$1:$ZZ$1,0))
A7: =INDEX(Translations!$D:$ZZ, MATCH(9,Translations!$A:$A,0), MATCH('Project Information'!$C$4,Translations!$D$1:$ZZ$1,0)) | B7: =INDEX(Translations!$D:$ZZ, MATCH(10,Translations!$A:$A,0), MATCH('Project Information'!$C$4,Translations!$D$1:$ZZ$1,0))
A8: =INDEX(Translations!$D:$ZZ, MATCH(11,Translations!$A:$A,0), MATCH('Project Information'!$C$4,Translations!$D$1:$ZZ$1,0)) | B8: =INDEX(Translations!$D:$ZZ, MATCH(12,Translations!$A:$A,0), MATCH('Project Information'!$C$4,Translations!$D$1:$ZZ$1,0))
A9: =INDEX(Translations!$D:$ZZ, MATCH(13,Translations!$A:$A,0), MATCH('Project Information'!$C$4,Translations!$D$1:$ZZ$1,0)) | B9: =SUM($H$14:$H$36) | J9: =IF($B$9<=40,"S",IF($B$9<=70,"M",IF($B$9<=100,"L","XL")))
A10: =INDEX(Translations!$D:$ZZ, MATCH(14,Translations!$A:$A,0), MATCH('Project Information'!$C$4,Translations!$D$1:$ZZ$1,0)) | B10: =IF($J$9="S",INDEX(Translations!$D:$ZZ,MATCH(5,Translations!$A:$A,0),MATCH('Project Information'!$C$4,Translations!$D$1:$ZZ$1,0)),IF($J$9="M",INDEX(Translations!$D:$ZZ,MATCH(7,Translations!$A:$A,0),MATCH('Project Information'!$C$4,Translations!$D$1:$ZZ$1,0)),IF($J$9="L",INDEX(Translations!$D:$ZZ,MATCH(9,Translations!$A:$A,0),MATCH('Project Information'!$C$4,Translations!$D$1:$ZZ$1,0)),INDEX(Translations!$D:$ZZ,MATCH(11,Translations!$A:$A,0),MATCH('Project Information'!$C$4,Translations!$D$1:$ZZ$1,0)))))
A11: =INDEX(Translations!$D:$ZZ, MATCH(15,Translations!$A:$A,0), MATCH('Project Information'!$C$4,Translations!$D$1:$ZZ$1,0))
A12: =INDEX(Translations!$D:$ZZ, MATCH(16,Translations!$A:$A,0), MATCH('Project Information'!$C$4,Translations!$D$1:$ZZ$1,0)) | B12: =INDEX(Translations!$D:$ZZ, MATCH(17,Translations!$A:$A,0), MATCH('Project Information'!$C$4,Translations!$D$1:$ZZ$1,0)) | C12: =INDEX(Translations!$D:$ZZ, MATCH(18,Translations!$A:$A,0), MATCH('Project Information'!$C$4,Translations!$D$1:$ZZ$1,0)) | D12: =INDEX(Translations!$D:$ZZ, MATCH(19,Translations!$A:$A,0), MATCH('Project Information'!$C$4,Translations!$D$1:$ZZ$1,0)) | E12: =INDEX(Translations!$D:$ZZ, MATCH(20,Translations!$A:$A,0), MATCH('Project Information'!$C$4,Translations!$D$1:$ZZ$1,0)) | F12: =INDEX(Translations!$D:$ZZ, MATCH(21,Translations!$A:$A,0), MATCH('Project Information'!$C$4,Translations!$D$1:$ZZ$1,0)) | G12: =INDEX(Translations!$D:$ZZ, MATCH(22,Translations!$A:$A,0), MATCH('Project Information'!$C$4,Translations!$D$1:$ZZ$1,0)) | H12: =INDEX(Translations!$D:$ZZ, MATCH(23,Translations!$A:$A,0), MATCH('Project Information'!$C$4,Translations!$D$1:$ZZ$1,0)) | I12: =INDEX(Translations!$D:$ZZ, MATCH(24,Translations!$A:$A,0), MATCH('Project Information'!$C$4,Translations!$D$1:$ZZ$1,0)) | K12: Applicable?
A13: 1 | B13: =INDEX(Translations!$D:$ZZ, MATCH(169,Translations!$A:$A,0), MATCH('Project Information'!$C$4,Translations!$D$1:$ZZ$1,0)) | C13: =INDEX(Translations!$D:$ZZ, MATCH(170,Translations!$A:$A,0), MATCH('Project Information'!$C$4,Translations!$D$1:$ZZ$1,0)) | D13: =INDEX(Translations!$D:$ZZ, MATCH(172,Translations!$A:$A,0), MATCH('Project Information'!$C$4,Translations!$D$1:$ZZ$1,0)) | H13: =IF(OR(TRIM(F13)="Evet",TRIM(F13)="Yes"),E13,IF(G13="","",E13*G13)) | K13: =IFERROR(AND(OR(INDEX('Question Restrictions'!$D:$D,MATCH($B13,'Question Restrictions'!$C:$C,0))="All",ISNUMBER(SEARCH('Project Information'!$C$10,INDEX('Question Restrictions'!$D:$D,MATCH($B13,'Question Restrictions'!$C:$C,0))))),OR(INDEX('Question Restrictions'!$E:$E,MATCH($B13,'Question Restrictions'!$C:$C,0))="All",ISNUMBER(SEARCH('Project Information'!$C$11,INDEX('Question Restrictions'!$E:$E,MATCH($B13,'Question Restrictions'!$C:$C,0))))),OR(INDEX('Question Restrictions'!$F:$F,MATCH($B13,'Question Restrictions'!$C:$C,0))="All",ISNUMBER(SEARCH('Project Information'!$C$12,INDEX('Question Restrictions'!$F:$F,MATCH($B13,'Question Restrictions'!$C:$C,0))))),INDEX('Question Restrictions'!$G:$G,MATCH($B13,'Question Restrictions'!$C:$C,0))="Yes"),TRUE())
A14: 2 | B14: =INDEX(Translations!$D:$ZZ, MATCH(173,Translations!$A:$A,0), MATCH('Project Information'!$C$4,Translations!$D$1:$ZZ$1,0)) | C14: =INDEX(Translations!$D:$ZZ, MATCH(174,Translations!$A:$A,0), MATCH('Project Information'!$C$4,Translations!$D$1:$ZZ$1,0)) | D14: =INDEX(Translations!$D:$ZZ, MATCH(172,Translations!$A:$A,0), MATCH('Project Information'!$C$4,Translations!$D$1:$ZZ$1,0)) | H14: =IF(OR(TRIM(F14)="Evet",TRIM(F14)="Yes"),E14,IF(G14="","",E14*G14)) | K14: =IFERROR(AND(OR(INDEX('Question Restrictions'!$D:$D,MATCH($B14,'Question Restrictions'!$C:$C,0))="All",ISNUMBER(SEARCH('Project Information'!$C$10,INDEX('Question Restrictions'!$D:$D,MATCH($B14,'Question Restrictions'!$C:$C,0))))),OR(INDEX('Question Restrictions'!$E:$E,MATCH($B14,'Question Restrictions'!$C:$C,0))="All",ISNUMBER(SEARCH('Project Information'!$C$11,INDEX('Question Restrictions'!$E:$E,MATCH($B14,'Question Restrictions'!$C:$C,0))))),OR(INDEX('Question Restrictions'!$F:$F,MATCH($B14,'Question Restrictions'!$C:$C,0))="All",ISNUMBER(SEARCH('Project Information'!$C$12,INDEX('Question Restrictions'!$F:$F,MATCH($B14,'Question Restrictions'!$C:$C,0))))),INDEX('Question Restrictions'!$G:$G,MATCH($B14,'Question Restrictions'!$C:$C,0))="Yes"),TRUE())
A15: 3 | B15: =INDEX(Translations!$D:$ZZ, MATCH(175,Translations!$A:$A,0), MATCH('Project Information'!$C$4,Translations!$D$1:$ZZ$1,0)) | C15: =INDEX(Translations!$D:$ZZ, MATCH(176,Translations!$A:$A,0), MATCH('Project Information'!$C$4,Translations!$D$1:$ZZ$1,0)) | D15: =INDEX(Translations!$D:$ZZ, MATCH(172,Translations!$A:$A,0), MATCH('Project Information'!$C$4,Translations!$D$1:$ZZ$1,0)) | H15: =IF(OR(TRIM(F15)="Evet",TRIM(F15)="Yes"),E15,IF(G15="","",E15*G15)) | K15: =IFERROR(AND(OR(INDEX('Question Restrictions'!$D:$D,MATCH($B15,'Question Restrictions'!$C:$C,0))="All",ISNUMBER(SEARCH('Project Information'!$C$10,INDEX('Question Restrictions'!$D:$D,MATCH($B15,'Question Restrictions'!$C:$C,0))))),OR(INDEX('Question Restrictions'!$E:$E,MATCH($B15,'Question Restrictions'!$C:$C,0))="All",ISNUMBER(SEARCH('Project Information'!$C$11,INDEX('Question Restrictions'!$E:$E,MATCH($B15,'Question Restrictions'!$C:$C,0))))),OR(INDEX('Question Restrictions'!$F:$F,MATCH($B15,'Question Restrictions'!$C:$C,0))="All",ISNUMBER(SEARCH('Project Information'!$C$12,INDEX('Question Restrictions'!$F:$F,MATCH($B15,'Question Restrictions'!$C:$C,0))))),INDEX('Question Restrictions'!$G:$G,MATCH($B15,'Question Restrictions'!$C:$C,0))="Yes"),TRUE())
A16: 4 | B16: =INDEX(Translations!$D:$ZZ, MATCH(201,Translations!$A:$A,0), MATCH('Project Information'!$C$4,Translations!$D$1:$ZZ$1,0)) | C16: =INDEX(Translations!$D:$ZZ, MATCH(202,Translations!$A:$A,0), MATCH('Project Information'!$C$4,Translations!$D$1:$ZZ$1,0)) | D16: =INDEX(Translations!$D:$ZZ, MATCH(27,Translations!$A:$A,0), MATCH('Project Information'!$C$4,Translations!$D$1:$ZZ$1,0)) | H16: =IF(OR(TRIM(F16)="Evet",TRIM(F16)="Yes"),E16,IF(G16="","",E16*G16)) | K16: =IFERROR(AND(OR(INDEX('Question Restrictions'!$D:$D,MATCH($B16,'Question Restrictions'!$C:$C,0))="All",ISNUMBER(SEARCH('Project Information'!$C$10,INDEX('Question Restrictions'!$D:$D,MATCH($B16,'Question Restrictions'!$C:$C,0))))),OR(INDEX('Question Restrictions'!$E:$E,MATCH($B16,'Question Restrictions'!$C:$C,0))="All",ISNUMBER(SEARCH('Project Information'!$C$11,INDEX('Question Restrictions'!$E:$E,MATCH($B16,'Question Restrictions'!$C:$C,0))))),OR(INDEX('Question Restrictions'!$F:$F,MATCH($B16,'Question Restrictions'!$C:$C,0))="All",ISNUMBER(SEARCH('Project Information'!$C$12,INDEX('Question Restrictions'!$F:$F,MATCH($B16,'Question Restrictions'!$C:$C,0))))),INDEX('Question Restrictions'!$G:$G,MATCH($B16,'Question Restrictions'!$C:$C,0))="Yes"),TRUE())
A17: 5 | B17: =INDEX(Translations!$D:$ZZ, MATCH(205,Translations!$A:$A,0), MATCH('Project Information'!$C$4,Translations!$D$1:$ZZ$1,0)) | C17: =INDEX(Translations!$D:$ZZ, MATCH(206,Translations!$A:$A,0), MATCH('Project Information'!$C$4,Translations!$D$1:$ZZ$1,0)) | D17: =INDEX(Translations!$D:$ZZ, MATCH(27,Translations!$A:$A,0), MATCH('Project Information'!$C$4,Translations!$D$1:$ZZ$1,0)) | H17: =IF(OR(TRIM(F17)="Evet",TRIM(F17)="Yes"),E17,IF(G17="","",E17*G17)) | K17: =IFERROR(AND(OR(INDEX('Question Restrictions'!$D:$D,MATCH($B17,'Question Restrictions'!$C:$C,0))="All",ISNUMBER(SEARCH('Project Information'!$C$10,INDEX('Question Restrictions'!$D:$D,MATCH($B17,'Question Restrictions'!$C:$C,0))))),OR(INDEX('Question Restrictions'!$E:$E,MATCH($B17,'Question Restrictions'!$C:$C,0))="All",ISNUMBER(SEARCH('Project Information'!$C$11,INDEX('Question Restrictions'!$E:$E,MATCH($B17,'Question Restrictions'!$C:$C,0))))),OR(INDEX('Question Restrictions'!$F:$F,MATCH($B17,'Question Restrictions'!$C:$C,0))="All",ISNUMBER(SEARCH('Project Information'!$C$12,INDEX('Question Restrictions'!$F:$F,MATCH($B17,'Question Restrictions'!$C:$C,0))))),INDEX('Question Restrictions'!$G:$G,MATCH($B17,'Question Restrictions'!$C:$C,0))="Yes"),TRUE())
A18: 6 | B18: =INDEX(Translations!$D:$ZZ, MATCH(209,Translations!$A:$A,0), MATCH('Project Information'!$C$4,Translations!$D$1:$ZZ$1,0)) | C18: =INDEX(Translations!$D:$ZZ, MATCH(210,Translations!$A:$A,0), MATCH('Project Information'!$C$4,Translations!$D$1:$ZZ$1,0)) | D18: =INDEX(Translations!$D:$ZZ, MATCH(172,Translations!$A:$A,0), MATCH('Project Information'!$C$4,Translations!$D$1:$ZZ$1,0)) | H18: =IF(OR(TRIM(F18)="Evet",TRIM(F18)="Yes"),E18,IF(G18="","",E18*G18)) | K18: =IFERROR(AND(OR(INDEX('Question Restrictions'!$D:$D,MATCH($B18,'Question Restrictions'!$C:$C,0))="All",ISNUMBER(SEARCH('Project Information'!$C$10,INDEX('Question Restrictions'!$D:$D,MATCH($B18,'Question Restrictions'!$C:$C,0))))),OR(INDEX('Question Restrictions'!$E:$E,MATCH($B18,'Question Restrictions'!$C:$C,0))="All",ISNUMBER(SEARCH('Project Information'!$C$11,INDEX('Question Restrictions'!$E:$E,MATCH($B18,'Question Restrictions'!$C:$C,0))))),OR(INDEX('Question Restrictions'!$F:$F,MATCH($B18,'Question Restrictions'!$C:$C,0))="All",ISNUMBER(SEARCH('Project Information'!$C$12,INDEX('Question Restrictions'!$F:$F,MATCH($B18,'Question Restrictions'!$C:$C,0))))),INDEX('Question Restrictions'!$G:$G,MATCH($B18,'Question Restrictions'!$C:$C,0))="Yes"),TRUE())
A19: 7 | B19: =INDEX(Translations!$D:$ZZ, MATCH(211,Translations!$A:$A,0), MATCH('Project Information'!$C$4,Translations!$D$1:$ZZ$1,0)) | C19: =INDEX(Translations!$D:$ZZ, MATCH(212,Translations!$A:$A,0), MATCH('Project Information'!$C$4,Translations!$D$1:$ZZ$1,0)) | D19: =INDEX(Translations!$D:$ZZ, MATCH(172,Translations!$A:$A,0), MATCH('Project Information'!$C$4,Translations!$D$1:$ZZ$1,0)) | H19: =IF(OR(TRIM(F19)="Evet",TRIM(F19)="Yes"),E19,IF(G19="","",E19*G19)) | K19: =IFERROR(AND(OR(INDEX('Question Restrictions'!$D:$D,MATCH($B19,'Question Restrictions'!$C:$C,0))="All",ISNUMBER(SEARCH('Project Information'!$C$10,INDEX('Question Restrictions'!$D:$D,MATCH($B19,'Question Restrictions'!$C:$C,0))))),OR(INDEX('Question Restrictions'!$E:$E,MATCH($B19,'Question Restrictions'!$C:$C,0))="All",ISNUMBER(SEARCH('Project Information'!$C$11,INDEX('Question Restrictions'!$E:$E,MATCH($B19,'Question Restrictions'!$C:$C,0))))),OR(INDEX('Question Restrictions'!$F:$F,MATCH($B19,'Question Restrictions'!$C:$C,0))="All",ISNUMBER(SEARCH('Project Information'!$C$12,INDEX('Question Restrictions'!$F:$F,MATCH($B19,'Question Restrictions'!$C:$C,0))))),INDEX('Question Restrictions'!$G:$G,MATCH($B19,'Question Restrictions'!$C:$C,0))="Yes"),TRUE())
A20: 8 | B20: =INDEX(Translations!$D:$ZZ, MATCH(213,Translations!$A:$A,0), MATCH('Project Information'!$C$4,Translations!$D$1:$ZZ$1,0)) | C20: =INDEX(Translations!$D:$ZZ, MATCH(214,Translations!$A:$A,0), MATCH('Project Information'!$C$4,Translations!$D$1:$ZZ$1,0)) | D20: =INDEX(Translations!$D:$ZZ, MATCH(172,Translations!$A:$A,0), MATCH('Project Information'!$C$4,Translations!$D$1:$ZZ$1,0)) | H20: =IF(OR(TRIM(F20)="Evet",TRIM(F20)="Yes"),E20,IF(G20="","",E20*G20)) | K20: =IFERROR(AND(OR(INDEX('Question Restrictions'!$D:$D,MATCH($B20,'Question Restrictions'!$C:$C,0))="All",ISNUMBER(SEARCH('Project Information'!$C$10,INDEX('Question Restrictions'!$D:$D,MATCH($B20,'Question Restrictions'!$C:$C,0))))),OR(INDEX('Question Restrictions'!$E:$E,MATCH($B20,'Question Restrictions'!$C:$C,0))="All",ISNUMBER(SEARCH('Project Information'!$C$11,INDEX('Question Restrictions'!$E:$E,MATCH($B20,'Question Restrictions'!$C:$C,0))))),OR(INDEX('Question Restrictions'!$F:$F,MATCH($B20,'Question Restrictions'!$C:$C,0))="All",ISNUMBER(SEARCH('Project Information'!$C$12,INDEX('Question Restrictions'!$F:$F,MATCH($B20,'Question Restrictions'!$C:$C,0))))),INDEX('Question Restrictions'!$G:$G,MATCH($B20,'Question Restrictions'!$C:$C,0))="Yes"),TRUE())
A21: 9 | B21: =INDEX(Translations!$D:$ZZ, MATCH(215,Translations!$A:$A,0), MATCH('Project Information'!$C$4,Translations!$D$1:$ZZ$1,0)) | C21: =INDEX(Translations!$D:$ZZ, MATCH(216,Translations!$A:$A,0), MATCH('Project Information'!$C$4,Translations!$D$1:$ZZ$1,0)) | D21: =INDEX(Translations!$D:$ZZ, MATCH(172,Translations!$A:$A,0), MATCH('Project Information'!$C$4,Translations!$D$1:$ZZ$1,0)) | H21: =IF(OR(TRIM(F21)="Evet",TRIM(F21)="Yes"),E21,IF(G21="","",E21*G21)) | K21: =IFERROR(AND(OR(INDEX('Question Restrictions'!$D:$D,MATCH($B21,'Question Restrictions'!$C:$C,0))="All",ISNUMBER(SEARCH('Project Information'!$C$10,INDEX('Question Restrictions'!$D:$D,MATCH($B21,'Question Restrictions'!$C:$C,0))))),OR(INDEX('Question Restrictions'!$E:$E,MATCH($B21,'Question Restrictions'!$C:$C,0))="All",ISNUMBER(SEARCH('Project Information'!$C$11,INDEX('Question Restrictions'!$E:$E,MATCH($B21,'Question Restrictions'!$C:$C,0))))),OR(INDEX('Question Restrictions'!$F:$F,MATCH($B21,'Question Restrictions'!$C:$C,0))="All",ISNUMBER(SEARCH('Project Information'!$C$12,INDEX('Question Restrictions'!$F:$F,MATCH($B21,'Question Restrictions'!$C:$C,0))))),INDEX('Question Restrictions'!$G:$G,MATCH($B21,'Question Restrictions'!$C:$C,0))="Yes"),TRUE())
A22: 10 | B22: =INDEX(Translations!$D:$ZZ, MATCH(224,Translations!$A:$A,0), MATCH('Project Information'!$C$4,Translations!$D$1:$ZZ$1,0)) | C22: =INDEX(Translations!$D:$ZZ, MATCH(194,Translations!$A:$A,0), MATCH('Project Information'!$C$4,Translations!$D$1:$ZZ$1,0)) | D22: =INDEX(Translations!$D:$ZZ, MATCH(27,Translations!$A:$A,0), MATCH('Project Information'!$C$4,Translations!$D$1:$ZZ$1,0)) | H22: =IF(OR(TRIM(F22)="Evet",TRIM(F22)="Yes"),E22,IF(G22="","",E22*G22)) | K22: =IFERROR(AND(OR(INDEX('Question Restrictions'!$D:$D,MATCH($B22,'Question Restrictions'!$C:$C,0))="All",ISNUMBER(SEARCH('Project Information'!$C$10,INDEX('Question Restrictions'!$D:$D,MATCH($B22,'Question Restrictions'!$C:$C,0))))),OR(INDEX('Question Restrictions'!$E:$E,MATCH($B22,'Question Restrictions'!$C:$C,0))="All",ISNUMBER(SEARCH('Project Information'!$C$11,INDEX('Question Restrictions'!$E:$E,MATCH($B22,'Question Restrictions'!$C:$C,0))))),OR(INDEX('Question Restrictions'!$F:$F,MATCH($B22,'Question Restrictions'!$C:$C,0))="All",ISNUMBER(SEARCH('Project Information'!$C$12,INDEX('Question Restrictions'!$F:$F,MATCH($B22,'Question Restrictions'!$C:$C,0))))),INDEX('Question Restrictions'!$G:$G,MATCH($B22,'Question Restrictions'!$C:$C,0))="Yes"),TRUE())
A23: 11 | B23: =INDEX(Translations!$D:$ZZ, MATCH(225,Translations!$A:$A,0), MATCH('Project Information'!$C$4,Translations!$D$1:$ZZ$1,0)) | C23: =INDEX(Translations!$D:$ZZ, MATCH(226,Translations!$A:$A,0), MATCH('Project Information'!$C$4,Translations!$D$1:$ZZ$1,0)) | D23: =INDEX(Translations!$D:$ZZ, MATCH(172,Translations!$A:$A,0), MATCH('Project Information'!$C$4,Translations!$D$1:$ZZ$1,0)) | H23: =IF(OR(TRIM(F23)="Evet",TRIM(F23)="Yes"),E23,IF(G23="","",E23*G23)) | K23: =IFERROR(AND(OR(INDEX('Question Restrictions'!$D:$D,MATCH($B23,'Question Restrictions'!$C:$C,0))="All",ISNUMBER(SEARCH('Project Information'!$C$10,INDEX('Question Restrictions'!$D:$D,MATCH($B23,'Question Restrictions'!$C:$C,0))))),OR(INDEX('Question Restrictions'!$E:$E,MATCH($B23,'Question Restrictions'!$C:$C,0))="All",ISNUMBER(SEARCH('Project Information'!$C$11,INDEX('Question Restrictions'!$E:$E,MATCH($B23,'Question Restrictions'!$C:$C,0))))),OR(INDEX('Question Restrictions'!$F:$F,MATCH($B23,'Question Restrictions'!$C:$C,0))="All",ISNUMBER(SEARCH('Project Information'!$C$12,INDEX('Question Restrictions'!$F:$F,MATCH($B23,'Question Restrictions'!$C:$C,0))))),INDEX('Question Restrictions'!$G:$G,MATCH($B23,'Question Restrictions'!$C:$C,0))="Yes"),TRUE())
A24: 12 | B24: =INDEX(Translations!$D:$ZZ, MATCH(227,Translations!$A:$A,0), MATCH('Project Information'!$C$4,Translations!$D$1:$ZZ$1,0)) | C24: =INDEX(Translations!$D:$ZZ, MATCH(228,Translations!$A:$A,0), MATCH('Project Information'!$C$4,Translations!$D$1:$ZZ$1,0)) | D24: =INDEX(Translations!$D:$ZZ, MATCH(27,Translations!$A:$A,0), MATCH('Project Information'!$C$4,Translations!$D$1:$ZZ$1,0)) | H24: =IF(OR(TRIM(F24)="Evet",TRIM(F24)="Yes"),E24,IF(G24="","",E24*G24)) | K24: =IFERROR(AND(OR(INDEX('Question Restrictions'!$D:$D,MATCH($B24,'Question Restrictions'!$C:$C,0))="All",ISNUMBER(SEARCH('Project Information'!$C$10,INDEX('Question Restrictions'!$D:$D,MATCH($B24,'Question Restrictions'!$C:$C,0))))),OR(INDEX('Question Restrictions'!$E:$E,MATCH($B24,'Question Restrictions'!$C:$C,0))="All",ISNUMBER(SEARCH('Project Information'!$C$11,INDEX('Question Restrictions'!$E:$E,MATCH($B24,'Question Restrictions'!$C:$C,0))))),OR(INDEX('Question Restrictions'!$F:$F,MATCH($B24,'Question Restrictions'!$C:$C,0))="All",ISNUMBER(SEARCH('Project Information'!$C$12,INDEX('Question Restrictions'!$F:$F,MATCH($B24,'Question Restrictions'!$C:$C,0))))),INDEX('Question Restrictions'!$G:$G,MATCH($B24,'Question Restrictions'!$C:$C,0))="Yes"),TRUE())
A25: 13 | B25: =INDEX(Translations!$D:$ZZ, MATCH(229,Translations!$A:$A,0), MATCH('Project Information'!$C$4,Translations!$D$1:$ZZ$1,0)) | C25: =INDEX(Translations!$D:$ZZ, MATCH(230,Translations!$A:$A,0), MATCH('Project Information'!$C$4,Translations!$D$1:$ZZ$1,0)) | D25: =INDEX(Translations!$D:$ZZ, MATCH(172,Translations!$A:$A,0), MATCH('Project Information'!$C$4,Translations!$D$1:$ZZ$1,0)) | H25: =IF(OR(TRIM(F25)="Evet",TRIM(F25)="Yes"),E25,IF(G25="","",E25*G25)) | K25: =IFERROR(AND(OR(INDEX('Question Restrictions'!$D:$D,MATCH($B25,'Question Restrictions'!$C:$C,0))="All",ISNUMBER(SEARCH('Project Information'!$C$10,INDEX('Question Restrictions'!$D:$D,MATCH($B25,'Question Restrictions'!$C:$C,0))))),OR(INDEX('Question Restrictions'!$E:$E,MATCH($B25,'Question Restrictions'!$C:$C,0))="All",ISNUMBER(SEARCH('Project Information'!$C$11,INDEX('Question Restrictions'!$E:$E,MATCH($B25,'Question Restrictions'!$C:$C,0))))),OR(INDEX('Question Restrictions'!$F:$F,MATCH($B25,'Question Restrictions'!$C:$C,0))="All",ISNUMBER(SEARCH('Project Information'!$C$12,INDEX('Question Restrictions'!$F:$F,MATCH($B25,'Question Restrictions'!$C:$C,0))))),INDEX('Question Restrictions'!$G:$G,MATCH($B25,'Question Restrictions'!$C:$C,0))="Yes"),TRUE())
A26: 14 | B26: =INDEX(Translations!$D:$ZZ, MATCH(233,Translations!$A:$A,0), MATCH('Project Information'!$C$4,Translations!$D$1:$ZZ$1,0)) | C26: =INDEX(Translations!$D:$ZZ, MATCH(194,Translations!$A:$A,0), MATCH('Project Information'!$C$4,Translations!$D$1:$ZZ$1,0)) | D26: =INDEX(Translations!$D:$ZZ, MATCH(172,Translations!$A:$A,0), MATCH('Project Information'!$C$4,Translations!$D$1:$ZZ$1,0)) | H26: =IF(OR(TRIM(F26)="Evet",TRIM(F26)="Yes"),E26,IF(G26="","",E26*G26)) | K26: =IFERROR(AND(OR(INDEX('Question Restrictions'!$D:$D,MATCH($B26,'Question Restrictions'!$C:$C,0))="All",ISNUMBER(SEARCH('Project Information'!$C$10,INDEX('Question Restrictions'!$D:$D,MATCH($B26,'Question Restrictions'!$C:$C,0))))),OR(INDEX('Question Restrictions'!$E:$E,MATCH($B26,'Question Restrictions'!$C:$C,0))="All",ISNUMBER(SEARCH('Project Information'!$C$11,INDEX('Question Restrictions'!$E:$E,MATCH($B26,'Question Restrictions'!$C:$C,0))))),OR(INDEX('Question Restrictions'!$F:$F,MATCH($B26,'Question Restrictions'!$C:$C,0))="All",ISNUMBER(SEARCH('Project Information'!$C$12,INDEX('Question Restrictions'!$F:$F,MATCH($B26,'Question Restrictions'!$C:$C,0))))),INDEX('Question Restrictions'!$G:$G,MATCH($B26,'Question Restrictions'!$C:$C,0))="Yes"),TRUE())
A27: 15 | B27: =INDEX(Translations!$D:$ZZ, MATCH(237,Translations!$A:$A,0), MATCH('Project Information'!$C$4,Translations!$D$1:$ZZ$1,0)) | C27: =INDEX(Translations!$D:$ZZ, MATCH(238,Translations!$A:$A,0), MATCH('Project Information'!$C$4,Translations!$D$1:$ZZ$1,0)) | D27: =INDEX(Translations!$D:$ZZ, MATCH(172,Translations!$A:$A,0), MATCH('Project Information'!$C$4,Translations!$D$1:$ZZ$1,0)) | H27: =IF(OR(TRIM(F27)="Evet",TRIM(F27)="Yes"),E27,IF(G27="","",E27*G27)) | K27: =IFERROR(AND(OR(INDEX('Question Restrictions'!$D:$D,MATCH($B27,'Question Restrictions'!$C:$C,0))="All",ISNUMBER(SEARCH('Project Information'!$C$10,INDEX('Question Restrictions'!$D:$D,MATCH($B27,'Question Restrictions'!$C:$C,0))))),OR(INDEX('Question Restrictions'!$E:$E,MATCH($B27,'Question Restrictions'!$C:$C,0))="All",ISNUMBER(SEARCH('Project Information'!$C$11,INDEX('Question Restrictions'!$E:$E,MATCH($B27,'Question Restrictions'!$C:$C,0))))),OR(INDEX('Question Restrictions'!$F:$F,MATCH($B27,'Question Restrictions'!$C:$C,0))="All",ISNUMBER(SEARCH('Project Information'!$C$12,INDEX('Question Restrictions'!$F:$F,MATCH($B27,'Question Restrictions'!$C:$C,0))))),INDEX('Question Restrictions'!$G:$G,MATCH($B27,'Question Restrictions'!$C:$C,0))="Yes"),TRUE())
A28: 16 | B28: =INDEX(Translations!$D:$ZZ, MATCH(274,Translations!$A:$A,0), MATCH('Project Information'!$C$4,Translations!$D$1:$ZZ$1,0)) | C28: =INDEX(Translations!$D:$ZZ, MATCH(194,Translations!$A:$A,0), MATCH('Project Information'!$C$4,Translations!$D$1:$ZZ$1,0)) | D28: =INDEX(Translations!$D:$ZZ, MATCH(172,Translations!$A:$A,0), MATCH('Project Information'!$C$4,Translations!$D$1:$ZZ$1,0)) | H28: =IF(OR(TRIM(F28)="Evet",TRIM(F28)="Yes"),E28,IF(G28="","",E28*G28)) | K28: =IFERROR(AND(OR(INDEX('Question Restrictions'!$D:$D,MATCH($B28,'Question Restrictions'!$C:$C,0))="All",ISNUMBER(SEARCH('Project Information'!$C$10,INDEX('Question Restrictions'!$D:$D,MATCH($B28,'Question Restrictions'!$C:$C,0))))),OR(INDEX('Question Restrictions'!$E:$E,MATCH($B28,'Question Restrictions'!$C:$C,0))="All",ISNUMBER(SEARCH('Project Information'!$C$11,INDEX('Question Restrictions'!$E:$E,MATCH($B28,'Question Restrictions'!$C:$C,0))))),OR(INDEX('Question Restrictions'!$F:$F,MATCH($B28,'Question Restrictions'!$C:$C,0))="All",ISNUMBER(SEARCH('Project Information'!$C$12,INDEX('Question Restrictions'!$F:$F,MATCH($B28,'Question Restrictions'!$C:$C,0))))),INDEX('Question Restrictions'!$G:$G,MATCH($B28,'Question Restrictions'!$C:$C,0))="Yes"),TRUE())
A29: 17 | B29: =INDEX(Translations!$D:$ZZ, MATCH(275,Translations!$A:$A,0), MATCH('Project Information'!$C$4,Translations!$D$1:$ZZ$1,0)) | C29: =INDEX(Translations!$D:$ZZ, MATCH(194,Translations!$A:$A,0), MATCH('Project Information'!$C$4,Translations!$D$1:$ZZ$1,0)) | D29: =INDEX(Translations!$D:$ZZ, MATCH(172,Translations!$A:$A,0), MATCH('Project Information'!$C$4,Translations!$D$1:$ZZ$1,0)) | H29: =IF(OR(TRIM(F29)="Evet",TRIM(F29)="Yes"),E29,IF(G29="","",E29*G29)) | K29: =IFERROR(AND(OR(INDEX('Question Restrictions'!$D:$D,MATCH($B29,'Question Restrictions'!$C:$C,0))="All",ISNUMBER(SEARCH('Project Information'!$C$10,INDEX('Question Restrictions'!$D:$D,MATCH($B29,'Question Restrictions'!$C:$C,0))))),OR(INDEX('Question Restrictions'!$E:$E,MATCH($B29,'Question Restrictions'!$C:$C,0))="All",ISNUMBER(SEARCH('Project Information'!$C$11,INDEX('Question Restrictions'!$E:$E,MATCH($B29,'Question Restrictions'!$C:$C,0))))),OR(INDEX('Question Restrictions'!$F:$F,MATCH($B29,'Question Restrictions'!$C:$C,0))="All",ISNUMBER(SEARCH('Project Information'!$C$12,INDEX('Question Restrictions'!$F:$F,MATCH($B29,'Question Restrictions'!$C:$C,0))))),INDEX('Question Restrictions'!$G:$G,MATCH($B29,'Question Restrictions'!$C:$C,0))="Yes"),TRUE())
A30: 18 | B30: =INDEX(Translations!$D:$ZZ, MATCH(239,Translations!$A:$A,0), MATCH('Project Information'!$C$4,Translations!$D$1:$ZZ$1,0)) | C30: =INDEX(Translations!$D:$ZZ, MATCH(194,Translations!$A:$A,0), MATCH('Project Information'!$C$4,Translations!$D$1:$ZZ$1,0)) | D30: =INDEX(Translations!$D:$ZZ, MATCH(172,Translations!$A:$A,0), MATCH('Project Information'!$C$4,Translations!$D$1:$ZZ$1,0)) | H30: =IF(OR(TRIM(F30)="Evet",TRIM(F30)="Yes"),E30,IF(G30="","",E30*G30)) | K30: =IFERROR(AND(OR(INDEX('Question Restrictions'!$D:$D,MATCH($B30,'Question Restrictions'!$C:$C,0))="All",ISNUMBER(SEARCH('Project Information'!$C$10,INDEX('Question Restrictions'!$D:$D,MATCH($B30,'Question Restrictions'!$C:$C,0))))),OR(INDEX('Question Restrictions'!$E:$E,MATCH($B30,'Question Restrictions'!$C:$C,0))="All",ISNUMBER(SEARCH('Project Information'!$C$11,INDEX('Question Restrictions'!$E:$E,MATCH($B30,'Question Restrictions'!$C:$C,0))))),OR(INDEX('Question Restrictions'!$F:$F,MATCH($B30,'Question Restrictions'!$C:$C,0))="All",ISNUMBER(SEARCH('Project Information'!$C$12,INDEX('Question Restrictions'!$F:$F,MATCH($B30,'Question Restrictions'!$C:$C,0))))),INDEX('Question Restrictions'!$G:$G,MATCH($B30,'Question Restrictions'!$C:$C,0))="Yes"),TRUE())
A31: 19 | B31: =INDEX(Translations!$D:$ZZ, MATCH(240,Translations!$A:$A,0), MATCH('Project Information'!$C$4,Translations!$D$1:$ZZ$1,0)) | C31: =INDEX(Translations!$D:$ZZ, MATCH(194,Translations!$A:$A,0), MATCH('Project Information'!$C$4,Translations!$D$1:$ZZ$1,0)) | D31: =INDEX(Translations!$D:$ZZ, MATCH(172,Translations!$A:$A,0), MATCH('Project Information'!$C$4,Translations!$D$1:$ZZ$1,0)) | H31: =IF(OR(TRIM(F31)="Evet",TRIM(F31)="Yes"),E31,IF(G31="","",E31*G31)) | K31: =IFERROR(AND(OR(INDEX('Question Restrictions'!$D:$D,MATCH($B31,'Question Restrictions'!$C:$C,0))="All",ISNUMBER(SEARCH('Project Information'!$C$10,INDEX('Question Restrictions'!$D:$D,MATCH($B31,'Question Restrictions'!$C:$C,0))))),OR(INDEX('Question Restrictions'!$E:$E,MATCH($B31,'Question Restrictions'!$C:$C,0))="All",ISNUMBER(SEARCH('Project Information'!$C$11,INDEX('Question Restrictions'!$E:$E,MATCH($B31,'Question Restrictions'!$C:$C,0))))),OR(INDEX('Question Restrictions'!$F:$F,MATCH($B31,'Question Restrictions'!$C:$C,0))="All",ISNUMBER(SEARCH('Project Information'!$C$12,INDEX('Question Restrictions'!$F:$F,MATCH($B31,'Question Restrictions'!$C:$C,0))))),INDEX('Question Restrictions'!$G:$G,MATCH($B31,'Question Restrictions'!$C:$C,0))="Yes"),TRUE())
A32: 20 | B32: =INDEX(Translations!$D:$ZZ, MATCH(241,Translations!$A:$A,0), MATCH('Project Information'!$C$4,Translations!$D$1:$ZZ$1,0)) | C32: =INDEX(Translations!$D:$ZZ, MATCH(208,Translations!$A:$A,0), MATCH('Project Information'!$C$4,Translations!$D$1:$ZZ$1,0)) | D32: =INDEX(Translations!$D:$ZZ, MATCH(172,Translations!$A:$A,0), MATCH('Project Information'!$C$4,Translations!$D$1:$ZZ$1,0)) | H32: =IF(OR(TRIM(F32)="Evet",TRIM(F32)="Yes"),E32,IF(G32="","",E32*G32)) | K32: =IFERROR(AND(OR(INDEX('Question Restrictions'!$D:$D,MATCH($B32,'Question Restrictions'!$C:$C,0))="All",ISNUMBER(SEARCH('Project Information'!$C$10,INDEX('Question Restrictions'!$D:$D,MATCH($B32,'Question Restrictions'!$C:$C,0))))),OR(INDEX('Question Restrictions'!$E:$E,MATCH($B32,'Question Restrictions'!$C:$C,0))="All",ISNUMBER(SEARCH('Project Information'!$C$11,INDEX('Question Restrictions'!$E:$E,MATCH($B32,'Question Restrictions'!$C:$C,0))))),OR(INDEX('Question Restrictions'!$F:$F,MATCH($B32,'Question Restrictions'!$C:$C,0))="All",ISNUMBER(SEARCH('Project Information'!$C$12,INDEX('Question Restrictions'!$F:$F,MATCH($B32,'Question Restrictions'!$C:$C,0))))),INDEX('Question Restrictions'!$G:$G,MATCH($B32,'Question Restrictions'!$C:$C,0))="Yes"),TRUE())
A33: 21 | B33: =INDEX(Translations!$D:$ZZ, MATCH(242,Translations!$A:$A,0), MATCH('Project Information'!$C$4,Translations!$D$1:$ZZ$1,0)) | C33: =INDEX(Translations!$D:$ZZ, MATCH(194,Translations!$A:$A,0), MATCH('Project Information'!$C$4,Translations!$D$1:$ZZ$1,0)) | D33: =INDEX(Translations!$D:$ZZ, MATCH(172,Translations!$A:$A,0), MATCH('Project Information'!$C$4,Translations!$D$1:$ZZ$1,0)) | H33: =IF(OR(TRIM(F33)="Evet",TRIM(F33)="Yes"),E33,IF(G33="","",E33*G33)) | K33: =IFERROR(AND(OR(INDEX('Question Restrictions'!$D:$D,MATCH($B33,'Question Restrictions'!$C:$C,0))="All",ISNUMBER(SEARCH('Project Information'!$C$10,INDEX('Question Restrictions'!$D:$D,MATCH($B33,'Question Restrictions'!$C:$C,0))))),OR(INDEX('Question Restrictions'!$E:$E,MATCH($B33,'Question Restrictions'!$C:$C,0))="All",ISNUMBER(SEARCH('Project Information'!$C$11,INDEX('Question Restrictions'!$E:$E,MATCH($B33,'Question Restrictions'!$C:$C,0))))),OR(INDEX('Question Restrictions'!$F:$F,MATCH($B33,'Question Restrictions'!$C:$C,0))="All",ISNUMBER(SEARCH('Project Information'!$C$12,INDEX('Question Restrictions'!$F:$F,MATCH($B33,'Question Restrictions'!$C:$C,0))))),INDEX('Question Restrictions'!$G:$G,MATCH($B33,'Question Restrictions'!$C:$C,0))="Yes"),TRUE())
A34: 22 | B34: =INDEX(Translations!$D:$ZZ, MATCH(248,Translations!$A:$A,0), MATCH('Project Information'!$C$4,Translations!$D$1:$ZZ$1,0)) | C34: =INDEX(Translations!$D:$ZZ, MATCH(1021,Translations!$A:$A,0), MATCH('Project Information'!$C$4,Translations!$D$1:$ZZ$1,0)) | D34: =INDEX(Translations!$D:$ZZ, MATCH(172,Translations!$A:$A,0), MATCH('Project Information'!$C$4,Translations!$D$1:$ZZ$1,0)) | H34: =IF(OR(TRIM(F34)="Evet",TRIM(F34)="Yes"),E34,IF(G34="","",E34*G34)) | K34: =IFERROR(AND(OR(INDEX('Question Restrictions'!$D:$D,MATCH($B34,'Question Restrictions'!$C:$C,0))="All",ISNUMBER(SEARCH('Project Information'!$C$10,INDEX('Question Restrictions'!$D:$D,MATCH($B34,'Question Restrictions'!$C:$C,0))))),OR(INDEX('Question Restrictions'!$E:$E,MATCH($B34,'Question Restrictions'!$C:$C,0))="All",ISNUMBER(SEARCH('Project Information'!$C$11,INDEX('Question Restrictions'!$E:$E,MATCH($B34,'Question Restrictions'!$C:$C,0))))),OR(INDEX('Question Restrictions'!$F:$F,MATCH($B34,'Question Restrictions'!$C:$C,0))="All",ISNUMBER(SEARCH('Project Information'!$C$12,INDEX('Question Restrictions'!$F:$F,MATCH($B34,'Question Restrictions'!$C:$C,0))))),INDEX('Question Restrictions'!$G:$G,MATCH($B34,'Question Restrictions'!$C:$C,0))="Yes"),TRUE())
A35: 23 | B35: =INDEX(Translations!$D:$ZZ, MATCH(251,Translations!$A:$A,0), MATCH('Project Information'!$C$4,Translations!$D$1:$ZZ$1,0)) | C35: =INDEX(Translations!$D:$ZZ, MATCH(252,Translations!$A:$A,0), MATCH('Project Information'!$C$4,Translations!$D$1:$ZZ$1,0)) | D35: =INDEX(Translations!$D:$ZZ, MATCH(27,Translations!$A:$A,0), MATCH('Project Information'!$C$4,Translations!$D$1:$ZZ$1,0)) | H35: =IF(OR(TRIM(F35)="Evet",TRIM(F35)="Yes"),E35,IF(G35="","",E35*G35)) | K35: =IFERROR(AND(OR(INDEX('Question Restrictions'!$D:$D,MATCH($B35,'Question Restrictions'!$C:$C,0))="All",ISNUMBER(SEARCH('Project Information'!$C$10,INDEX('Question Restrictions'!$D:$D,MATCH($B35,'Question Restrictions'!$C:$C,0))))),OR(INDEX('Question Restrictions'!$E:$E,MATCH($B35,'Question Restrictions'!$C:$C,0))="All",ISNUMBER(SEARCH('Project Information'!$C$11,INDEX('Question Restrictions'!$E:$E,MATCH($B35,'Question Restrictions'!$C:$C,0))))),OR(INDEX('Question Restrictions'!$F:$F,MATCH($B35,'Question Restrictions'!$C:$C,0))="All",ISNUMBER(SEARCH('Project Information'!$C$12,INDEX('Question Restrictions'!$F:$F,MATCH($B35,'Question Restrictions'!$C:$C,0))))),INDEX('Question Restrictions'!$G:$G,MATCH($B35,'Question Restrictions'!$C:$C,0))="Yes"),TRUE())
A36: 24 | B36: =INDEX(Translations!$D:$ZZ, MATCH(267,Translations!$A:$A,0), MATCH('Project Information'!$C$4,Translations!$D$1:$ZZ$1,0)) | C36: =INDEX(Translations!$D:$ZZ, MATCH(268,Translations!$A:$A,0), MATCH('Project Information'!$C$4,Translations!$D$1:$ZZ$1,0)) | D36: =INDEX(Translations!$D:$ZZ, MATCH(172,Translations!$A:$A,0), MATCH('Project Information'!$C$4,Translations!$D$1:$ZZ$1,0)) | H36: =IF(OR(TRIM(F36)="Evet",TRIM(F36)="Yes"),E36,IF(G36="","",E36*G36)) | K36: =IFERROR(AND(OR(INDEX('Question Restrictions'!$D:$D,MATCH($B36,'Question Restrictions'!$C:$C,0))="All",ISNUMBER(SEARCH('Project Information'!$C$10,INDEX('Question Restrictions'!$D:$D,MATCH($B36,'Question Restrictions'!$C:$C,0))))),OR(INDEX('Question Restrictions'!$E:$E,MATCH($B36,'Question Restrictions'!$C:$C,0))="All",ISNUMBER(SEARCH('Project Information'!$C$11,INDEX('Question Restrictions'!$E:$E,MATCH($B36,'Question Restrictions'!$C:$C,0))))),OR(INDEX('Question Restrictions'!$F:$F,MATCH($B36,'Question Restrictions'!$C:$C,0))="All",ISNUMBER(SEARCH('Project Information'!$C$12,INDEX('Question Restrictions'!$F:$F,MATCH($B36,'Question Restrictions'!$C:$C,0))))),INDEX('Question Restrictions'!$G:$G,MATCH($B36,'Question Restrictions'!$C:$C,0))="Yes"),TRUE())

Sheet Module Selection
A1: Modül | B1: Var/Yok | C1: Ekip Sayısı | D1: Grup
A2: FI | B2: Yok | D2: S4Core
A3: CO | B3: Yok | D3: S4Core
A4: TRM | B4: Yok | D4: Advanced Solution
A5: CM | B5: Yok | D5: Advanced Solution
A6: FM | B6: Yok | D6: Advanced Solution
A7: RM | B7: Yok | D7: Advanced Solution
A8: RE/FX | B8: Yok | D8: Advanced Solution
A9: MM | B9: Yok | D9: S4Core
A10: PP | B10: Yok | D10: S4Core
A11: SD | B11: Yok | D11: S4Core
A12: QM | B12: Yok | D12: S4Core
A13: PM | B13: Yok | D13: S4Core
... A35: NTT Data POS | B35: Yok | D35: NTT Own IP
A37: Not:
A38: Varsayılan tüm modüller 'Var' gelir. Gerekmediklerini 'Yok' yapabilirsiniz. | B38: Yok | D38: S4Core

Sheet Localization Selection
A1: =INDEX(Translations!$D:$ZZ, MATCH(322,Translations!$A:$A,0), MATCH('Project Information'!$C$4,Translations!$D$1:$ZZ$1,0))
A3: =INDEX(Translations!$D:$ZZ, MATCH(323,Translations!$A:$A,0), MATCH('Project Information'!$C$4,Translations!$D$1:$ZZ$1,0)) | B3: =INDEX(Translations!$D:$ZZ, MATCH(68,Translations!$A:$A,0), MATCH('Project Information'!$C$4,Translations!$D$1:$ZZ$1,0))
A4: =INDEX(Translations!$D:$ZZ, MATCH(326,Translations!$A:$A,0), MATCH('Project Information'!$C$4,Translations!$D$1:$ZZ$1,0)) | B4: Yok
A5: =INDEX(Translations!$D:$ZZ, MATCH(327,Translations!$A:$A,0), MATCH('Project Information'!$C$4,Translations!$D$1:$ZZ$1,0)) | B5: Yok
A6: =INDEX(Translations!$D:$ZZ, MATCH(328,Translations!$A:$A,0), MATCH('Project Information'!$C$4,Translations!$D$1:$ZZ$1,0)) | B6: Yok
A7: =INDEX(Translations!$D:$ZZ, MATCH(329,Translations!$A:$A,0), MATCH('Project Information'!$C$4,Translations!$D$1:$ZZ$1,0)) | B7: Yok
A8: =INDEX(Translations!$D:$ZZ, MATCH(330,Translations!$A:$A,0), MATCH('Project Information'!$C$4,Translations!$D$1:$ZZ$1,0)) | B8: Yok
A9: =INDEX(Translations!$D:$ZZ, MATCH(363,Translations!$A:$A,0), MATCH('Project Information'!$C$4,Translations!$D$1:$ZZ$1,0)) | B9: Yok

Sheet Hypercare & Go Live Support
A1: =INDEX(Translations!$D:$ZZ, MATCH(67,Translations!$A:$A,0), MATCH('Project Information'!$C$4,Translations!$D$1:$ZZ$1,0)) | B1: =INDEX(Translations!$D:$ZZ, MATCH(294,Translations!$A:$A,0), MATCH('Project Information'!$C$4,Translations!$D$1:$ZZ$1,0)) | C1: =INDEX(Translations!$D:$ZZ, MATCH(295,Translations!$A:$A,0), MATCH('Project Information'!$C$4,Translations!$D$1:$ZZ$1,0)) | D1: =INDEX(Translations!$D:$ZZ, MATCH(296,Translations!$A:$A,0), MATCH('Project Information'!$C$4,Translations!$D$1:$ZZ$1,0)) | E1: =INDEX(Translations!$D:$ZZ, MATCH(297,Translations!$A:$A,0), MATCH('Project Information'!$C$4,Translations!$D$1:$ZZ$1,0)) | F1: =INDEX(Translations!$D:$ZZ, MATCH(298,Translations!$A:$A,0), MATCH('Project Information'!$C$4,Translations!$D$1:$ZZ$1,0)) | G1: =INDEX(Translations!$D:$ZZ, MATCH(299,Translations!$A:$A,0), MATCH('Project Information'!$C$4,Translations!$D$1:$ZZ$1,0))
A2: =IF(OR('Module Selection'!$B$2="Var",'Module Selection'!$B$2="Include"),'Module Selection'!$A$2,"") | B2: 2 | C2: 5 | D2: 1 | E2: 1 | F2: 60 | G2: =IF($A2="","",IF(COUNTA(B2:E2)=0,0,PRODUCT(B2:E2)))
A3: =IF(OR('Module Selection'!$B$3="Var",'Module Selection'!$B$3="Include"),'Module Selection'!$A$3,"") | B3: 2 | C3: 5 | D3: 1 | E3: 1 | F3: 40 | G3: =IF($A3="","",IF(COUNTA(B3:E3)=0,0,PRODUCT(B3:E3)))
A4: =IF(OR('Module Selection'!$B$4="Var",'Module Selection'!$B$4="Include"),'Module Selection'!$A$4,"") | G4: =IF($A4="","",IF(COUNTA(B4:E4)=0,0,PRODUCT(B4:E4)))
A5: =IF(OR('Module Selection'!$B$5="Var",'Module Selection'!$B$5="Include"),'Module Selection'!$A$5,"") | B5: 1 | C5: 4 | D5: 1 | E5: 1 | F5: 15 | G5: =IF($A5="","",IF(COUNTA(B5:E5)=0,0,PRODUCT(B5:E5)))
A6: =IF(OR('Module Selection'!$B$6="Var",'Module Selection'!$B$6="Include"),'Module Selection'!$A$6,"") | G6: =IF($A6="","",IF(COUNTA(B6:E6)=0,0,PRODUCT(B6:E6)))
A7: =IF(OR('Module Selection'!$B$7="Var",'Module Selection'!$B$7="Include"),'Module Selection'!$A$7,"") | G7: =IF($A7="","",IF(COUNTA(B7:E7)=0,0,PRODUCT(B7:E7)))
A8: =IF(OR('Module Selection'!$B$8="Var",'Module Selection'!$B$8="Include"),'Module Selection'!$A$8,"") | G8: =IF($A8="","",IF(COUNTA(B8:E8)=0,0,PRODUCT(B8:E8)))
A9: =IF(OR('Module Selection'!$B$9="Var",'Module Selection'!$B$9="Include"),'Module Selection'!$A$9,"") | B9: 2 | C9: 14 | D9: 1 | E9: 1 | F9: 80 | G9: =IF($A9="","",IF(COUNTA(B9:E9)=0,0,PRODUCT(B9:E9)))
A10: =IF(OR('Module Selection'!$B$10="Var",'Module Selection'!$B$10="Include"),'Module Selection'!$A$10,"") | B10: 2 | C10: 14 | D10: 1 | E10: 1 | F10: 80 | G10: =IF($A10="","",IF(COUNTA(B10:E10)=0,0,PRODUCT(B10:E10)))
A11: =IF(OR('Module Selection'!$B$11="Var",'Module Selection'!$B$11="Include"),'Module Selection'!$A$11,"") | B11: 2 | C11: 14 | D11: 1 | E11: 1 | F11: 80 | G11: =IF($A11="","",IF(COUNTA(B11:E11)=0,0,PRODUCT(B11:E11)))
A12: =IF(OR('Module Selection'!$B$12="Var",'Module Selection'!$B$12="Include"),'Module Selection'!$A$12,"") | B12: 2 | C12: 14 | D12: 1 | E12: 1 | F12: 60 | G12: =IF($A12="","",IF(COUNTA(B12:E12)=0,0,PRODUCT(B12:E12)))
A13: =IF(OR('Module Selection'!$B$13="Var",'Module Selection'!$B$13="Include"),'Module Selection'!$A$13,"") | B13: 2 | C13: 6 | D13: 1 | E13: 1 | F13: 30 | G13: =IF($A13="","",IF(COUNTA(B13:E13)=0,0,PRODUCT(B13:E13)))
A14: =IF(OR('Module Selection'!$B$14="Var",'Module Selection'!$B$14="Include"),'Module Selection'!$A$14,"") | B14: 2 | C14: 6 | D14: 1 | E14: 1 | F14: 30 | G14: =IF($A14="","",IF(COUNTA(B14:E14)=0,0,PRODUCT(B14:E14)))
A15: =IF(OR('Module Selection'!$B$15="Var",'Module Selection'!$B$15="Include"),'Module Selection'!$A$15,"") | B15: 2 | C15: 14 | D15: 1 | E15: 1 | F15: 60 | G15: =IF($A15="","",IF(COUNTA(B15:E15)=0,0,PRODUCT(B15:E15)))
A16: =IF(OR('Module Selection'!$B$16="Var",'Module Selection'!$B$16="Include"),'Module Selection'!$A$16,"") | G16: =IF($A16="","",IF(COUNTA(B16:E16)=0,0,PRODUCT(B16:E16)))
A17: =IF(OR('Module Selection'!$B$17="Var",'Module Selection'!$B$17="Include"),'Module Selection'!$A$17,"") | G17: =IF($A17="","",IF(COUNTA(B17:E17)=0,0,PRODUCT(B17:E17)))
A18: =IF(OR('Module Selection'!$B$18="Var",'Module Selection'!$B$18="Include"),'Module Selection'!$A$18,"") | G18: =IF($A18="","",IF(COUNTA(B18:E18)=0,0,PRODUCT(B18:E18)))
A19: =IF(OR('Module Selection'!$B$19="Var",'Module Selection'!$B$19="Include"),'Module Selection'!$A$19,"") | B19: 2 | C19: 4 | D19: 1 | E19: 1 | F19: 5 | G19: =IF($A19="","",IF(COUNTA(B19:E19)=0,0,PRODUCT(B19:E19)))
A20: =IF(OR('Module Selection'!$B$20="Var",'Module Selection'!$B$20="Include"),'Module Selection'!$A$20,"") | B20: 2 | C20: 5 | D20: 1 | E20: 1 | F20: 15 | G20: =IF($A20="","",IF(COUNTA(B20:E20)=0,0,PRODUCT(B20:E20)))
A21: =IF(OR('Module Selection'!$B$21="Var",'Module Selection'!$B$21="Include"),'Module Selection'!$A$21,"") | B21: 2 | C21: 5 | D21: 1 | E21: 1 | F21: 15 | G21: =IF($A21="","",IF(COUNTA(B21:E21)=0,0,PRODUCT(B21:E21)))
A22: =IF(OR('Module Selection'!$B$22="Var",'Module Selection'!$B$22="Include"),'Module Selection'!$A$22,"") | B22: 1 | C22: 5 | D22: 1 | E22: 1 | F22: 15 | G22: =IF($A22="","",IF(COUNTA(B22:E22)=0,0,PRODUCT(B22:E22)))
A23: =IF(OR('Module Selection'!$B$23="Var",'Module Selection'!$B$23="Include"),'Module Selection'!$A$23,"") | G23: =IF($A23="","",IF(COUNTA(B23:E23)=0,0,PRODUCT(B23:E23)))
A24: =IF(OR('Module Selection'!$B$24="Var",'Module Selection'!$B$24="Include"),'Module Selection'!$A$24,"") | G24: =IF($A24="","",IF(COUNTA(B24:E24)=0,0,PRODUCT(B24:E24)))
A25: =IF(OR('Module Selection'!$B$25="Var",'Module Selection'!$B$25="Include"),'Module Selection'!$A$25,"") | B25: 2 | C25: 3 | D25: 1 | E25: 1 | F25: 15 | G25: =IF($A25="","",IF(COUNTA(B25:E25)=0,0,PRODUCT(B25:E25)))
A26: =IF(OR('Module Selection'!$B$26="Var",'Module Selection'!$B$26="Include"),'Module Selection'!$A$26,"") | B26: 2 | C26: 3 | D26: 1 | E26: 1 | F26: 15 | G26: =IF($A26="","",IF(COUNTA(B26:E26)=0,0,PRODUCT(B26:E26)))
A27: =IF(OR('Module Selection'!$B$27="Var",'Module Selection'!$B$27="Include"),'Module Selection'!$A$27,"") | G27: =IF($A27="","",IF(COUNTA(B27:E27)=0,0,PRODUCT(B27:E27)))
A28: =IF(OR('Module Selection'!$B$28="Var",'Module Selection'!$B$28="Include"),'Module Selection'!$A$28,"") | G28: =IF($A28="","",IF(COUNTA(B28:E28)=0,0,PRODUCT(B28:E28)))
A29: =IF(OR('Module Selection'!$B$29="Var",'Module Selection'!$B$29="Include"),'Module Selection'!$A$29,"") | G29: =IF($A29="","",IF(COUNTA(B29:E29)=0,0,PRODUCT(B29:E29)))
A30: =IF(OR('Module Selection'!$B$30="Var",'Module Selection'!$B$30="Include"),'Module Selection'!$A$30,"") | G30: =IF($A30="","",IF(COUNTA(B30:E30)=0,0,PRODUCT(B30:E30)))
A31: =IF(OR('Module Selection'!$B$31="Var",'Module Selection'!$B$31="Include"),'Module Selection'!$A$31,"") | B31: 1 | C31: 5 | D31: 1 | E31: 1 | F31: 15 | G31: =IF($A31="","",IF(COUNTA(B31:E31)=0,0,PRODUCT(B31:E31)))
A32: =IF(OR('Module Selection'!$B$32="Var",'Module Selection'!$B$32="Include"),'Module Selection'!$A$32,"") | G32: =IF($A32="","",IF(COUNTA(B32:E32)=0,0,PRODUCT(B32:E32)))
A33: =IF(OR('Module Selection'!$B$33="Var",'Module Selection'!$B$33="Include"),'Module Selection'!$A$33,"") | G33: =IF($A33="","",IF(COUNTA(B33:E33)=0,0,PRODUCT(B33:E33)))
A34: =IF(OR('Module Selection'!$B$34="Var",'Module Selection'!$B$34="Include"),'Module Selection'!$A$34,"") | G34: =IF($A34="","",IF(COUNTA(B34:E34)=0,0,PRODUCT(B34:E34)))
A35: =IF(OR('Module Selection'!$B$35="Var",'Module Selection'!$B$35="Include"),'Module Selection'!$A$35,"") | G35: =IF($A35="","",IF(COUNTA(B35:E35)=0,0,PRODUCT(B35:E35)))

Sheet Final Effort
A1: =INDEX(Translations!$D:$ZZ, MATCH(67,Translations!$A:$A,0), MATCH('Project Information'!$C$4,Translations!$D$1:$ZZ$1,0)) | B1: =INDEX(Translations!$D:$ZZ, MATCH(75,Translations!$A:$A,0), MATCH('Project Information'!$C$4,Translations!$D$1:$ZZ$1,0)) | C1: =INDEX(Translations!$D:$ZZ, MATCH(76,Translations!$A:$A,0), MATCH('Project Information'!$C$4,Translations!$D$1:$ZZ$1,0)) | D1: =INDEX(Translations!$D:$ZZ, MATCH(77,Translations!$A:$A,0), MATCH('Project Information'!$C$4,Translations!$D$1:$ZZ$1,0)) | E1: =INDEX(Translations!$D:$ZZ, MATCH(78,Translations!$A:$A,0), MATCH('Project Information'!$C$4,Translations!$D$1:$ZZ$1,0)) | F1: =INDEX(Translations!$D:$ZZ, MATCH(79,Translations!$A:$A,0), MATCH('Project Information'!$C$4,Translations!$D$1:$ZZ$1,0)) | G1: =INDEX(Translations!$D:$ZZ, MATCH(80,Translations!$A:$A,0), MATCH('Project Information'!$C$4,Translations!$D$1:$ZZ$1,0)) | H1: =INDEX(Translations!$D:$ZZ, MATCH(81,Translations!$A:$A,0), MATCH('Project Information'!$C$4,Translations!$D$1:$ZZ$1,0)) | I1: =INDEX(Translations!$D:$ZZ, MATCH(82,Translations!$A:$A,0), MATCH('Project Information'!$C$4,Translations!$D$1:$ZZ$1,0)) | J1: =INDEX(Translations!$D:$ZZ, MATCH(83,Translations!$A:$A,0), MATCH('Project Information'!$C$4,Translations!$D$1:$ZZ$1,0)) | K1: =INDEX(Translations!$D:$ZZ, MATCH(84,Translations!$A:$A,0), MATCH('Project Information'!$C$4,Translations!$D$1:$ZZ$1,0)) | L1: =INDEX(Translations!$D:$ZZ, MATCH(85,Translations!$A:$A,0), MATCH('Project Information'!$C$4,Translations!$D$1:$ZZ$1,0)) | M1: =INDEX(Translations!$D:$ZZ, MATCH(86,Translations!$A:$A,0), MATCH('Project Information'!$C$4,Translations!$D$1:$ZZ$1,0)) | N1: =INDEX(Translations!$D:$ZZ, MATCH(87,Translations!$A:$A,0), MATCH('Project Information'!$C$4,Translations!$D$1:$ZZ$1,0)) | O1: =INDEX(Translations!$D:$ZZ, MATCH(88,Translations!$A:$A,0), MATCH('Project Information'!$C$4,Translations!$D$1:$ZZ$1,0)) | P1: =INDEX(Translations!$D:$ZZ, MATCH(89,Translations!$A:$A,0), MATCH('Project Information'!$C$4,Translations!$D$1:$ZZ$1,0)) | Q1: =INDEX(Translations!$D:$ZZ, MATCH(90,Translations!$A:$A,0), MATCH('Project Information'!$C$4,Translations!$D$1:$ZZ$1,0)) | AZ1: =INDEX(Translations!$D:$ZZ, MATCH(300,Translations!$A:$A,0), MATCH('Project Information'!$C$4,Translations!$D$1:$ZZ$1,0)) | BA1: =INDEX(Translations!$D:$ZZ, MATCH(276,Translations!$A:$A,0), MATCH('Project Information'!$C$4,Translations!$D$1:$ZZ$1,0)) | BB1: =INDEX(Translations!$D:$ZZ, MATCH(67,Translations!$A:$A,0), MATCH('Project Information'!$C$4,Translations!$D$1:$ZZ$1,0)) | BC1: =INDEX(Translations!$D:$ZZ, MATCH(301,Translations!$A:$A,0), MATCH('Project Information'!$C$4,Translations!$D$1:$ZZ$1,0)) | BD1: =INDEX(Translations!$D:$ZZ, MATCH(302,Translations!$A:$A,0), MATCH('Project Information'!$C$4,Translations!$D$1:$ZZ$1,0)) | BE1: =INDEX(Translations!$D:$ZZ, MATCH(303,Translations!$A:$A,0), MATCH('Project Information'!$C$4,Translations!$D$1:$ZZ$1,0)) | BF1: =INDEX(Translations!$D:$ZZ, MATCH(304,Translations!$A:$A,0), MATCH('Project Information'!$C$4,Translations!$D$1:$ZZ$1,0)) | BH1: =INDEX(Translations!$D:$ZZ, MATCH(300,Translations!$A:$A,0), MATCH('Project Information'!$C$4,Translations!$D$1:$ZZ$1,0)) | BI1: =INDEX(Translations!$D:$ZZ, MATCH(276,Translations!$A:$A,0), MATCH('Project Information'!$C$4,Translations!$D$1:$ZZ$1,0)) | BJ1: =INDEX(Translations!$D:$ZZ, MATCH(67,Translations!$A:$A,0), MATCH('Project Information'!$C$4,Translations!$D$1:$ZZ$1,0)) | BK1: =INDEX(Translations!$D:$ZZ, MATCH(301,Translations!$A:$A,0), MATCH('Project Information'!$C$4,Translations!$D$1:$ZZ$1,0)) | BL1: =INDEX(Translations!$D:$ZZ, MATCH(302,Translations!$A:$A,0), MATCH('Project Information'!$C$4,Translations!$D$1:$ZZ$1,0)) | BM1: =INDEX(Translations!$D:$ZZ, MATCH(303,Translations!$A:$A,0), MATCH('Project Information'!$C$4,Translations!$D$1:$ZZ$1,0)) | BN1: =INDEX(Translations!$D:$ZZ, MATCH(304,Translations!$A:$A,0), MATCH('Project Information'!$C$4,Translations!$D$1:$ZZ$1,0))
A2: ='Project Definitions'!$D$2 | B2: =IF(AND('Module Selection'!$B2<>"Var",'Module Selection'!$B2<>"Include"),"",IF($A2="","",IFERROR(INDEX('Fixed Days'!$B:$P,MATCH('Project Information'!$C$11&"|"&IF(Scope!$J$9="S","SMALL",IF(Scope!$J$9="M","MEDIUM",IF(Scope!$J$9="L","LARGE","X-LARGE")))&"|"&$A2,'Fixed Days'!$AA:$AA,0),MATCH(B$1,'Fixed Days'!$B$3:$P$3,0)),0)*IFERROR(IF(OR(TRIM("")="Evet",TRIM("")="Yes"),MAX(N('Module Selection'!$C2),1),1),1)+IFERROR(SUMIFS($BF$2:$BF$700,$BB$2:$BB$700,$A2,$BC$2:$BC$700,B$1),0)+0)) | C2: =IF(AND('Module Selection'!$B2<>"Var",'Module Selection'!$B2<>"Include"),"",IF($A2="","",IFERROR(INDEX('Fixed Days'!$B:$P,MATCH('Project Information'!$C$11&"|"&IF(Scope!$J$9="S","SMALL",IF(Scope!$J$9="M","MEDIUM",IF(Scope!$J$9="L","LARGE","X-LARGE")))&"|"&$A2,'Fixed Days'!$AA:$AA,0),MATCH(C$1,'Fixed Days'!$B$3:$P$3,0)),0)*IFERROR(IF(OR(TRIM("")="Evet",TRIM("")="Yes"),MAX(N('Module Selection'!$C2),1),1),1)+IFERROR(SUMIFS($BF$2:$BF$700,$BB$2:$BB$700,$A2,$BC$2:$BC$700,C$1),0)+0)) | D2: =IF(AND('Module Selection'!$B2<>"Var",'Module Selection'!$B2<>"Include"),"",IF($A2="","",IFERROR(INDEX('Fixed Days'!$B:$P,MATCH('Project Information'!$C$11&"|"&IF(Scope!$J$9="S","SMALL",IF(Scope!$J$9="M","MEDIUM",IF(Scope!$J$9="L","LARGE","X-LARGE")))&"|"&$A2,'Fixed Days'!$AA:$AA,0),MATCH(D$1,'Fixed Days'!$B$3:$P$3,0)),0)*IFERROR(IF(OR(TRIM("")="Evet",TRIM("")="Yes"),MAX(N('Module Selection'!$C2),1),1),1)+IFERROR(SUMIFS($BF$2:$BF$700,$BB$2:$BB$700,$A2,$BC$2:$BC$700,D$1),0)+0)) | E2: =IF(AND('Module Selection'!$B2<>"Var",'Module Selection'!$B2<>"Include"),"",IF($A2="","",IFERROR(INDEX('Fixed Days'!$B:$P,MATCH('Project Information'!$C$11&"|"&IF(Scope!$J$9="S","SMALL",IF(Scope!$J$9="M","MEDIUM",IF(Scope!$J$9="L","LARGE","X-LARGE")))&"|"&$A2,'Fixed Days'!$AA:$AA,0),MATCH(E$1,'Fixed Days'!$B$3:$P$3,0)),0)*IFERROR(IF(OR(TRIM("")="Evet",TRIM("")="Yes"),MAX(N('Module Selection'!$C2),1),1),1)+IFERROR(SUMIFS($BF$2:$BF$700,$BB$2:$BB$700,$A2,$BC$2:$BC$700,E$1),0)+0)) | F2: =IF(AND('Module Selection'!$B2<>"Var",'Module Selection'!$B2<>"Include"),"",IF($A2="","",IFERROR(INDEX('Fixed Days'!$B:$P,MATCH('Project Information'!$C$11&"|"&IF(Scope!$J$9="S","SMALL",IF(Scope!$J$9="M","MEDIUM",IF(Scope!$J$9="L","LARGE","X-LARGE")))&"|"&$A2,'Fixed Days'!$AA:$AA,0),MATCH(F$1,'Fixed Days'!$B$3:$P$3,0)),0)*IFERROR(IF(OR(TRIM("")="Evet",TRIM("")="Yes"),MAX(N('Module Selection'!$C2),1),1),1)+IFERROR(SUMIFS($BF$2:$BF$700,$BB$2:$BB$700,$A2,$BC$2:$BC$700,F$1),0)+0)) | G2: =IF(AND('Module Selection'!$B2<>"Var",'Module Selection'!$B2<>"Include"),"",IF($A2="","",IFERROR(INDEX('Fixed Days'!$B:$P,MATCH('Project Information'!$C$11&"|"&IF(Scope!$J$9="S","SMALL",IF(Scope!$J$9="M","MEDIUM",IF(Scope!$J$9="L","LARGE","X-LARGE")))&"|"&$A2,'Fixed Days'!$AA:$AA,0),MATCH(G$1,'Fixed Days'!$B$3:$P$3,0)),0)*IFERROR(IF(OR(TRIM("")="Evet",TRIM("")="Yes"),MAX(N('Module Selection'!$C2),1),1),1)+IFERROR(SUMIFS($BF$2:$BF$700,$BB$2:$BB$700,$A2,$BC$2:$BC$700,G$1),0)+0)) | H2: =IF(AND('Module Selection'!$B2<>"Var",'Module Selection'!$B2<>"Include"),"",IF($A2="","",IFERROR(INDEX('Fixed Days'!$B:$P,MATCH('Project Information'!$C$11&"|"&IF(Scope!$J$9="S","SMALL",IF(Scope!$J$9="M","MEDIUM",IF(Scope!$J$9="L","LARGE","X-LARGE")))&"|"&$A2,'Fixed Days'!$AA:$AA,0),MATCH(H$1,'Fixed Days'!$B$3:$P$3,0)),0)*IFERROR(IF(OR(TRIM("")="Evet",TRIM("")="Yes"),MAX(N('Module Selection'!$C2),1),1),1)+IFERROR(SUMIFS($BF$2:$BF$700,$BB$2:$BB$700,$A2,$BC$2:$BC$700,H$1),0)+0)) | I2: =IF(AND('Module Selection'!$B2<>"Var",'Module Selection'!$B2<>"Include"),"",IF($A2="","",IFERROR(INDEX('Fixed Days'!$B:$P,MATCH('Project Information'!$C$11&"|"&IF(Scope!$J$9="S","SMALL",IF(Scope!$J$9="M","MEDIUM",IF(Scope!$J$9="L","LARGE","X-LARGE")))&"|"&$A2,'Fixed Days'!$AA:$AA,0),MATCH(I$1,'Fixed Days'!$B$3:$P$3,0)),0)*IFERROR(IF(OR(TRIM("")="Evet",TRIM("")="Yes"),MAX(N('Module Selection'!$C2),1),1),1)+IFERROR(SUMIFS($BF$2:$BF$700,$BB$2:$BB$700,$A2,$BC$2:$BC$700,I$1),0)+0)) | ... N2: =IF(AND('Module Selection'!$B2<>"Var",'Module Selection'!$B2<>"Include"),"",IF($A2="","",IFERROR(INDEX('Fixed Days'!$B:$P,MATCH('Project Information'!$C$11&"|"&IF(Scope!$J$9="S","SMALL",IF(Scope!$J$9="M","MEDIUM",IF(Scope!$J$9="L","LARGE","X-LARGE")))&"|"&$A2,'Fixed Days'!$AA:$AA,0),MATCH(N$1,'Fixed Days'!$B$3:$P$3,0)),0)*IFERROR(IF(OR(TRIM("")="Evet",TRIM("")="Yes"),MAX(N('Module Selection'!$C2),1),1),1)+IFERROR(SUMIFS($BF$2:$BF$700,$BB$2:$BB$700,$A2,$BC$2:$BC$700,N$1),0)+0)) | O2: =IF(AND('Module Selection'!$B2<>"Var",'Module Selection'!$B2<>"Include"),"",IF($A2="","",IFERROR(INDEX('Fixed Days'!$B:$P,MATCH('Project Information'!$C$11&"|"&IF(Scope!$J$9="S","SMALL",IF(Scope!$J$9="M","MEDIUM",IF(Scope!$J$9="L","LARGE","X-LARGE")))&"|"&$A2,'Fixed Days'!$AA:$AA,0),MATCH(O$1,'Fixed Days'!$B$3:$P$3,0)),0)*IFERROR(IF(OR(TRIM("")="Evet",TRIM("")="Yes"),MAX(N('Module Selection'!$C2),1),1),1)+IFERROR(SUMIFS($BF$2:$BF$700,$BB$2:$BB$700,$A2,$BC$2:$BC$700,O$1),0)+IFERROR(INDEX('Hypercare & Go Live Support'!$G:$G,MATCH($A2,'Hypercare & Go Live Support'!$A:$A,0)),0))) | P2: =IF(AND('Module Selection'!$B2<>"Var",'Module Selection'!$B2<>"Include"),"",IF($A2="","",IFERROR(INDEX('Fixed Days'!$B:$P,MATCH('Project Information'!$C$11&"|"&IF(Scope!$J$9="S","SMALL",IF(Scope!$J$9="M","MEDIUM",IF(Scope!$J$9="L","LARGE","X-LARGE")))&"|"&$A2,'Fixed Days'!$AA:$AA,0),MATCH(P$1,'Fixed Days'!$B$3:$P$3,0)),0)*IFERROR(IF(OR(TRIM("")="Evet",TRIM("")="Yes"),MAX(N('Module Selection'!$C2),1),1),1)+IFERROR(SUMIFS($BF$2:$BF$700,$BB$2:$BB$700,$A2,$BC$2:$BC$700,P$1),0)+IFERROR(INDEX('Hypercare & Go Live Support'!$F:$F,MATCH($A2,'Hypercare & Go Live Support'!$A:$A,0)),0))) | Q2: =SUM(B2:P2) | AZ2: =INDEX(Translations!$D:$ZZ, MATCH(305,Translations!$A:$A,0), MATCH('Project Information'!$C$4,Translations!$D$1:$ZZ$1,0)) | BA2: =INDEX(Translations!$D:$ZZ, MATCH(32,Translations!$A:$A,0), MATCH('Project Information'!$C$4,Translations!$D$1:$ZZ$1,0)) | BB2: =INDEX(Translations!$D:$ZZ, MATCH(343,Translations!$A:$A,0), MATCH('Project Information'!$C$4,Translations!$D$1:$ZZ$1,0)) | BC2: =INDEX(Translations!$D:$ZZ, MATCH(75,Translations!$A:$A,0), MATCH('Project Information'!$C$4,Translations!$D$1:$ZZ$1,0)) | BD2: =IF(OR(TRIM("")="Evet",TRIM("")="Yes"),1,0) | BE2: 3 | BF2: =BD2*BE2 | BH2: =INDEX(Translations!$D:$ZZ, MATCH(306,Translations!$A:$A,0), MATCH('Project Information'!$C$4,Translations!$D$1:$ZZ$1,0)) | BI2: =INDEX(Translations!$D:$ZZ, MATCH(251,Translations!$A:$A,0), MATCH('Project Information'!$C$4,Translations!$D$1:$ZZ$1,0)) | BJ2: =INDEX(Translations!$D:$ZZ, MATCH(346,Translations!$A:$A,0), MATCH('Project Information'!$C$4,Translations!$D$1:$ZZ$1,0)) | BK2: =INDEX(Translations!$D:$ZZ, MATCH(78,Translations!$A:$A,0), MATCH('Project Information'!$C$4,Translations!$D$1:$ZZ$1,0)) | BL2: =MAX(N(Development!$G$35),0) | BM2: 12 | BN2: =BL2*BM2
A3: ='Project Definitions'!$D$3 | B3: =IF(AND('Module Selection'!$B3<>"Var",'Module Selection'!$B3<>"Include"),"",IF($A3="","",IFERROR(INDEX('Fixed Days'!$B:$P,MATCH('Project Information'!$C$11&"|"&IF(Scope!$J$9="S","SMALL",IF(Scope!$J$9="M","MEDIUM",IF(Scope!$J$9="L","LARGE","X-LARGE")))&"|"&$A3,'Fixed Days'!$AA:$AA,0),MATCH(B$1,'Fixed Days'!$B$3:$P$3,0)),0)*IFERROR(IF(OR(TRIM("")="Evet",TRIM("")="Yes"),MAX(N('Module Selection'!$C3),1),1),1)+IFERROR(SUMIFS($BF$2:$BF$700,$BB$2:$BB$700,$A3,$BC$2:$BC$700,B$1),0)+0)) | C3: =IF(AND('Module Selection'!$B3<>"Var",'Module Selection'!$B3<>"Include"),"",IF($A3="","",IFERROR(INDEX('Fixed Days'!$B:$P,MATCH('Project Information'!$C$11&"|"&IF(Scope!$J$9="S","SMALL",IF(Scope!$J$9="M","MEDIUM",IF(Scope!$J$9="L","LARGE","X-LARGE")))&"|"&$A3,'Fixed Days'!$AA:$AA,0),MATCH(C$1,'Fixed Days'!$B$3:$P$3,0)),0)*IFERROR(IF(OR(TRIM("")="Evet",TRIM("")="Yes"),MAX(N('Module Selection'!$C3),1),1),1)+IFERROR(SUMIFS($BF$2:$BF$700,$BB$2:$BB$700,$A3,$BC$2:$BC$700,C$1),0)+0)) | D3: =IF(AND('Module Selection'!$B3<>"Var",'Module Selection'!$B3<>"Include"),"",IF($A3="","",IFERROR(INDEX('Fixed Days'!$B:$P,MATCH('Project Information'!$C$11&"|"&IF(Scope!$J$9="S","SMALL",IF(Scope!$J$9="M","MEDIUM",IF(Scope!$J$9="L","LARGE","X-LARGE")))&"|"&$A3,'Fixed Days'!$AA:$AA,0),MATCH(D$1,'Fixed Days'!$B$3:$P$3,0)),0)*IFERROR(IF(OR(TRIM("")="Evet",TRIM("")="Yes"),MAX(N('Module Selection'!$C3),1),1),1)+IFERROR(SUMIFS($BF$2:$BF$700,$BB$2:$BB$700,$A3,$BC$2:$BC$700,D$1),0)+0)) | E3: =IF(AND('Module Selection'!$B3<>"Var",'Module Selection'!$B3<>"Include"),"",IF($A3="","",IFERROR(INDEX('Fixed Days'!$B:$P,MATCH('Project Information'!$C$11&"|"&IF(Scope!$J$9="S","SMALL",IF(Scope!$J$9="M","MEDIUM",IF(Scope!$J$9="L","LARGE","X-LARGE")))&"|"&$A3,'Fixed Days'!$AA:$AA,0),MATCH(E$1,'Fixed Days'!$B$3:$P$3,0)),0)*IFERROR(IF(OR(TRIM("")="Evet",TRIM("")="Yes"),MAX(N('Module Selection'!$C3),1),1),1)+IFERROR(SUMIFS($BF$2:$BF$700,$BB$2:$BB$700,$A3,$BC$2:$BC$700,E$1),0)+0)) | F3: =IF(AND('Module Selection'!$B3<>"Var",'Module Selection'!$B3<>"Include"),"",IF($A3="","",IFERROR(INDEX('Fixed Days'!$B:$P,MATCH('Project Information'!$C$11&"|"&IF(Scope!$J$9="S","SMALL",IF(Scope!$J$9="M","MEDIUM",IF(Scope!$J$9="L","LARGE","X-LARGE")))&"|"&$A3,'Fixed Days'!$AA:$AA,0),MATCH(F$1,'Fixed Days'!$B$3:$P$3,0)),0)*IFERROR(IF(OR(TRIM("")="Evet",TRIM("")="Yes"),MAX(N('Module Selection'!$C3),1),1),1)+IFERROR(SUMIFS($BF$2:$BF$700,$BB$2:$BB$700,$A3,$BC$2:$BC$700,F$1),0)+0)) | G3: =IF(AND('Module Selection'!$B3<>"Var",'Module Selection'!$B3<>"Include"),"",IF($A3="","",IFERROR(INDEX('Fixed Days'!$B:$P,MATCH('Project Information'!$C$11&"|"&IF(Scope!$J$9="S","SMALL",IF(Scope!$J$9="M","MEDIUM",IF(Scope!$J$9="L","LARGE","X-LARGE")))&"|"&$A3,'Fixed Days'!$AA:$AA,0),MATCH(G$1,'Fixed Days'!$B$3:$P$3,0)),0)*IFERROR(IF(OR(TRIM("")="Evet",TRIM("")="Yes"),MAX(N('Module Selection'!$C3),1),1),1)+IFERROR(SUMIFS($BF$2:$BF$700,$BB$2:$BB$700,$A3,$BC$2:$BC$700,G$1),0)+0)) | H3: =IF(AND('Module Selection'!$B3<>"Var",'Module Selection'!$B3<>"Include"),"",IF($A3="","",IFERROR(INDEX('Fixed Days'!$B:$P,MATCH('Project Information'!$C$11&"|"&IF(Scope!$J$9="S","SMALL",IF(Scope!$J$9="M","MEDIUM",IF(Scope!$J$9="L","LARGE","X-LARGE")))&"|"&$A3,'Fixed Days'!$AA:$AA,0),MATCH(H$1,'Fixed Days'!$B$3:$P$3,0)),0)*IFERROR(IF(OR(TRIM("")="Evet",TRIM("")="Yes"),MAX(N('Module Selection'!$C3),1),1),1)+IFERROR(SUMIFS($BF$2:$BF$700,$BB$2:$BB$700,$A3,$BC$2:$BC$700,H$1),0)+0)) | I3: =IF(AND('Module Selection'!$B3<>"Var",'Module Selection'!$B3<>"Include"),"",IF($A3="","",IFERROR(INDEX('Fixed Days'!$B:$P,MATCH('Project Information'!$C$11&"|"&IF(Scope!$J$9="S","SMALL",IF(Scope!$J$9="M","MEDIUM",IF(Scope!$J$9="L","LARGE","X-LARGE")))&"|"&$A3,'Fixed Days'!$AA:$AA,0),MATCH(I$1,'Fixed Days'!$B$3:$P$3,0)),0)*IFERROR(IF(OR(TRIM("")="Evet",TRIM("")="Yes"),MAX(N('Module Selection'!$C3),1),1),1)+IFERROR(SUMIFS($BF$2:$BF$700,$BB$2:$BB$700,$A3,$BC$2:$BC$700,I$1),0)+0)) | ... N3: =IF(AND('Module Selection'!$B3<>"Var",'Module Selection'!$B3<>"Include"),"",IF($A3="","",IFERROR(INDEX('Fixed Days'!$B:$P,MATCH('Project Information'!$C$11&"|"&IF(Scope!$J$9="S","SMALL",IF(Scope!$J$9="M","MEDIUM",IF(Scope!$J$9="L","LARGE","X-LARGE")))&"|"&$A3,'Fixed Days'!$AA:$AA,0),MATCH(N$1,'Fixed Days'!$B$3:$P$3,0)),0)*IFERROR(IF(OR(TRIM("")="Evet",TRIM("")="Yes"),MAX(N('Module Selection'!$C3),1),1),1)+IFERROR(SUMIFS($BF$2:$BF$700,$BB$2:$BB$700,$A3,$BC$2:$BC$700,N$1),0)+0)) | O3: =IF(AND('Module Selection'!$B3<>"Var",'Module Selection'!$B3<>"Include"),"",IF($A3="","",IFERROR(INDEX('Fixed Days'!$B:$P,MATCH('Project Information'!$C$11&"|"&IF(Scope!$J$9="S","SMALL",IF(Scope!$J$9="M","MEDIUM",IF(Scope!$J$9="L","LARGE","X-LARGE")))&"|"&$A3,'Fixed Days'!$AA:$AA,0),MATCH(O$1,'Fixed Days'!$B$3:$P$3,0)),0)*IFERROR(IF(OR(TRIM("")="Evet",TRIM("")="Yes"),MAX(N('Module Selection'!$C3),1),1),1)+IFERROR(SUMIFS($BF$2:$BF$700,$BB$2:$BB$700,$A3,$BC$2:$BC$700,O$1),0)+IFERROR(INDEX('Hypercare & Go Live Support'!$G:$G,MATCH($A3,'Hypercare & Go Live Support'!$A:$A,0)),0))) | P3: =IF(AND('Module Selection'!$B3<>"Var",'Module Selection'!$B3<>"Include"),"",IF($A3="","",IFERROR(INDEX('Fixed Days'!$B:$P,MATCH('Project Information'!$C$11&"|"&IF(Scope!$J$9="S","SMALL",IF(Scope!$J$9="M","MEDIUM",IF(Scope!$J$9="L","LARGE","X-LARGE")))&"|"&$A3,'Fixed Days'!$AA:$AA,0),MATCH(P$1,'Fixed Days'!$B$3:$P$3,0)),0)*IFERROR(IF(OR(TRIM("")="Evet",TRIM("")="Yes"),MAX(N('Module Selection'!$C3),1),1),1)+IFERROR(SUMIFS($BF$2:$BF$700,$BB$2:$BB$700,$A3,$BC$2:$BC$700,P$1),0)+IFERROR(INDEX('Hypercare & Go Live Support'!$F:$F,MATCH($A3,'Hypercare & Go Live Support'!$A:$A,0)),0))) | Q3: =SUM(B3:P3) | AZ3: =INDEX(Translations!$D:$ZZ, MATCH(305,Translations!$A:$A,0), MATCH('Project Information'!$C$4,Translations!$D$1:$ZZ$1,0)) | BA3: =INDEX(Translations!$D:$ZZ, MATCH(32,Translations!$A:$A,0), MATCH('Project Information'!$C$4,Translations!$D$1:$ZZ$1,0)) | BB3: =INDEX(Translations!$D:$ZZ, MATCH(343,Translations!$A:$A,0), MATCH('Project Information'!$C$4,Translations!$D$1:$ZZ$1,0)) | BC3: =INDEX(Translations!$D:$ZZ, MATCH(76,Translations!$A:$A,0), MATCH('Project Information'!$C$4,Translations!$D$1:$ZZ$1,0)) | BD3: =IF(OR(TRIM("")="Evet",TRIM("")="Yes"),1,0) | BE3: 1 | BF3: =BD3*BE3 | BH3: =INDEX(Translations!$D:$ZZ, MATCH(306,Translations!$A:$A,0), MATCH('Project Information'!$C$4,Translations!$D$1:$ZZ$1,0)) | BI3: =INDEX(Translations!$D:$ZZ, MATCH(251,Translations!$A:$A,0), MATCH('Project Information'!$C$4,Translations!$D$1:$ZZ$1,0)) | BJ3: =INDEX(Translations!$D:$ZZ, MATCH(343,Translations!$A:$A,0), MATCH('Project Information'!$C$4,Translations!$D$1:$ZZ$1,0)) | BK3: =INDEX(Translations!$D:$ZZ, MATCH(75,Translations!$A:$A,0), MATCH('Project Information'!$C$4,Translations!$D$1:$ZZ$1,0)) | BL3: =MAX(N(Development!$G$35),0) | BM3: 3 | BN3: =BL3*BM3
A4: ='Project Definitions'!$D$4 | B4: =IF(AND('Module Selection'!$B4<>"Var",'Module Selection'!$B4<>"Include"),"",IF($A4="","",IFERROR(INDEX('Fixed Days'!$B:$P,MATCH('Project Information'!$C$11&"|"&IF(Scope!$J$9="S","SMALL",IF(Scope!$J$9="M","MEDIUM",IF(Scope!$J$9="L","LARGE","X-LARGE")))&"|"&$A4,'Fixed Days'!$AA:$AA,0),MATCH(B$1,'Fixed Days'!$B$3:$P$3,0)),0)*IFERROR(IF(OR(TRIM("")="Evet",TRIM("")="Yes"),MAX(N('Module Selection'!$C4),1),1),1)+IFERROR(SUMIFS($BF$2:$BF$700,$BB$2:$BB$700,$A4,$BC$2:$BC$700,B$1),0)+0)) | C4: =IF(AND('Module Selection'!$B4<>"Var",'Module Selection'!$B4<>"Include"),"",IF($A4="","",IFERROR(INDEX('Fixed Days'!$B:$P,MATCH('Project Information'!$C$11&"|"&IF(Scope!$J$9="S","SMALL",IF(Scope!$J$9="M","MEDIUM",IF(Scope!$J$9="L","LARGE","X-LARGE")))&"|"&$A4,'Fixed Days'!$AA:$AA,0),MATCH(C$1,'Fixed Days'!$B$3:$P$3,0)),0)*IFERROR(IF(OR(TRIM("")="Evet",TRIM("")="Yes"),MAX(N('Module Selection'!$C4),1),1),1)+IFERROR(SUMIFS($BF$2:$BF$700,$BB$2:$BB$700,$A4,$BC$2:$BC$700,C$1),0)+0)) | D4: =IF(AND('Module Selection'!$B4<>"Var",'Module Selection'!$B4<>"Include"),"",IF($A4="","",IFERROR(INDEX('Fixed Days'!$B:$P,MATCH('Project Information'!$C$11&"|"&IF(Scope!$J$9="S","SMALL",IF(Scope!$J$9="M","MEDIUM",IF(Scope!$J$9="L","LARGE","X-LARGE")))&"|"&$A4,'Fixed Days'!$AA:$AA,0),MATCH(D$1,'Fixed Days'!$B$3:$P$3,0)),0)*IFERROR(IF(OR(TRIM("")="Evet",TRIM("")="Yes"),MAX(N('Module Selection'!$C4),1),1),1)+IFERROR(SUMIFS($BF$2:$BF$700,$BB$2:$BB$700,$A4,$BC$2:$BC$700,D$1),0)+0)) | E4: =IF(AND('Module Selection'!$B4<>"Var",'Module Selection'!$B4<>"Include"),"",IF($A4="","",IFERROR(INDEX('Fixed Days'!$B:$P,MATCH('Project Information'!$C$11&"|"&IF(Scope!$J$9="S","SMALL",IF(Scope!$J$9="M","MEDIUM",IF(Scope!$J$9="L","LARGE","X-LARGE")))&"|"&$A4,'Fixed Days'!$AA:$AA,0),MATCH(E$1,'Fixed Days'!$B$3:$P$3,0)),0)*IFERROR(IF(OR(TRIM("")="Evet",TRIM("")="Yes"),MAX(N('Module Selection'!$C4),1),1),1)+IFERROR(SUMIFS($BF$2:$BF$700,$BB$2:$BB$700,$A4,$BC$2:$BC$700,E$1),0)+0)) | F4: =IF(AND('Module Selection'!$B4<>"Var",'Module Selection'!$B4<>"Include"),"",IF($A4="","",IFERROR(INDEX('Fixed Days'!$B:$P,MATCH('Project Information'!$C$11&"|"&IF(Scope!$J$9="S","SMALL",IF(Scope!$J$9="M","MEDIUM",IF(Scope!$J$9="L","LARGE","X-LARGE")))&"|"&$A4,'Fixed Days'!$AA:$AA,0),MATCH(F$1,'Fixed Days'!$B$3:$P$3,0)),0)*IFERROR(IF(OR(TRIM("")="Evet",TRIM("")="Yes"),MAX(N('Module Selection'!$C4),1),1),1)+IFERROR(SUMIFS($BF$2:$BF$700,$BB$2:$BB$700,$A4,$BC$2:$BC$700,F$1),0)+0)) | G4: =IF(AND('Module Selection'!$B4<>"Var",'Module Selection'!$B4<>"Include"),"",IF($A4="","",IFERROR(INDEX('Fixed Days'!$B:$P,MATCH('Project Information'!$C$11&"|"&IF(Scope!$J$9="S","SMALL",IF(Scope!$J$9="M","MEDIUM",IF(Scope!$J$9="L","LARGE","X-LARGE")))&"|"&$A4,'Fixed Days'!$AA:$AA,0),MATCH(G$1,'Fixed Days'!$B$3:$P$3,0)),0)*IFERROR(IF(OR(TRIM("")="Evet",TRIM("")="Yes"),MAX(N('Module Selection'!$C4),1),1),1)+IFERROR(SUMIFS($BF$2:$BF$700,$BB$2:$BB$700,$A4,$BC$2:$BC$700,G$1),0)+0)) | H4: =IF(AND('Module Selection'!$B4<>"Var",'Module Selection'!$B4<>"Include"),"",IF($A4="","",IFERROR(INDEX('Fixed Days'!$B:$P,MATCH('Project Information'!$C$11&"|"&IF(Scope!$J$9="S","SMALL",IF(Scope!$J$9="M","MEDIUM",IF(Scope!$J$9="L","LARGE","X-LARGE")))&"|"&$A4,'Fixed Days'!$AA:$AA,0),MATCH(H$1,'Fixed Days'!$B$3:$P$3,0)),0)*IFERROR(IF(OR(TRIM("")="Evet",TRIM("")="Yes"),MAX(N('Module Selection'!$C4),1),1),1)+IFERROR(SUMIFS($BF$2:$BF$700,$BB$2:$BB$700,$A4,$BC$2:$BC$700,H$1),0)+0)) | I4: =IF(AND('Module Selection'!$B4<>"Var",'Module Selection'!$B4<>"Include"),"",IF($A4="","",IFERROR(INDEX('Fixed Days'!$B:$P,MATCH('Project Information'!$C$11&"|"&IF(Scope!$J$9="S","SMALL",IF(Scope!$J$9="M","MEDIUM",IF(Scope!$J$9="L","LARGE","X-LARGE")))&"|"&$A4,'Fixed Days'!$AA:$AA,0),MATCH(I$1,'Fixed Days'!$B$3:$P$3,0)),0)*IFERROR(IF(OR(TRIM("")="Evet",TRIM("")="Yes"),MAX(N('Module Selection'!$C4),1),1),1)+IFERROR(SUMIFS($BF$2:$BF$700,$BB$2:$BB$700,$A4,$BC$2:$BC$700,I$1),0)+0)) | ... N4: =IF(AND('Module Selection'!$B4<>"Var",'Module Selection'!$B4<>"Include"),"",IF($A4="","",IFERROR(INDEX('Fixed Days'!$B:$P,MATCH('Project Information'!$C$11&"|"&IF(Scope!$J$9="S","SMALL",IF(Scope!$J$9="M","MEDIUM",IF(Scope!$J$9="L","LARGE","X-LARGE")))&"|"&$A4,'Fixed Days'!$AA:$AA,0),MATCH(N$1,'Fixed Days'!$B$3:$P$3,0)),0)*IFERROR(IF(OR(TRIM("")="Evet",TRIM("")="Yes"),MAX(N('Module Selection'!$C4),1),1),1)+IFERROR(SUMIFS($BF$2:$BF$700,$BB$2:$BB$700,$A4,$BC$2:$BC$700,N$1),0)+0)) | O4: =IF(AND('Module Selection'!$B4<>"Var",'Module Selection'!$B4<>"Include"),"",IF($A4="","",IFERROR(INDEX('Fixed Days'!$B:$P,MATCH('Project Information'!$C$11&"|"&IF(Scope!$J$9="S","SMALL",IF(Scope!$J$9="M","MEDIUM",IF(Scope!$J$9="L","LARGE","X-LARGE")))&"|"&$A4,'Fixed Days'!$AA:$AA,0),MATCH(O$1,'Fixed Days'!$B$3:$P$3,0)),0)*IFERROR(IF(OR(TRIM("")="Evet",TRIM("")="Yes"),MAX(N('Module Selection'!$C4),1),1),1)+IFERROR(SUMIFS($BF$2:$BF$700,$BB$2:$BB$700,$A4,$BC$2:$BC$700,O$1),0)+IFERROR(INDEX('Hypercare & Go Live Support'!$G:$G,MATCH($A4,'Hypercare & Go Live Support'!$A:$A,0)),0))) | P4: =IF(AND('Module Selection'!$B4<>"Var",'Module Selection'!$B4<>"Include"),"",IF($A4="","",IFERROR(INDEX('Fixed Days'!$B:$P,MATCH('Project Information'!$C$11&"|"&IF(Scope!$J$9="S","SMALL",IF(Scope!$J$9="M","MEDIUM",IF(Scope!$J$9="L","LARGE","X-LARGE")))&"|"&$A4,'Fixed Days'!$AA:$AA,0),MATCH(P$1,'Fixed Days'!$B$3:$P$3,0)),0)*IFERROR(IF(OR(TRIM("")="Evet",TRIM("")="Yes"),MAX(N('Module Selection'!$C4),1),1),1)+IFERROR(SUMIFS($BF$2:$BF$700,$BB$2:$BB$700,$A4,$BC$2:$BC$700,P$1),0)+IFERROR(INDEX('Hypercare & Go Live Support'!$F:$F,MATCH($A4,'Hypercare & Go Live Support'!$A:$A,0)),0))) | Q4: =SUM(B4:P4) | AZ4: =INDEX(Translations!$D:$ZZ, MATCH(305,Translations!$A:$A,0), MATCH('Project Information'!$C$4,Translations!$D$1:$ZZ$1,0)) | BA4: =INDEX(Translations!$D:$ZZ, MATCH(32,Translations!$A:$A,0), MATCH('Project Information'!$C$4,Translations!$D$1:$ZZ$1,0)) | BB4: =INDEX(Translations!$D:$ZZ, MATCH(343,Translations!$A:$A,0), MATCH('Project Information'!$C$4,Translations!$D$1:$ZZ$1,0)) | BC4: =INDEX(Translations!$D:$ZZ, MATCH(79,Translations!$A:$A,0), MATCH('Project Information'!$C$4,Translations!$D$1:$ZZ$1,0)) | BD4: =IF(OR(TRIM("")="Evet",TRIM("")="Yes"),1,0) | BE4: 1 | BF4: =BD4*BE4 | BH4: =INDEX(Translations!$D:$ZZ, MATCH(306,Translations!$A:$A,0), MATCH('Project Information'!$C$4,Translations!$D$1:$ZZ$1,0)) | BI4: =INDEX(Translations!$D:$ZZ, MATCH(251,Translations!$A:$A,0), MATCH('Project Information'!$C$4,Translations!$D$1:$ZZ$1,0)) | BJ4: =INDEX(Translations!$D:$ZZ, MATCH(343,Translations!$A:$A,0), MATCH('Project Information'!$C$4,Translations!$D$1:$ZZ$1,0)) | BK4: =INDEX(Translations!$D:$ZZ, MATCH(76,Translations!$A:$A,0), MATCH('Project Information'!$C$4,Translations!$D$1:$ZZ$1,0)) | BL4: =MAX(N(Development!$G$35),0) | BM4: 1 | BN4: =BL4*BM4
A5: ='Project Definitions'!$D$5 | B5: =IF(AND('Module Selection'!$B5<>"Var",'Module Selection'!$B5<>"Include"),"",IF($A5="","",IFERROR(INDEX('Fixed Days'!$B:$P,MATCH('Project Information'!$C$11&"|"&IF(Scope!$J$9="S","SMALL",IF(Scope!$J$9="M","MEDIUM",IF(Scope!$J$9="L","LARGE","X-LARGE")))&"|"&$A5,'Fixed Days'!$AA:$AA,0),MATCH(B$1,'Fixed Days'!$B$3:$P$3,0)),0)*IFERROR(IF(OR(TRIM("")="Evet",TRIM("")="Yes"),MAX(N('Module Selection'!$C5),1),1),1)+IFERROR(SUMIFS($BF$2:$BF$700,$BB$2:$BB$700,$A5,$BC$2:$BC$700,B$1),0)+0)) | C5: =IF(AND('Module Selection'!$B5<>"Var",'Module Selection'!$B5<>"Include"),"",IF($A5="","",IFERROR(INDEX('Fixed Days'!$B:$P,MATCH('Project Information'!$C$11&"|"&IF(Scope!$J$9="S","SMALL",IF(Scope!$J$9="M","MEDIUM",IF(Scope!$J$9="L","LARGE","X-LARGE")))&"|"&$A5,'Fixed Days'!$AA:$AA,0),MATCH(C$1,'Fixed Days'!$B$3:$P$3,0)),0)*IFERROR(IF(OR(TRIM("")="Evet",TRIM("")="Yes"),MAX(N('Module Selection'!$C5),1),1),1)+IFERROR(SUMIFS($BF$2:$BF$700,$BB$2:$BB$700,$A5,$BC$2:$BC$700,C$1),0)+0)) | D5: =IF(AND('Module Selection'!$B5<>"Var",'Module Selection'!$B5<>"Include"),"",IF($A5="","",IFERROR(INDEX('Fixed Days'!$B:$P,MATCH('Project Information'!$C$11&"|"&IF(Scope!$J$9="S","SMALL",IF(Scope!$J$9="M","MEDIUM",IF(Scope!$J$9="L","LARGE","X-LARGE")))&"|"&$A5,'Fixed Days'!$AA:$AA,0),MATCH(D$1,'Fixed Days'!$B$3:$P$3,0)),0)*IFERROR(IF(OR(TRIM("")="Evet",TRIM("")="Yes"),MAX(N('Module Selection'!$C5),1),1),1)+IFERROR(SUMIFS($BF$2:$BF$700,$BB$2:$BB$700,$A5,$BC$2:$BC$700,D$1),0)+0)) | E5: =IF(AND('Module Selection'!$B5<>"Var",'Module Selection'!$B5<>"Include"),"",IF($A5="","",IFERROR(INDEX('Fixed Days'!$B:$P,MATCH('Project Information'!$C$11&"|"&IF(Scope!$J$9="S","SMALL",IF(Scope!$J$9="M","MEDIUM",IF(Scope!$J$9="L","LARGE","X-LARGE")))&"|"&$A5,'Fixed Days'!$AA:$AA,0),MATCH(E$1,'Fixed Days'!$B$3:$P$3,0)),0)*IFERROR(IF(OR(TRIM("")="Evet",TRIM("")="Yes"),MAX(N('Module Selection'!$C5),1),1),1)+IFERROR(SUMIFS($BF$2:$BF$700,$BB$2:$BB$700,$A5,$BC$2:$BC$700,E$1),0)+0)) | F5: =IF(AND('Module Selection'!$B5<>"Var",'Module Selection'!$B5<>"Include"),"",IF($A5="","",IFERROR(INDEX('Fixed Days'!$B:$P,MATCH('Project Information'!$C$11&"|"&IF(Scope!$J$9="S","SMALL",IF(Scope!$J$9="M","MEDIUM",IF(Scope!$J$9="L","LARGE","X-LARGE")))&"|"&$A5,'Fixed Days'!$AA:$AA,0),MATCH(F$1,'Fixed Days'!$B$3:$P$3,0)),0)*IFERROR(IF(OR(TRIM("")="Evet",TRIM("")="Yes"),MAX(N('Module Selection'!$C5),1),1),1)+IFERROR(SUMIFS($BF$2:$BF$700,$BB$2:$BB$700,$A5,$BC$2:$BC$700,F$1),0)+0)) | G5: =IF(AND('Module Selection'!$B5<>"Var",'Module Selection'!$B5<>"Include"),"",IF($A5="","",IFERROR(INDEX('Fixed Days'!$B:$P,MATCH('Project Information'!$C$11&"|"&IF(Scope!$J$9="S","SMALL",IF(Scope!$J$9="M","MEDIUM",IF(Scope!$J$9="L","LARGE","X-LARGE")))&"|"&$A5,'Fixed Days'!$AA:$AA,0),MATCH(G$1,'Fixed Days'!$B$3:$P$3,0)),0)*IFERROR(IF(OR(TRIM("")="Evet",TRIM("")="Yes"),MAX(N('Module Selection'!$C5),1),1),1)+IFERROR(SUMIFS($BF$2:$BF$700,$BB$2:$BB$700,$A5,$BC$2:$BC$700,G$1),0)+0)) | H5: =IF(AND('Module Selection'!$B5<>"Var",'Module Selection'!$B5<>"Include"),"",IF($A5="","",IFERROR(INDEX('Fixed Days'!$B:$P,MATCH('Project Information'!$C$11&"|"&IF(Scope!$J$9="S","SMALL",IF(Scope!$J$9="M","MEDIUM",IF(Scope!$J$9="L","LARGE","X-LARGE")))&"|"&$A5,'Fixed Days'!$AA:$AA,0),MATCH(H$1,'Fixed Days'!$B$3:$P$3,0)),0)*IFERROR(IF(OR(TRIM("")="Evet",TRIM("")="Yes"),MAX(N('Module Selection'!$C5),1),1),1)+IFERROR(SUMIFS($BF$2:$BF$700,$BB$2:$BB$700,$A5,$BC$2:$BC$700,H$1),0)+0)) | I5: =IF(AND('Module Selection'!$B5<>"Var",'Module Selection'!$B5<>"Include"),"",IF($A5="","",IFERROR(INDEX('Fixed Days'!$B:$P,MATCH('Project Information'!$C$11&"|"&IF(Scope!$J$9="S","SMALL",IF(Scope!$J$9="M","MEDIUM",IF(Scope!$J$9="L","LARGE","X-LARGE")))&"|"&$A5,'Fixed Days'!$AA:$AA,0),MATCH(I$1,'Fixed Days'!$B$3:$P$3,0)),0)*IFERROR(IF(OR(TRIM("")="Evet",TRIM("")="Yes"),MAX(N('Module Selection'!$C5),1),1),1)+IFERROR(SUMIFS($BF$2:$BF$700,$BB$2:$BB$700,$A5,$BC$2:$BC$700,I$1),0)+0)) | ... N5: =IF(AND('Module Selection'!$B5<>"Var",'Module Selection'!$B5<>"Include"),"",IF($A5="","",IFERROR(INDEX('Fixed Days'!$B:$P,MATCH('Project Information'!$C$11&"|"&IF(Scope!$J$9="S","SMALL",IF(Scope!$J$9="M","MEDIUM",IF(Scope!$J$9="L","LARGE","X-LARGE")))&"|"&$A5,'Fixed Days'!$AA:$AA,0),MATCH(N$1,'Fixed Days'!$B$3:$P$3,0)),0)*IFERROR(IF(OR(TRIM("")="Evet",TRIM("")="Yes"),MAX(N('Module Selection'!$C5),1),1),1)+IFERROR(SUMIFS($BF$2:$BF$700,$BB$2:$BB$700,$A5,$BC$2:$BC$700,N$1),0)+0)) | O5: =IF(AND('Module Selection'!$B5<>"Var",'Module Selection'!$B5<>"Include"),"",IF($A5="","",IFERROR(INDEX('Fixed Days'!$B:$P,MATCH('Project Information'!$C$11&"|"&IF(Scope!$J$9="S","SMALL",IF(Scope!$J$9="M","MEDIUM",IF(Scope!$J$9="L","LARGE","X-LARGE")))&"|"&$A5,'Fixed Days'!$AA:$AA,0),MATCH(O$1,'Fixed Days'!$B$3:$P$3,0)),0)*IFERROR(IF(OR(TRIM("")="Evet",TRIM("")="Yes"),MAX(N('Module Selection'!$C5),1),1),1)+IFERROR(SUMIFS($BF$2:$BF$700,$BB$2:$BB$700,$A5,$BC$2:$BC$700,O$1),0)+IFERROR(INDEX('Hypercare & Go Live Support'!$G:$G,MATCH($A5,'Hypercare & Go Live Support'!$A:$A,0)),0))) | P5: =IF(AND('Module Selection'!$B5<>"Var",'Module Selection'!$B5<>"Include"),"",IF($A5="","",IFERROR(INDEX('Fixed Days'!$B:$P,MATCH('Project Information'!$C$11&"|"&IF(Scope!$J$9="S","SMALL",IF(Scope!$J$9="M","MEDIUM",IF(Scope!$J$9="L","LARGE","X-LARGE")))&"|"&$A5,'Fixed Days'!$AA:$AA,0),MATCH(P$1,'Fixed Days'!$B$3:$P$3,0)),0)*IFERROR(IF(OR(TRIM("")="Evet",TRIM("")="Yes"),MAX(N('Module Selection'!$C5),1),1),1)+IFERROR(SUMIFS($BF$2:$BF$700,$BB$2:$BB$700,$A5,$BC$2:$BC$700,P$1),0)+IFERROR(INDEX('Hypercare & Go Live Support'!$F:$F,MATCH($A5,'Hypercare & Go Live Support'!$A:$A,0)),0))) | Q5: =SUM(B5:P5) | AZ5: =INDEX(Translations!$D:$ZZ, MATCH(305,Translations!$A:$A,0), MATCH('Project Information'!$C$4,Translations!$D$1:$ZZ$1,0)) | BA5: =INDEX(Translations!$D:$ZZ, MATCH(32,Translations!$A:$A,0), MATCH('Project Information'!$C$4,Translations!$D$1:$ZZ$1,0)) | BB5: =INDEX(Translations!$D:$ZZ, MATCH(343,Translations!$A:$A,0), MATCH('Project Information'!$C$4,Translations!$D$1:$ZZ$1,0)) | BC5: =INDEX(Translations!$D:$ZZ, MATCH(82,Translations!$A:$A,0), MATCH('Project Information'!$C$4,Translations!$D$1:$ZZ$1,0)) | BD5: =IF(OR(TRIM("")="Evet",TRIM("")="Yes"),1,0) | BE5: 0.5 | BF5: =BD5*BE5 | BH5: =INDEX(Translations!$D:$ZZ, MATCH(306,Translations!$A:$A,0), MATCH('Project Information'!$C$4,Translations!$D$1:$ZZ$1,0)) | BI5: =INDEX(Translations!$D:$ZZ, MATCH(251,Translations!$A:$A,0), MATCH('Project Information'!$C$4,Translations!$D$1:$ZZ$1,0)) | BJ5: =INDEX(Translations!$D:$ZZ, MATCH(343,Translations!$A:$A,0), MATCH('Project Information'!$C$4,Translations!$D$1:$ZZ$1,0)) | BK5: =INDEX(Translations!$D:$ZZ, MATCH(79,Translations!$A:$A,0), MATCH('Project Information'!$C$4,Translations!$D$1:$ZZ$1,0)) | BL5: =MAX(N(Development!$G$35),0) | BM5: 5 | BN5: =BL5*BM5
A6: ='Project Definitions'!$D$6 | B6: =IF(AND('Module Selection'!$B6<>"Var",'Module Selection'!$B6<>"Include"),"",IF($A6="","",IFERROR(INDEX('Fixed Days'!$B:$P,MATCH('Project Information'!$C$11&"|"&IF(Scope!$J$9="S","SMALL",IF(Scope!$J$9="M","MEDIUM",IF(Scope!$J$9="L","LARGE","X-LARGE")))&"|"&$A6,'Fixed Days'!$AA:$AA,0),MATCH(B$1,'Fixed Days'!$B$3:$P$3,0)),0)*IFERROR(IF(OR(TRIM("")="Evet",TRIM("")="Yes"),MAX(N('Module Selection'!$C6),1),1),1)+IFERROR(SUMIFS($BF$2:$BF$700,$BB$2:$BB$700,$A6,$BC$2:$BC$700,B$1),0)+0)) | C6: =IF(AND('Module Selection'!$B6<>"Var",'Module Selection'!$B6<>"Include"),"",IF($A6="","",IFERROR(INDEX('Fixed Days'!$B:$P,MATCH('Project Information'!$C$11&"|"&IF(Scope!$J$9="S","SMALL",IF(Scope!$J$9="M","MEDIUM",IF(Scope!$J$9="L","LARGE","X-LARGE")))&"|"&$A6,'Fixed Days'!$AA:$AA,0),MATCH(C$1,'Fixed Days'!$B$3:$P$3,0)),0)*IFERROR(IF(OR(TRIM("")="Evet",TRIM("")="Yes"),MAX(N('Module Selection'!$C6),1),1),1)+IFERROR(SUMIFS($BF$2:$BF$700,$BB$2:$BB$700,$A6,$BC$2:$BC$700,C$1),0)+0)) | D6: =IF(AND('Module Selection'!$B6<>"Var",'Module Selection'!$B6<>"Include"),"",IF($A6="","",IFERROR(INDEX('Fixed Days'!$B:$P,MATCH('Project Information'!$C$11&"|"&IF(Scope!$J$9="S","SMALL",IF(Scope!$J$9="M","MEDIUM",IF(Scope!$J$9="L","LARGE","X-LARGE")))&"|"&$A6,'Fixed Days'!$AA:$AA,0),MATCH(D$1,'Fixed Days'!$B$3:$P$3,0)),0)*IFERROR(IF(OR(TRIM("")="Evet",TRIM("")="Yes"),MAX(N('Module Selection'!$C6),1),1),1)+IFERROR(SUMIFS($BF$2:$BF$700,$BB$2:$BB$700,$A6,$BC$2:$BC$700,D$1),0)+0)) | E6: =IF(AND('Module Selection'!$B6<>"Var",'Module Selection'!$B6<>"Include"),"",IF($A6="","",IFERROR(INDEX('Fixed Days'!$B:$P,MATCH('Project Information'!$C$11&"|"&IF(Scope!$J$9="S","SMALL",IF(Scope!$J$9="M","MEDIUM",IF(Scope!$J$9="L","LARGE","X-LARGE")))&"|"&$A6,'Fixed Days'!$AA:$AA,0),MATCH(E$1,'Fixed Days'!$B$3:$P$3,0)),0)*IFERROR(IF(OR(TRIM("")="Evet",TRIM("")="Yes"),MAX(N('Module Selection'!$C6),1),1),1)+IFERROR(SUMIFS($BF$2:$BF$700,$BB$2:$BB$700,$A6,$BC$2:$BC$700,E$1),0)+0)) | F6: =IF(AND('Module Selection'!$B6<>"Var",'Module Selection'!$B6<>"Include"),"",IF($A6="","",IFERROR(INDEX('Fixed Days'!$B:$P,MATCH('Project Information'!$C$11&"|"&IF(Scope!$J$9="S","SMALL",IF(Scope!$J$9="M","MEDIUM",IF(Scope!$J$9="L","LARGE","X-LARGE")))&"|"&$A6,'Fixed Days'!$AA:$AA,0),MATCH(F$1,'Fixed Days'!$B$3:$P$3,0)),0)*IFERROR(IF(OR(TRIM("")="Evet",TRIM("")="Yes"),MAX(N('Module Selection'!$C6),1),1),1)+IFERROR(SUMIFS($BF$2:$BF$700,$BB$2:$BB$700,$A6,$BC$2:$BC$700,F$1),0)+0)) | G6: =IF(AND('Module Selection'!$B6<>"Var",'Module Selection'!$B6<>"Include"),"",IF($A6="","",IFERROR(INDEX('Fixed Days'!$B:$P,MATCH('Project Information'!$C$11&"|"&IF(Scope!$J$9="S","SMALL",IF(Scope!$J$9="M","MEDIUM",IF(Scope!$J$9="L","LARGE","X-LARGE")))&"|"&$A6,'Fixed Days'!$AA:$AA,0),MATCH(G$1,'Fixed Days'!$B$3:$P$3,0)),0)*IFERROR(IF(OR(TRIM("")="Evet",TRIM("")="Yes"),MAX(N('Module Selection'!$C6),1),1),1)+IFERROR(SUMIFS($BF$2:$BF$700,$BB$2:$BB$700,$A6,$BC$2:$BC$700,G$1),0)+0)) | H6: =IF(AND('Module Selection'!$B6<>"Var",'Module Selection'!$B6<>"Include"),"",IF($A6="","",IFERROR(INDEX('Fixed Days'!$B:$P,MATCH('Project Information'!$C$11&"|"&IF(Scope!$J$9="S","SMALL",IF(Scope!$J$9="M","MEDIUM",IF(Scope!$J$9="L","LARGE","X-LARGE")))&"|"&$A6,'Fixed Days'!$AA:$AA,0),MATCH(H$1,'Fixed Days'!$B$3:$P$3,0)),0)*IFERROR(IF(OR(TRIM("")="Evet",TRIM("")="Yes"),MAX(N('Module Selection'!$C6),1),1),1)+IFERROR(SUMIFS($BF$2:$BF$700,$BB$2:$BB$700,$A6,$BC$2:$BC$700,H$1),0)+0)) | I6: =IF(AND('Module Selection'!$B6<>"Var",'Module Selection'!$B6<>"Include"),"",IF($A6="","",IFERROR(INDEX('Fixed Days'!$B:$P,MATCH('Project Information'!$C$11&"|"&IF(Scope!$J$9="S","SMALL",IF(Scope!$J$9="M","MEDIUM",IF(Scope!$J$9="L","LARGE","X-LARGE")))&"|"&$A6,'Fixed Days'!$AA:$AA,0),MATCH(I$1,'Fixed Days'!$B$3:$P$3,0)),0)*IFERROR(IF(OR(TRIM("")="Evet",TRIM("")="Yes"),MAX(N('Module Selection'!$C6),1),1),1)+IFERROR(SUMIFS($BF$2:$BF$700,$BB$2:$BB$700,$A6,$BC$2:$BC$700,I$1),0)+0)) | ... N6: =IF(AND('Module Selection'!$B6<>"Var",'Module Selection'!$B6<>"Include"),"",IF($A6="","",IFERROR(INDEX('Fixed Days'!$B:$P,MATCH('Project Information'!$C$11&"|"&IF(Scope!$J$9="S","SMALL",IF(Scope!$J$9="M","MEDIUM",IF(Scope!$J$9="L","LARGE","X-LARGE")))&"|"&$A6,'Fixed Days'!$AA:$AA,0),MATCH(N$1,'Fixed Days'!$B$3:$P$3,0)),0)*IFERROR(IF(OR(TRIM("")="Evet",TRIM("")="Yes"),MAX(N('Module Selection'!$C6),1),1),1)+IFERROR(SUMIFS($BF$2:$BF$700,$BB$2:$BB$700,$A6,$BC$2:$BC$700,N$1),0)+0)) | O6: =IF(AND('Module Selection'!$B6<>"Var",'Module Selection'!$B6<>"Include"),"",IF($A6="","",IFERROR(INDEX('Fixed Days'!$B:$P,MATCH('Project Information'!$C$11&"|"&IF(Scope!$J$9="S","SMALL",IF(Scope!$J$9="M","MEDIUM",IF(Scope!$J$9="L","LARGE","X-LARGE")))&"|"&$A6,'Fixed Days'!$AA:$AA,0),MATCH(O$1,'Fixed Days'!$B$3:$P$3,0)),0)*IFERROR(IF(OR(TRIM("")="Evet",TRIM("")="Yes"),MAX(N('Module Selection'!$C6),1),1),1)+IFERROR(SUMIFS($BF$2:$BF$700,$BB$2:$BB$700,$A6,$BC$2:$BC$700,O$1),0)+IFERROR(INDEX('Hypercare & Go Live Support'!$G:$G,MATCH($A6,'Hypercare & Go Live Support'!$A:$A,0)),0))) | P6: =IF(AND('Module Selection'!$B6<>"Var",'Module Selection'!$B6<>"Include"),"",IF($A6="","",IFERROR(INDEX('Fixed Days'!$B:$P,MATCH('Project Information'!$C$11&"|"&IF(Scope!$J$9="S","SMALL",IF(Scope!$J$9="M","MEDIUM",IF(Scope!$J$9="L","LARGE","X-LARGE")))&"|"&$A6,'Fixed Days'!$AA:$AA,0),MATCH(P$1,'Fixed Days'!$B$3:$P$3,0)),0)*IFERROR(IF(OR(TRIM("")="Evet",TRIM("")="Yes"),MAX(N('Module Selection'!$C6),1),1),1)+IFERROR(SUMIFS($BF$2:$BF$700,$BB$2:$BB$700,$A6,$BC$2:$BC$700,P$1),0)+IFERROR(INDEX('Hypercare & Go Live Support'!$F:$F,MATCH($A6,'Hypercare & Go Live Support'!$A:$A,0)),0))) | Q6: =SUM(B6:P6) | AZ6: =INDEX(Translations!$D:$ZZ, MATCH(305,Translations!$A:$A,0), MATCH('Project Information'!$C$4,Translations!$D$1:$ZZ$1,0)) | BA6: =INDEX(Translations!$D:$ZZ, MATCH(32,Translations!$A:$A,0), MATCH('Project Information'!$C$4,Translations!$D$1:$ZZ$1,0)) | BB6: =INDEX(Translations!$D:$ZZ, MATCH(343,Translations!$A:$A,0), MATCH('Project Information'!$C$4,Translations!$D$1:$ZZ$1,0)) | BC6: =INDEX(Translations!$D:$ZZ, MATCH(83,Translations!$A:$A,0), MATCH('Project Information'!$C$4,Translations!$D$1:$ZZ$1,0)) | BD6: =IF(OR(TRIM("")="Evet",TRIM("")="Yes"),1,0) | BE6: 1 | BF6: =BD6*BE6 | BH6: =INDEX(Translations!$D:$ZZ, MATCH(306,Translations!$A:$A,0), MATCH('Project Information'!$C$4,Translations!$D$1:$ZZ$1,0)) | BI6: =INDEX(Translations!$D:$ZZ, MATCH(251,Translations!$A:$A,0), MATCH('Project Information'!$C$4,Translations!$D$1:$ZZ$1,0)) | BJ6: =INDEX(Translations!$D:$ZZ, MATCH(337,Translations!$A:$A,0), MATCH('Project Information'!$C$4,Translations!$D$1:$ZZ$1,0)) | BK6: =INDEX(Translations!$D:$ZZ, MATCH(75,Translations!$A:$A,0), MATCH('Project Information'!$C$4,Translations!$D$1:$ZZ$1,0)) | BL6: =MAX(N(Development!$G$35),0) | BM6: 2 | BN6: =BL6*BM6
A7: ='Project Definitions'!$D$7 | B7: =IF(AND('Module Selection'!$B7<>"Var",'Module Selection'!$B7<>"Include"),"",IF($A7="","",IFERROR(INDEX('Fixed Days'!$B:$P,MATCH('Project Information'!$C$11&"|"&IF(Scope!$J$9="S","SMALL",IF(Scope!$J$9="M","MEDIUM",IF(Scope!$J$9="L","LARGE","X-LARGE")))&"|"&$A7,'Fixed Days'!$AA:$AA,0),MATCH(B$1,'Fixed Days'!$B$3:$P$3,0)),0)*IFERROR(IF(OR(TRIM("")="Evet",TRIM("")="Yes"),MAX(N('Module Selection'!$C7),1),1),1)+IFERROR(SUMIFS($BF$2:$BF$700,$BB$2:$BB$700,$A7,$BC$2:$BC$700,B$1),0)+0)) | C7: =IF(AND('Module Selection'!$B7<>"Var",'Module Selection'!$B7<>"Include"),"",IF($A7="","",IFERROR(INDEX('Fixed Days'!$B:$P,MATCH('Project Information'!$C$11&"|"&IF(Scope!$J$9="S","SMALL",IF(Scope!$J$9="M","MEDIUM",IF(Scope!$J$9="L","LARGE","X-LARGE")))&"|"&$A7,'Fixed Days'!$AA:$AA,0),MATCH(C$1,'Fixed Days'!$B$3:$P$3,0)),0)*IFERROR(IF(OR(TRIM("")="Evet",TRIM("")="Yes"),MAX(N('Module Selection'!$C7),1),1),1)+IFERROR(SUMIFS($BF$2:$BF$700,$BB$2:$BB$700,$A7,$BC$2:$BC$700,C$1),0)+0)) | D7: =IF(AND('Module Selection'!$B7<>"Var",'Module Selection'!$B7<>"Include"),"",IF($A7="","",IFERROR(INDEX('Fixed Days'!$B:$P,MATCH('Project Information'!$C$11&"|"&IF(Scope!$J$9="S","SMALL",IF(Scope!$J$9="M","MEDIUM",IF(Scope!$J$9="L","LARGE","X-LARGE")))&"|"&$A7,'Fixed Days'!$AA:$AA,0),MATCH(D$1,'Fixed Days'!$B$3:$P$3,0)),0)*IFERROR(IF(OR(TRIM("")="Evet",TRIM("")="Yes"),MAX(N('Module Selection'!$C7),1),1),1)+IFERROR(SUMIFS($BF$2:$BF$700,$BB$2:$BB$700,$A7,$BC$2:$BC$700,D$1),0)+0)) | E7: =IF(AND('Module Selection'!$B7<>"Var",'Module Selection'!$B7<>"Include"),"",IF($A7="","",IFERROR(INDEX('Fixed Days'!$B:$P,MATCH('Project Information'!$C$11&"|"&IF(Scope!$J$9="S","SMALL",IF(Scope!$J$9="M","MEDIUM",IF(Scope!$J$9="L","LARGE","X-LARGE")))&"|"&$A7,'Fixed Days'!$AA:$AA,0),MATCH(E$1,'Fixed Days'!$B$3:$P$3,0)),0)*IFERROR(IF(OR(TRIM("")="Evet",TRIM("")="Yes"),MAX(N('Module Selection'!$C7),1),1),1)+IFERROR(SUMIFS($BF$2:$BF$700,$BB$2:$BB$700,$A7,$BC$2:$BC$700,E$1),0)+0)) | F7: =IF(AND('Module Selection'!$B7<>"Var",'Module Selection'!$B7<>"Include"),"",IF($A7="","",IFERROR(INDEX('Fixed Days'!$B:$P,MATCH('Project Information'!$C$11&"|"&IF(Scope!$J$9="S","SMALL",IF(Scope!$J$9="M","MEDIUM",IF(Scope!$J$9="L","LARGE","X-LARGE")))&"|"&$A7,'Fixed Days'!$AA:$AA,0),MATCH(F$1,'Fixed Days'!$B$3:$P$3,0)),0)*IFERROR(IF(OR(TRIM("")="Evet",TRIM("")="Yes"),MAX(N('Module Selection'!$C7),1),1),1)+IFERROR(SUMIFS($BF$2:$BF$700,$BB$2:$BB$700,$A7,$BC$2:$BC$700,F$1),0)+0)) | G7: =IF(AND('Module Selection'!$B7<>"Var",'Module Selection'!$B7<>"Include"),"",IF($A7="","",IFERROR(INDEX('Fixed Days'!$B:$P,MATCH('Project Information'!$C$11&"|"&IF(Scope!$J$9="S","SMALL",IF(Scope!$J$9="M","MEDIUM",IF(Scope!$J$9="L","LARGE","X-LARGE")))&"|"&$A7,'Fixed Days'!$AA:$AA,0),MATCH(G$1,'Fixed Days'!$B$3:$P$3,0)),0)*IFERROR(IF(OR(TRIM("")="Evet",TRIM("")="Yes"),MAX(N('Module Selection'!$C7),1),1),1)+IFERROR(SUMIFS($BF$2:$BF$700,$BB$2:$BB$700,$A7,$BC$2:$BC$700,G$1),0)+0)) | H7: =IF(AND('Module Selection'!$B7<>"Var",'Module Selection'!$B7<>"Include"),"",IF($A7="","",IFERROR(INDEX('Fixed Days'!$B:$P,MATCH('Project Information'!$C$11&"|"&IF(Scope!$J$9="S","SMALL",IF(Scope!$J$9="M","MEDIUM",IF(Scope!$J$9="L","LARGE","X-LARGE")))&"|"&$A7,'Fixed Days'!$AA:$AA,0),MATCH(H$1,'Fixed Days'!$B$3:$P$3,0)),0)*IFERROR(IF(OR(TRIM("")="Evet",TRIM("")="Yes"),MAX(N('Module Selection'!$C7),1),1),1)+IFERROR(SUMIFS($BF$2:$BF$700,$BB$2:$BB$700,$A7,$BC$2:$BC$700,H$1),0)+0)) | I7: =IF(AND('Module Selection'!$B7<>"Var",'Module Selection'!$B7<>"Include"),"",IF($A7="","",IFERROR(INDEX('Fixed Days'!$B:$P,MATCH('Project Information'!$C$11&"|"&IF(Scope!$J$9="S","SMALL",IF(Scope!$J$9="M","MEDIUM",IF(Scope!$J$9="L","LARGE","X-LARGE")))&"|"&$A7,'Fixed Days'!$AA:$AA,0),MATCH(I$1,'Fixed Days'!$B$3:$P$3,0)),0)*IFERROR(IF(OR(TRIM("")="Evet",TRIM("")="Yes"),MAX(N('Module Selection'!$C7),1),1),1)+IFERROR(SUMIFS($BF$2:$BF$700,$BB$2:$BB$700,$A7,$BC$2:$BC$700,I$1),0)+0)) | ... N7: =IF(AND('Module Selection'!$B7<>"Var",'Module Selection'!$B7<>"Include"),"",IF($A7="","",IFERROR(INDEX('Fixed Days'!$B:$P,MATCH('Project Information'!$C$11&"|"&IF(Scope!$J$9="S","SMALL",IF(Scope!$J$9="M","MEDIUM",IF(Scope!$J$9="L","LARGE","X-LARGE")))&"|"&$A7,'Fixed Days'!$AA:$AA,0),MATCH(N$1,'Fixed Days'!$B$3:$P$3,0)),0)*IFERROR(IF(OR(TRIM("")="Evet",TRIM("")="Yes"),MAX(N('Module Selection'!$C7),1),1),1)+IFERROR(SUMIFS($BF$2:$BF$700,$BB$2:$BB$700,$A7,$BC$2:$BC$700,N$1),0)+0)) | O7: =IF(AND('Module Selection'!$B7<>"Var",'Module Selection'!$B7<>"Include"),"",IF($A7="","",IFERROR(INDEX('Fixed Days'!$B:$P,MATCH('Project Information'!$C$11&"|"&IF(Scope!$J$9="S","SMALL",IF(Scope!$J$9="M","MEDIUM",IF(Scope!$J$9="L","LARGE","X-LARGE")))&"|"&$A7,'Fixed Days'!$AA:$AA,0),MATCH(O$1,'Fixed Days'!$B$3:$P$3,0)),0)*IFERROR(IF(OR(TRIM("")="Evet",TRIM("")="Yes"),MAX(N('Module Selection'!$C7),1),1),1)+IFERROR(SUMIFS($BF$2:$BF$700,$BB$2:$BB$700,$A7,$BC$2:$BC$700,O$1),0)+IFERROR(INDEX('Hypercare & Go Live Support'!$G:$G,MATCH($A7,'Hypercare & Go Live Support'!$A:$A,0)),0))) | P7: =IF(AND('Module Selection'!$B7<>"Var",'Module Selection'!$B7<>"Include"),"",IF($A7="","",IFERROR(INDEX('Fixed Days'!$B:$P,MATCH('Project Information'!$C$11&"|"&IF(Scope!$J$9="S","SMALL",IF(Scope!$J$9="M","MEDIUM",IF(Scope!$J$9="L","LARGE","X-LARGE")))&"|"&$A7,'Fixed Days'!$AA:$AA,0),MATCH(P$1,'Fixed Days'!$B$3:$P$3,0)),0)*IFERROR(IF(OR(TRIM("")="Evet",TRIM("")="Yes"),MAX(N('Module Selection'!$C7),1),1),1)+IFERROR(SUMIFS($BF$2:$BF$700,$BB$2:$BB$700,$A7,$BC$2:$BC$700,P$1),0)+IFERROR(INDEX('Hypercare & Go Live Support'!$F:$F,MATCH($A7,'Hypercare & Go Live Support'!$A:$A,0)),0))) | Q7: =SUM(B7:P7) | AZ7: =INDEX(Translations!$D:$ZZ, MATCH(305,Translations!$A:$A,0), MATCH('Project Information'!$C$4,Translations!$D$1:$ZZ$1,0)) | BA7: =INDEX(Translations!$D:$ZZ, MATCH(32,Translations!$A:$A,0), MATCH('Project Information'!$C$4,Translations!$D$1:$ZZ$1,0)) | BB7: =INDEX(Translations!$D:$ZZ, MATCH(341,Translations!$A:$A,0), MATCH('Project Information'!$C$4,Translations!$D$1:$ZZ$1,0)) | BC7: =INDEX(Translations!$D:$ZZ, MATCH(75,Translations!$A:$A,0), MATCH('Project Information'!$C$4,Translations!$D$1:$ZZ$1,0)) | BD7: =IF(OR(TRIM("")="Evet",TRIM("")="Yes"),1,0) | BE7: 3 | BF7: =BD7*BE7 | BH7: =INDEX(Translations!$D:$ZZ, MATCH(306,Translations!$A:$A,0), MATCH('Project Information'!$C$4,Translations!$D$1:$ZZ$1,0)) | BI7: =INDEX(Translations!$D:$ZZ, MATCH(251,Translations!$A:$A,0), MATCH('Project Information'!$C$4,Translations!$D$1:$ZZ$1,0)) | BJ7: =INDEX(Translations!$D:$ZZ, MATCH(337,Translations!$A:$A,0), MATCH('Project Information'!$C$4,Translations!$D$1:$ZZ$1,0)) | BK7: =INDEX(Translations!$D:$ZZ, MATCH(76,Translations!$A:$A,0), MATCH('Project Information'!$C$4,Translations!$D$1:$ZZ$1,0)) | BL7: =MAX(N(Development!$G$35),0) | BM7: 1 | BN7: =BL7*BM7
A8: ='Project Definitions'!$D$8 | B8: =IF(AND('Module Selection'!$B8<>"Var",'Module Selection'!$B8<>"Include"),"",IF($A8="","",IFERROR(INDEX('Fixed Days'!$B:$P,MATCH('Project Information'!$C$11&"|"&IF(Scope!$J$9="S","SMALL",IF(Scope!$J$9="M","MEDIUM",IF(Scope!$J$9="L","LARGE","X-LARGE")))&"|"&$A8,'Fixed Days'!$AA:$AA,0),MATCH(B$1,'Fixed Days'!$B$3:$P$3,0)),0)*IFERROR(IF(OR(TRIM("")="Evet",TRIM("")="Yes"),MAX(N('Module Selection'!$C8),1),1),1)+IFERROR(SUMIFS($BF$2:$BF$700,$BB$2:$BB$700,$A8,$BC$2:$BC$700,B$1),0)+0)) | C8: =IF(AND('Module Selection'!$B8<>"Var",'Module Selection'!$B8<>"Include"),"",IF($A8="","",IFERROR(INDEX('Fixed Days'!$B:$P,MATCH('Project Information'!$C$11&"|"&IF(Scope!$J$9="S","SMALL",IF(Scope!$J$9="M","MEDIUM",IF(Scope!$J$9="L","LARGE","X-LARGE")))&"|"&$A8,'Fixed Days'!$AA:$AA,0),MATCH(C$1,'Fixed Days'!$B$3:$P$3,0)),0)*IFERROR(IF(OR(TRIM("")="Evet",TRIM("")="Yes"),MAX(N('Module Selection'!$C8),1),1),1)+IFERROR(SUMIFS($BF$2:$BF$700,$BB$2:$BB$700,$A8,$BC$2:$BC$700,C$1),0)+0)) | D8: =IF(AND('Module Selection'!$B8<>"Var",'Module Selection'!$B8<>"Include"),"",IF($A8="","",IFERROR(INDEX('Fixed Days'!$B:$P,MATCH('Project Information'!$C$11&"|"&IF(Scope!$J$9="S","SMALL",IF(Scope!$J$9="M","MEDIUM",IF(Scope!$J$9="L","LARGE","X-LARGE")))&"|"&$A8,'Fixed Days'!$AA:$AA,0),MATCH(D$1,'Fixed Days'!$B$3:$P$3,0)),0)*IFERROR(IF(OR(TRIM("")="Evet",TRIM("")="Yes"),MAX(N('Module Selection'!$C8),1),1),1)+IFERROR(SUMIFS($BF$2:$BF$700,$BB$2:$BB$700,$A8,$BC$2:$BC$700,D$1),0)+0)) | E8: =IF(AND('Module Selection'!$B8<>"Var",'Module Selection'!$B8<>"Include"),"",IF($A8="","",IFERROR(INDEX('Fixed Days'!$B:$P,MATCH('Project Information'!$C$11&"|"&IF(Scope!$J$9="S","SMALL",IF(Scope!$J$9="M","MEDIUM",IF(Scope!$J$9="L","LARGE","X-LARGE")))&"|"&$A8,'Fixed Days'!$AA:$AA,0),MATCH(E$1,'Fixed Days'!$B$3:$P$3,0)),0)*IFERROR(IF(OR(TRIM("")="Evet",TRIM("")="Yes"),MAX(N('Module Selection'!$C8),1),1),1)+IFERROR(SUMIFS($BF$2:$BF$700,$BB$2:$BB$700,$A8,$BC$2:$BC$700,E$1),0)+0)) | F8: =IF(AND('Module Selection'!$B8<>"Var",'Module Selection'!$B8<>"Include"),"",IF($A8="","",IFERROR(INDEX('Fixed Days'!$B:$P,MATCH('Project Information'!$C$11&"|"&IF(Scope!$J$9="S","SMALL",IF(Scope!$J$9="M","MEDIUM",IF(Scope!$J$9="L","LARGE","X-LARGE")))&"|"&$A8,'Fixed Days'!$AA:$AA,0),MATCH(F$1,'Fixed Days'!$B$3:$P$3,0)),0)*IFERROR(IF(OR(TRIM("")="Evet",TRIM("")="Yes"),MAX(N('Module Selection'!$C8),1),1),1)+IFERROR(SUMIFS($BF$2:$BF$700,$BB$2:$BB$700,$A8,$BC$2:$BC$700,F$1),0)+0)) | G8: =IF(AND('Module Selection'!$B8<>"Var",'Module Selection'!$B8<>"Include"),"",IF($A8="","",IFERROR(INDEX('Fixed Days'!$B:$P,MATCH('Project Information'!$C$11&"|"&IF(Scope!$J$9="S","SMALL",IF(Scope!$J$9="M","MEDIUM",IF(Scope!$J$9="L","LARGE","X-LARGE")))&"|"&$A8,'Fixed Days'!$AA:$AA,0),MATCH(G$1,'Fixed Days'!$B$3:$P$3,0)),0)*IFERROR(IF(OR(TRIM("")="Evet",TRIM("")="Yes"),MAX(N('Module Selection'!$C8),1),1),1)+IFERROR(SUMIFS($BF$2:$BF$700,$BB$2:$BB$700,$A8,$BC$2:$BC$700,G$1),0)+0)) | H8: =IF(AND('Module Selection'!$B8<>"Var",'Module Selection'!$B8<>"Include"),"",IF($A8="","",IFERROR(INDEX('Fixed Days'!$B:$P,MATCH('Project Information'!$C$11&"|"&IF(Scope!$J$9="S","SMALL",IF(Scope!$J$9="M","MEDIUM",IF(Scope!$J$9="L","LARGE","X-LARGE")))&"|"&$A8,'Fixed Days'!$AA:$AA,0),MATCH(H$1,'Fixed Days'!$B$3:$P$3,0)),0)*IFERROR(IF(OR(TRIM("")="Evet",TRIM("")="Yes"),MAX(N('Module Selection'!$C8),1),1),1)+IFERROR(SUMIFS($BF$2:$BF$700,$BB$2:$BB$700,$A8,$BC$2:$BC$700,H$1),0)+0)) | I8: =IF(AND('Module Selection'!$B8<>"Var",'Module Selection'!$B8<>"Include"),"",IF($A8="","",IFERROR(INDEX('Fixed Days'!$B:$P,MATCH('Project Information'!$C$11&"|"&IF(Scope!$J$9="S","SMALL",IF(Scope!$J$9="M","MEDIUM",IF(Scope!$J$9="L","LARGE","X-LARGE")))&"|"&$A8,'Fixed Days'!$AA:$AA,0),MATCH(I$1,'Fixed Days'!$B$3:$P$3,0)),0)*IFERROR(IF(OR(TRIM("")="Evet",TRIM("")="Yes"),MAX(N('Module Selection'!$C8),1),1),1)+IFERROR(SUMIFS($BF$2:$BF$700,$BB$2:$BB$700,$A8,$BC$2:$BC$700,I$1),0)+0)) | ... N8: =IF(AND('Module Selection'!$B8<>"Var",'Module Selection'!$B8<>"Include"),"",IF($A8="","",IFERROR(INDEX('Fixed Days'!$B:$P,MATCH('Project Information'!$C$11&"|"&IF(Scope!$J$9="S","SMALL",IF(Scope!$J$9="M","MEDIUM",IF(Scope!$J$9="L","LARGE","X-LARGE")))&"|"&$A8,'Fixed Days'!$AA:$AA,0),MATCH(N$1,'Fixed Days'!$B$3:$P$3,0)),0)*IFERROR(IF(OR(TRIM("")="Evet",TRIM("")="Yes"),MAX(N('Module Selection'!$C8),1),1),1)+IFERROR(SUMIFS($BF$2:$BF$700,$BB$2:$BB$700,$A8,$BC$2:$BC$700,N$1),0)+0)) | O8: =IF(AND('Module Selection'!$B8<>"Var",'Module Selection'!$B8<>"Include"),"",IF($A8="","",IFERROR(INDEX('Fixed Days'!$B:$P,MATCH('Project Information'!$C$11&"|"&IF(Scope!$J$9="S","SMALL",IF(Scope!$J$9="M","MEDIUM",IF(Scope!$J$9="L","LARGE","X-LARGE")))&"|"&$A8,'Fixed Days'!$AA:$AA,0),MATCH(O$1,'Fixed Days'!$B$3:$P$3,0)),0)*IFERROR(IF(OR(TRIM("")="Evet",TRIM("")="Yes"),MAX(N('Module Selection'!$C8),1),1),1)+IFERROR(SUMIFS($BF$2:$BF$700,$BB$2:$BB$700,$A8,$BC$2:$BC$700,O$1),0)+IFERROR(INDEX('Hypercare & Go Live Support'!$G:$G,MATCH($A8,'Hypercare & Go Live Support'!$A:$A,0)),0))) | P8: =IF(AND('Module Selection'!$B8<>"Var",'Module Selection'!$B8<>"Include"),"",IF($A8="","",IFERROR(INDEX('Fixed Days'!$B:$P,MATCH('Project Information'!$C$11&"|"&IF(Scope!$J$9="S","SMALL",IF(Scope!$J$9="M","MEDIUM",IF(Scope!$J$9="L","LARGE","X-LARGE")))&"|"&$A8,'Fixed Days'!$AA:$AA,0),MATCH(P$1,'Fixed Days'!$B$3:$P$3,0)),0)*IFERROR(IF(OR(TRIM("")="Evet",TRIM("")="Yes"),MAX(N('Module Selection'!$C8),1),1),1)+IFERROR(SUMIFS($BF$2:$BF$700,$BB$2:$BB$700,$A8,$BC$2:$BC$700,P$1),0)+IFERROR(INDEX('Hypercare & Go Live Support'!$F:$F,MATCH($A8,'Hypercare & Go Live Support'!$A:$A,0)),0))) | Q8: =SUM(B8:P8) | AZ8: =INDEX(Translations!$D:$ZZ, MATCH(305,Translations!$A:$A,0), MATCH('Project Information'!$C$4,Translations!$D$1:$ZZ$1,0)) | BA8: =INDEX(Translations!$D:$ZZ, MATCH(32,Translations!$A:$A,0), MATCH('Project Information'!$C$4,Translations!$D$1:$ZZ$1,0)) | BB8: =INDEX(Translations!$D:$ZZ, MATCH(341,Translations!$A:$A,0), MATCH('Project Information'!$C$4,Translations!$D$1:$ZZ$1,0)) | BC8: =INDEX(Translations!$D:$ZZ, MATCH(76,Translations!$A:$A,0), MATCH('Project Information'!$C$4,Translations!$D$1:$ZZ$1,0)) | BD8: =IF(OR(TRIM("")="Evet",TRIM("")="Yes"),1,0) | BE8: 1 | BF8: =BD8*BE8 | BH8: =INDEX(Translations!$D:$ZZ, MATCH(306,Translations!$A:$A,0), MATCH('Project Information'!$C$4,Translations!$D$1:$ZZ$1,0)) | BI8: =INDEX(Translations!$D:$ZZ, MATCH(251,Translations!$A:$A,0), MATCH('Project Information'!$C$4,Translations!$D$1:$ZZ$1,0)) | BJ8: =INDEX(Translations!$D:$ZZ, MATCH(337,Translations!$A:$A,0), MATCH('Project Information'!$C$4,Translations!$D$1:$ZZ$1,0)) | BK8: =INDEX(Translations!$D:$ZZ, MATCH(79,Translations!$A:$A,0), MATCH('Project Information'!$C$4,Translations!$D$1:$ZZ$1,0)) | BL8: =MAX(N(Development!$G$35),0) | BM8: 5 | BN8: =BL8*BM8
A9: ='Project Definitions'!$D$9 | B9: =IF(AND('Module Selection'!$B9<>"Var",'Module Selection'!$B9<>"Include"),"",IF($A9="","",IFERROR(INDEX('Fixed Days'!$B:$P,MATCH('Project Information'!$C$11&"|"&IF(Scope!$J$9="S","SMALL",IF(Scope!$J$9="M","MEDIUM",IF(Scope!$J$9="L","LARGE","X-LARGE")))&"|"&$A9,'Fixed Days'!$AA:$AA,0),MATCH(B$1,'Fixed Days'!$B$3:$P$3,0)),0)*IFERROR(IF(OR(TRIM("")="Evet",TRIM("")="Yes"),MAX(N('Module Selection'!$C9),1),1),1)+IFERROR(SUMIFS($BF$2:$BF$700,$BB$2:$BB$700,$A9,$BC$2:$BC$700,B$1),0)+0)) | C9: =IF(AND('Module Selection'!$B9<>"Var",'Module Selection'!$B9<>"Include"),"",IF($A9="","",IFERROR(INDEX('Fixed Days'!$B:$P,MATCH('Project Information'!$C$11&"|"&IF(Scope!$J$9="S","SMALL",IF(Scope!$J$9="M","MEDIUM",IF(Scope!$J$9="L","LARGE","X-LARGE")))&"|"&$A9,'Fixed Days'!$AA:$AA,0),MATCH(C$1,'Fixed Days'!$B$3:$P$3,0)),0)*IFERROR(IF(OR(TRIM("")="Evet",TRIM("")="Yes"),MAX(N('Module Selection'!$C9),1),1),1)+IFERROR(SUMIFS($BF$2:$BF$700,$BB$2:$BB$700,$A9,$BC$2:$BC$700,C$1),0)+0)) | D9: =IF(AND('Module Selection'!$B9<>"Var",'Module Selection'!$B9<>"Include"),"",IF($A9="","",IFERROR(INDEX('Fixed Days'!$B:$P,MATCH('Project Information'!$C$11&"|"&IF(Scope!$J$9="S","SMALL",IF(Scope!$J$9="M","MEDIUM",IF(Scope!$J$9="L","LARGE","X-LARGE")))&"|"&$A9,'Fixed Days'!$AA:$AA,0),MATCH(D$1,'Fixed Days'!$B$3:$P$3,0)),0)*IFERROR(IF(OR(TRIM("")="Evet",TRIM("")="Yes"),MAX(N('Module Selection'!$C9),1),1),1)+IFERROR(SUMIFS($BF$2:$BF$700,$BB$2:$BB$700,$A9,$BC$2:$BC$700,D$1),0)+0)) | E9: =IF(AND('Module Selection'!$B9<>"Var",'Module Selection'!$B9<>"Include"),"",IF($A9="","",IFERROR(INDEX('Fixed Days'!$B:$P,MATCH('Project Information'!$C$11&"|"&IF(Scope!$J$9="S","SMALL",IF(Scope!$J$9="M","MEDIUM",IF(Scope!$J$9="L","LARGE","X-LARGE")))&"|"&$A9,'Fixed Days'!$AA:$AA,0),MATCH(E$1,'Fixed Days'!$B$3:$P$3,0)),0)*IFERROR(IF(OR(TRIM("")="Evet",TRIM("")="Yes"),MAX(N('Module Selection'!$C9),1),1),1)+IFERROR(SUMIFS($BF$2:$BF$700,$BB$2:$BB$700,$A9,$BC$2:$BC$700,E$1),0)+0)) | F9: =IF(AND('Module Selection'!$B9<>"Var",'Module Selection'!$B9<>"Include"),"",IF($A9="","",IFERROR(INDEX('Fixed Days'!$B:$P,MATCH('Project Information'!$C$11&"|"&IF(Scope!$J$9="S","SMALL",IF(Scope!$J$9="M","MEDIUM",IF(Scope!$J$9="L","LARGE","X-LARGE")))&"|"&$A9,'Fixed Days'!$AA:$AA,0),MATCH(F$1,'Fixed Days'!$B$3:$P$3,0)),0)*IFERROR(IF(OR(TRIM("")="Evet",TRIM("")="Yes"),MAX(N('Module Selection'!$C9),1),1),1)+IFERROR(SUMIFS($BF$2:$BF$700,$BB$2:$BB$700,$A9,$BC$2:$BC$700,F$1),0)+0)) | G9: =IF(AND('Module Selection'!$B9<>"Var",'Module Selection'!$B9<>"Include"),"",IF($A9="","",IFERROR(INDEX('Fixed Days'!$B:$P,MATCH('Project Information'!$C$11&"|"&IF(Scope!$J$9="S","SMALL",IF(Scope!$J$9="M","MEDIUM",IF(Scope!$J$9="L","LARGE","X-LARGE")))&"|"&$A9,'Fixed Days'!$AA:$AA,0),MATCH(G$1,'Fixed Days'!$B$3:$P$3,0)),0)*IFERROR(IF(OR(TRIM("")="Evet",TRIM("")="Yes"),MAX(N('Module Selection'!$C9),1),1),1)+IFERROR(SUMIFS($BF$2:$BF$700,$BB$2:$BB$700,$A9,$BC$2:$BC$700,G$1),0)+0)) | H9: =IF(AND('Module Selection'!$B9<>"Var",'Module Selection'!$B9<>"Include"),"",IF($A9="","",IFERROR(INDEX('Fixed Days'!$B:$P,MATCH('Project Information'!$C$11&"|"&IF(Scope!$J$9="S","SMALL",IF(Scope!$J$9="M","MEDIUM",IF(Scope!$J$9="L","LARGE","X-LARGE")))&"|"&$A9,'Fixed Days'!$AA:$AA,0),MATCH(H$1,'Fixed Days'!$B$3:$P$3,0)),0)*IFERROR(IF(OR(TRIM("")="Evet",TRIM("")="Yes"),MAX(N('Module Selection'!$C9),1),1),1)+IFERROR(SUMIFS($BF$2:$BF$700,$BB$2:$BB$700,$A9,$BC$2:$BC$700,H$1),0)+0)) | I9: =IF(AND('Module Selection'!$B9<>"Var",'Module Selection'!$B9<>"Include"),"",IF($A9="","",IFERROR(INDEX('Fixed Days'!$B:$P,MATCH('Project Information'!$C$11&"|"&IF(Scope!$J$9="S","SMALL",IF(Scope!$J$9="M","MEDIUM",IF(Scope!$J$9="L","LARGE","X-LARGE")))&"|"&$A9,'Fixed Days'!$AA:$AA,0),MATCH(I$1,'Fixed Days'!$B$3:$P$3,0)),0)*IFERROR(IF(OR(TRIM("")="Evet",TRIM("")="Yes"),MAX(N('Module Selection'!$C9),1),1),1)+IFERROR(SUMIFS($BF$2:$BF$700,$BB$2:$BB$700,$A9,$BC$2:$BC$700,I$1),0)+0)) | ... N9: =IF(AND('Module Selection'!$B9<>"Var",'Module Selection'!$B9<>"Include"),"",IF($A9="","",IFERROR(INDEX('Fixed Days'!$B:$P,MATCH('Project Information'!$C$11&"|"&IF(Scope!$J$9="S","SMALL",IF(Scope!$J$9="M","MEDIUM",IF(Scope!$J$9="L","LARGE","X-LARGE")))&"|"&$A9,'Fixed Days'!$AA:$AA,0),MATCH(N$1,'Fixed Days'!$B$3:$P$3,0)),0)*IFERROR(IF(OR(TRIM("")="Evet",TRIM("")="Yes"),MAX(N('Module Selection'!$C9),1),1),1)+IFERROR(SUMIFS($BF$2:$BF$700,$BB$2:$BB$700,$A9,$BC$2:$BC$700,N$1),0)+0)) | O9: =IF(AND('Module Selection'!$B9<>"Var",'Module Selection'!$B9<>"Include"),"",IF($A9="","",IFERROR(INDEX('Fixed Days'!$B:$P,MATCH('Project Information'!$C$11&"|"&IF(Scope!$J$9="S","SMALL",IF(Scope!$J$9="M","MEDIUM",IF(Scope!$J$9="L","LARGE","X-LARGE")))&"|"&$A9,'Fixed Days'!$AA:$AA,0),MATCH(O$1,'Fixed Days'!$B$3:$P$3,0)),0)*IFERROR(IF(OR(TRIM("")="Evet",TRIM("")="Yes"),MAX(N('Module Selection'!$C9),1),1),1)+IFERROR(SUMIFS($BF$2:$BF$700,$BB$2:$BB$700,$A9,$BC$2:$BC$700,O$1),0)+IFERROR(INDEX('Hypercare & Go Live Support'!$G:$G,MATCH($A9,'Hypercare & Go Live Support'!$A:$A,0)),0))) | P9: =IF(AND('Module Selection'!$B9<>"Var",'Module Selection'!$B9<>"Include"),"",IF($A9="","",IFERROR(INDEX('Fixed Days'!$B:$P,MATCH('Project Information'!$C$11&"|"&IF(Scope!$J$9="S","SMALL",IF(Scope!$J$9="M","MEDIUM",IF(Scope!$J$9="L","LARGE","X-LARGE")))&"|"&$A9,'Fixed Days'!$AA:$AA,0),MATCH(P$1,'Fixed Days'!$B$3:$P$3,0)),0)*IFERROR(IF(OR(TRIM("")="Evet",TRIM("")="Yes"),MAX(N('Module Selection'!$C9),1),1),1)+IFERROR(SUMIFS($BF$2:$BF$700,$BB$2:$BB$700,$A9,$BC$2:$BC$700,P$1),0)+IFERROR(INDEX('Hypercare & Go Live Support'!$F:$F,MATCH($A9,'Hypercare & Go Live Support'!$A:$A,0)),0))) | Q9: =SUM(B9:P9) | AZ9: =INDEX(Translations!$D:$ZZ, MATCH(305,Translations!$A:$A,0), MATCH('Project Information'!$C$4,Translations!$D$1:$ZZ$1,0)) | BA9: =INDEX(Translations!$D:$ZZ, MATCH(32,Translations!$A:$A,0), MATCH('Project Information'!$C$4,Translations!$D$1:$ZZ$1,0)) | BB9: =INDEX(Translations!$D:$ZZ, MATCH(341,Translations!$A:$A,0), MATCH('Project Information'!$C$4,Translations!$D$1:$ZZ$1,0)) | BC9: =INDEX(Translations!$D:$ZZ, MATCH(79,Translations!$A:$A,0), MATCH('Project Information'!$C$4,Translations!$D$1:$ZZ$1,0)) | BD9: =IF(OR(TRIM("")="Evet",TRIM("")="Yes"),1,0) | BE9: 1 | BF9: =BD9*BE9 | BH9: =INDEX(Translations!$D:$ZZ, MATCH(306,Translations!$A:$A,0), MATCH('Project Information'!$C$4,Translations!$D$1:$ZZ$1,0)) | BI9: =INDEX(Translations!$D:$ZZ, MATCH(205,Translations!$A:$A,0), MATCH('Project Information'!$C$4,Translations!$D$1:$ZZ$1,0)) | BJ9: =INDEX(Translations!$D:$ZZ, MATCH(346,Translations!$A:$A,0), MATCH('Project Information'!$C$4,Translations!$D$1:$ZZ$1,0)) | BK9: =INDEX(Translations!$D:$ZZ, MATCH(78,Translations!$A:$A,0), MATCH('Project Information'!$C$4,Translations!$D$1:$ZZ$1,0)) | BL9: =MAX(N(Development!$G$17),0) | BM9: 5 | BN9: =BL9*BM9
A10: ='Project Definitions'!$D$10 | B10: =IF(AND('Module Selection'!$B10<>"Var",'Module Selection'!$B10<>"Include"),"",IF($A10="","",IFERROR(INDEX('Fixed Days'!$B:$P,MATCH('Project Information'!$C$11&"|"&IF(Scope!$J$9="S","SMALL",IF(Scope!$J$9="M","MEDIUM",IF(Scope!$J$9="L","LARGE","X-LARGE")))&"|"&$A10,'Fixed Days'!$AA:$AA,0),MATCH(B$1,'Fixed Days'!$B$3:$P$3,0)),0)*IFERROR(IF(OR(TRIM("")="Evet",TRIM("")="Yes"),MAX(N('Module Selection'!$C10),1),1),1)+IFERROR(SUMIFS($BF$2:$BF$700,$BB$2:$BB$700,$A10,$BC$2:$BC$700,B$1),0)+0)) | C10: =IF(AND('Module Selection'!$B10<>"Var",'Module Selection'!$B10<>"Include"),"",IF($A10="","",IFERROR(INDEX('Fixed Days'!$B:$P,MATCH('Project Information'!$C$11&"|"&IF(Scope!$J$9="S","SMALL",IF(Scope!$J$9="M","MEDIUM",IF(Scope!$J$9="L","LARGE","X-LARGE")))&"|"&$A10,'Fixed Days'!$AA:$AA,0),MATCH(C$1,'Fixed Days'!$B$3:$P$3,0)),0)*IFERROR(IF(OR(TRIM("")="Evet",TRIM("")="Yes"),MAX(N('Module Selection'!$C10),1),1),1)+IFERROR(SUMIFS($BF$2:$BF$700,$BB$2:$BB$700,$A10,$BC$2:$BC$700,C$1),0)+0)) | D10: =IF(AND('Module Selection'!$B10<>"Var",'Module Selection'!$B10<>"Include"),"",IF($A10="","",IFERROR(INDEX('Fixed Days'!$B:$P,MATCH('Project Information'!$C$11&"|"&IF(Scope!$J$9="S","SMALL",IF(Scope!$J$9="M","MEDIUM",IF(Scope!$J$9="L","LARGE","X-LARGE")))&"|"&$A10,'Fixed Days'!$AA:$AA,0),MATCH(D$1,'Fixed Days'!$B$3:$P$3,0)),0)*IFERROR(IF(OR(TRIM("")="Evet",TRIM("")="Yes"),MAX(N('Module Selection'!$C10),1),1),1)+IFERROR(SUMIFS($BF$2:$BF$700,$BB$2:$BB$700,$A10,$BC$2:$BC$700,D$1),0)+0)) | E10: =IF(AND('Module Selection'!$B10<>"Var",'Module Selection'!$B10<>"Include"),"",IF($A10="","",IFERROR(INDEX('Fixed Days'!$B:$P,MATCH('Project Information'!$C$11&"|"&IF(Scope!$J$9="S","SMALL",IF(Scope!$J$9="M","MEDIUM",IF(Scope!$J$9="L","LARGE","X-LARGE")))&"|"&$A10,'Fixed Days'!$AA:$AA,0),MATCH(E$1,'Fixed Days'!$B$3:$P$3,0)),0)*IFERROR(IF(OR(TRIM("")="Evet",TRIM("")="Yes"),MAX(N('Module Selection'!$C10),1),1),1)+IFERROR(SUMIFS($BF$2:$BF$700,$BB$2:$BB$700,$A10,$BC$2:$BC$700,E$1),0)+0)) | F10: =IF(AND('Module Selection'!$B10<>"Var",'Module Selection'!$B10<>"Include"),"",IF($A10="","",IFERROR(INDEX('Fixed Days'!$B:$P,MATCH('Project Information'!$C$11&"|"&IF(Scope!$J$9="S","SMALL",IF(Scope!$J$9="M","MEDIUM",IF(Scope!$J$9="L","LARGE","X-LARGE")))&"|"&$A10,'Fixed Days'!$AA:$AA,0),MATCH(F$1,'Fixed Days'!$B$3:$P$3,0)),0)*IFERROR(IF(OR(TRIM("")="Evet",TRIM("")="Yes"),MAX(N('Module Selection'!$C10),1),1),1)+IFERROR(SUMIFS($BF$2:$BF$700,$BB$2:$BB$700,$A10,$BC$2:$BC$700,F$1),0)+0)) | G10: =IF(AND('Module Selection'!$B10<>"Var",'Module Selection'!$B10<>"Include"),"",IF($A10="","",IFERROR(INDEX('Fixed Days'!$B:$P,MATCH('Project Information'!$C$11&"|"&IF(Scope!$J$9="S","SMALL",IF(Scope!$J$9="M","MEDIUM",IF(Scope!$J$9="L","LARGE","X-LARGE")))&"|"&$A10,'Fixed Days'!$AA:$AA,0),MATCH(G$1,'Fixed Days'!$B$3:$P$3,0)),0)*IFERROR(IF(OR(TRIM("")="Evet",TRIM("")="Yes"),MAX(N('Module Selection'!$C10),1),1),1)+IFERROR(SUMIFS($BF$2:$BF$700,$BB$2:$BB$700,$A10,$BC$2:$BC$700,G$1),0)+0)) | H10: =IF(AND('Module Selection'!$B10<>"Var",'Module Selection'!$B10<>"Include"),"",IF($A10="","",IFERROR(INDEX('Fixed Days'!$B:$P,MATCH('Project Information'!$C$11&"|"&IF(Scope!$J$9="S","SMALL",IF(Scope!$J$9="M","MEDIUM",IF(Scope!$J$9="L","LARGE","X-LARGE")))&"|"&$A10,'Fixed Days'!$AA:$AA,0),MATCH(H$1,'Fixed Days'!$B$3:$P$3,0)),0)*IFERROR(IF(OR(TRIM("")="Evet",TRIM("")="Yes"),MAX(N('Module Selection'!$C10),1),1),1)+IFERROR(SUMIFS($BF$2:$BF$700,$BB$2:$BB$700,$A10,$BC$2:$BC$700,H$1),0)+0)) | I10: =IF(AND('Module Selection'!$B10<>"Var",'Module Selection'!$B10<>"Include"),"",IF($A10="","",IFERROR(INDEX('Fixed Days'!$B:$P,MATCH('Project Information'!$C$11&"|"&IF(Scope!$J$9="S","SMALL",IF(Scope!$J$9="M","MEDIUM",IF(Scope!$J$9="L","LARGE","X-LARGE")))&"|"&$A10,'Fixed Days'!$AA:$AA,0),MATCH(I$1,'Fixed Days'!$B$3:$P$3,0)),0)*IFERROR(IF(OR(TRIM("")="Evet",TRIM("")="Yes"),MAX(N('Module Selection'!$C10),1),1),1)+IFERROR(SUMIFS($BF$2:$BF$700,$BB$2:$BB$700,$A10,$BC$2:$BC$700,I$1),0)+0)) | ... N10: =IF(AND('Module Selection'!$B10<>"Var",'Module Selection'!$B10<>"Include"),"",IF($A10="","",IFERROR(INDEX('Fixed Days'!$B:$P,MATCH('Project Information'!$C$11&"|"&IF(Scope!$J$9="S","SMALL",IF(Scope!$J$9="M","MEDIUM",IF(Scope!$J$9="L","LARGE","X-LARGE")))&"|"&$A10,'Fixed Days'!$AA:$AA,0),MATCH(N$1,'Fixed Days'!$B$3:$P$3,0)),0)*IFERROR(IF(OR(TRIM("")="Evet",TRIM("")="Yes"),MAX(N('Module Selection'!$C10),1),1),1)+IFERROR(SUMIFS($BF$2:$BF$700,$BB$2:$BB$700,$A10,$BC$2:$BC$700,N$1),0)+0)) | O10: =IF(AND('Module Selection'!$B10<>"Var",'Module Selection'!$B10<>"Include"),"",IF($A10="","",IFERROR(INDEX('Fixed Days'!$B:$P,MATCH('Project Information'!$C$11&"|"&IF(Scope!$J$9="S","SMALL",IF(Scope!$J$9="M","MEDIUM",IF(Scope!$J$9="L","LARGE","X-LARGE")))&"|"&$A10,'Fixed Days'!$AA:$AA,0),MATCH(O$1,'Fixed Days'!$B$3:$P$3,0)),0)*IFERROR(IF(OR(TRIM("")="Evet",TRIM("")="Yes"),MAX(N('Module Selection'!$C10),1),1),1)+IFERROR(SUMIFS($BF$2:$BF$700,$BB$2:$BB$700,$A10,$BC$2:$BC$700,O$1),0)+IFERROR(INDEX('Hypercare & Go Live Support'!$G:$G,MATCH($A10,'Hypercare & Go Live Support'!$A:$A,0)),0))) | P10: =IF(AND('Module Selection'!$B10<>"Var",'Module Selection'!$B10<>"Include"),"",IF($A10="","",IFERROR(INDEX('Fixed Days'!$B:$P,MATCH('Project Information'!$C$11&"|"&IF(Scope!$J$9="S","SMALL",IF(Scope!$J$9="M","MEDIUM",IF(Scope!$J$9="L","LARGE","X-LARGE")))&"|"&$A10,'Fixed Days'!$AA:$AA,0),MATCH(P$1,'Fixed Days'!$B$3:$P$3,0)),0)*IFERROR(IF(OR(TRIM("")="Evet",TRIM("")="Yes"),MAX(N('Module Selection'!$C10),1),1),1)+IFERROR(SUMIFS($BF$2:$BF$700,$BB$2:$BB$700,$A10,$BC$2:$BC$700,P$1),0)+IFERROR(INDEX('Hypercare & Go Live Support'!$F:$F,MATCH($A10,'Hypercare & Go Live Support'!$A:$A,0)),0))) | Q10: =SUM(B10:P10) | AZ10: =INDEX(Translations!$D:$ZZ, MATCH(305,Translations!$A:$A,0), MATCH('Project Information'!$C$4,Translations!$D$1:$ZZ$1,0)) | BA10: =INDEX(Translations!$D:$ZZ, MATCH(32,Translations!$A:$A,0), MATCH('Project Information'!$C$4,Translations!$D$1:$ZZ$1,0)) | BB10: =INDEX(Translations!$D:$ZZ, MATCH(341,Translations!$A:$A,0), MATCH('Project Information'!$C$4,Translations!$D$1:$ZZ$1,0)) | BC10: =INDEX(Translations!$D:$ZZ, MATCH(82,Translations!$A:$A,0), MATCH('Project Information'!$C$4,Translations!$D$1:$ZZ$1,0)) | BD10: =IF(OR(TRIM("")="Evet",TRIM("")="Yes"),1,0) | BE10: 0.5 | BF10: =BD10*BE10 | BH10: =INDEX(Translations!$D:$ZZ, MATCH(306,Translations!$A:$A,0), MATCH('Project Information'!$C$4,Translations!$D$1:$ZZ$1,0)) | BI10: =INDEX(Translations!$D:$ZZ, MATCH(205,Translations!$A:$A,0), MATCH('Project Information'!$C$4,Translations!$D$1:$ZZ$1,0)) | BJ10: =INDEX(Translations!$D:$ZZ, MATCH(332,Translations!$A:$A,0), MATCH('Project Information'!$C$4,Translations!$D$1:$ZZ$1,0)) | BK10: =INDEX(Translations!$D:$ZZ, MATCH(75,Translations!$A:$A,0), MATCH('Project Information'!$C$4,Translations!$D$1:$ZZ$1,0)) | BL10: =MAX(N(Development!$G$17),0) | BM10: 0.5 | BN10: =BL10*BM10
A11: ='Project Definitions'!$D$11 | B11: =IF(AND('Module Selection'!$B11<>"Var",'Module Selection'!$B11<>"Include"),"",IF($A11="","",IFERROR(INDEX('Fixed Days'!$B:$P,MATCH('Project Information'!$C$11&"|"&IF(Scope!$J$9="S","SMALL",IF(Scope!$J$9="M","MEDIUM",IF(Scope!$J$9="L","LARGE","X-LARGE")))&"|"&$A11,'Fixed Days'!$AA:$AA,0),MATCH(B$1,'Fixed Days'!$B$3:$P$3,0)),0)*IFERROR(IF(OR(TRIM("")="Evet",TRIM("")="Yes"),MAX(N('Module Selection'!$C11),1),1),1)+IFERROR(SUMIFS($BF$2:$BF$700,$BB$2:$BB$700,$A11,$BC$2:$BC$700,B$1),0)+0)) | C11: =IF(AND('Module Selection'!$B11<>"Var",'Module Selection'!$B11<>"Include"),"",IF($A11="","",IFERROR(INDEX('Fixed Days'!$B:$P,MATCH('Project Information'!$C$11&"|"&IF(Scope!$J$9="S","SMALL",IF(Scope!$J$9="M","MEDIUM",IF(Scope!$J$9="L","LARGE","X-LARGE")))&"|"&$A11,'Fixed Days'!$AA:$AA,0),MATCH(C$1,'Fixed Days'!$B$3:$P$3,0)),0)*IFERROR(IF(OR(TRIM("")="Evet",TRIM("")="Yes"),MAX(N('Module Selection'!$C11),1),1),1)+IFERROR(SUMIFS($BF$2:$BF$700,$BB$2:$BB$700,$A11,$BC$2:$BC$700,C$1),0)+0)) | D11: =IF(AND('Module Selection'!$B11<>"Var",'Module Selection'!$B11<>"Include"),"",IF($A11="","",IFERROR(INDEX('Fixed Days'!$B:$P,MATCH('Project Information'!$C$11&"|"&IF(Scope!$J$9="S","SMALL",IF(Scope!$J$9="M","MEDIUM",IF(Scope!$J$9="L","LARGE","X-LARGE")))&"|"&$A11,'Fixed Days'!$AA:$AA,0),MATCH(D$1,'Fixed Days'!$B$3:$P$3,0)),0)*IFERROR(IF(OR(TRIM("")="Evet",TRIM("")="Yes"),MAX(N('Module Selection'!$C11),1),1),1)+IFERROR(SUMIFS($BF$2:$BF$700,$BB$2:$BB$700,$A11,$BC$2:$BC$700,D$1),0)+0)) | E11: =IF(AND('Module Selection'!$B11<>"Var",'Module Selection'!$B11<>"Include"),"",IF($A11="","",IFERROR(INDEX('Fixed Days'!$B:$P,MATCH('Project Information'!$C$11&"|"&IF(Scope!$J$9="S","SMALL",IF(Scope!$J$9="M","MEDIUM",IF(Scope!$J$9="L","LARGE","X-LARGE")))&"|"&$A11,'Fixed Days'!$AA:$AA,0),MATCH(E$1,'Fixed Days'!$B$3:$P$3,0)),0)*IFERROR(IF(OR(TRIM("")="Evet",TRIM("")="Yes"),MAX(N('Module Selection'!$C11),1),1),1)+IFERROR(SUMIFS($BF$2:$BF$700,$BB$2:$BB$700,$A11,$BC$2:$BC$700,E$1),0)+0)) | F11: =IF(AND('Module Selection'!$B11<>"Var",'Module Selection'!$B11<>"Include"),"",IF($A11="","",IFERROR(INDEX('Fixed Days'!$B:$P,MATCH('Project Information'!$C$11&"|"&IF(Scope!$J$9="S","SMALL",IF(Scope!$J$9="M","MEDIUM",IF(Scope!$J$9="L","LARGE","X-LARGE")))&"|"&$A11,'Fixed Days'!$AA:$AA,0),MATCH(F$1,'Fixed Days'!$B$3:$P$3,0)),0)*IFERROR(IF(OR(TRIM("")="Evet",TRIM("")="Yes"),MAX(N('Module Selection'!$C11),1),1),1)+IFERROR(SUMIFS($BF$2:$BF$700,$BB$2:$BB$700,$A11,$BC$2:$BC$700,F$1),0)+0)) | G11: =IF(AND('Module Selection'!$B11<>"Var",'Module Selection'!$B11<>"Include"),"",IF($A11="","",IFERROR(INDEX('Fixed Days'!$B:$P,MATCH('Project Information'!$C$11&"|"&IF(Scope!$J$9="S","SMALL",IF(Scope!$J$9="M","MEDIUM",IF(Scope!$J$9="L","LARGE","X-LARGE")))&"|"&$A11,'Fixed Days'!$AA:$AA,0),MATCH(G$1,'Fixed Days'!$B$3:$P$3,0)),0)*IFERROR(IF(OR(TRIM("")="Evet",TRIM("")="Yes"),MAX(N('Module Selection'!$C11),1),1),1)+IFERROR(SUMIFS($BF$2:$BF$700,$BB$2:$BB$700,$A11,$BC$2:$BC$700,G$1),0)+0)) | H11: =IF(AND('Module Selection'!$B11<>"Var",'Module Selection'!$B11<>"Include"),"",IF($A11="","",IFERROR(INDEX('Fixed Days'!$B:$P,MATCH('Project Information'!$C$11&"|"&IF(Scope!$J$9="S","SMALL",IF(Scope!$J$9="M","MEDIUM",IF(Scope!$J$9="L","LARGE","X-LARGE")))&"|"&$A11,'Fixed Days'!$AA:$AA,0),MATCH(H$1,'Fixed Days'!$B$3:$P$3,0)),0)*IFERROR(IF(OR(TRIM("")="Evet",TRIM("")="Yes"),MAX(N('Module Selection'!$C11),1),1),1)+IFERROR(SUMIFS($BF$2:$BF$700,$BB$2:$BB$700,$A11,$BC$2:$BC$700,H$1),0)+0)) | I11: =IF(AND('Module Selection'!$B11<>"Var",'Module Selection'!$B11<>"Include"),"",IF($A11="","",IFERROR(INDEX('Fixed Days'!$B:$P,MATCH('Project Information'!$C$11&"|"&IF(Scope!$J$9="S","SMALL",IF(Scope!$J$9="M","MEDIUM",IF(Scope!$J$9="L","LARGE","X-LARGE")))&"|"&$A11,'Fixed Days'!$AA:$AA,0),MATCH(I$1,'Fixed Days'!$B$3:$P$3,0)),0)*IFERROR(IF(OR(TRIM("")="Evet",TRIM("")="Yes"),MAX(N('Module Selection'!$C11),1),1),1)+IFERROR(SUMIFS($BF$2:$BF$700,$BB$2:$BB$700,$A11,$BC$2:$BC$700,I$1),0)+0)) | ... N11: =IF(AND('Module Selection'!$B11<>"Var",'Module Selection'!$B11<>"Include"),"",IF($A11="","",IFERROR(INDEX('Fixed Days'!$B:$P,MATCH('Project Information'!$C$11&"|"&IF(Scope!$J$9="S","SMALL",IF(Scope!$J$9="M","MEDIUM",IF(Scope!$J$9="L","LARGE","X-LARGE")))&"|"&$A11,'Fixed Days'!$AA:$AA,0),MATCH(N$1,'Fixed Days'!$B$3:$P$3,0)),0)*IFERROR(IF(OR(TRIM("")="Evet",TRIM("")="Yes"),MAX(N('Module Selection'!$C11),1),1),1)+IFERROR(SUMIFS($BF$2:$BF$700,$BB$2:$BB$700,$A11,$BC$2:$BC$700,N$1),0)+0)) | O11: =IF(AND('Module Selection'!$B11<>"Var",'Module Selection'!$B11<>"Include"),"",IF($A11="","",IFERROR(INDEX('Fixed Days'!$B:$P,MATCH('Project Information'!$C$11&"|"&IF(Scope!$J$9="S","SMALL",IF(Scope!$J$9="M","MEDIUM",IF(Scope!$J$9="L","LARGE","X-LARGE")))&"|"&$A11,'Fixed Days'!$AA:$AA,0),MATCH(O$1,'Fixed Days'!$B$3:$P$3,0)),0)*IFERROR(IF(OR(TRIM("")="Evet",TRIM("")="Yes"),MAX(N('Module Selection'!$C11),1),1),1)+IFERROR(SUMIFS($BF$2:$BF$700,$BB$2:$BB$700,$A11,$BC$2:$BC$700,O$1),0)+IFERROR(INDEX('Hypercare & Go Live Support'!$G:$G,MATCH($A11,'Hypercare & Go Live Support'!$A:$A,0)),0))) | P11: =IF(AND('Module Selection'!$B11<>"Var",'Module Selection'!$B11<>"Include"),"",IF($A11="","",IFERROR(INDEX('Fixed Days'!$B:$P,MATCH('Project Information'!$C$11&"|"&IF(Scope!$J$9="S","SMALL",IF(Scope!$J$9="M","MEDIUM",IF(Scope!$J$9="L","LARGE","X-LARGE")))&"|"&$A11,'Fixed Days'!$AA:$AA,0),MATCH(P$1,'Fixed Days'!$B$3:$P$3,0)),0)*IFERROR(IF(OR(TRIM("")="Evet",TRIM("")="Yes"),MAX(N('Module Selection'!$C11),1),1),1)+IFERROR(SUMIFS($BF$2:$BF$700,$BB$2:$BB$700,$A11,$BC$2:$BC$700,P$1),0)+IFERROR(INDEX('Hypercare & Go Live Support'!$F:$F,MATCH($A11,'Hypercare & Go Live Support'!$A:$A,0)),0))) | Q11: =SUM(B11:P11) | AZ11: =INDEX(Translations!$D:$ZZ, MATCH(305,Translations!$A:$A,0), MATCH('Project Information'!$C$4,Translations!$D$1:$ZZ$1,0)) | BA11: =INDEX(Translations!$D:$ZZ, MATCH(32,Translations!$A:$A,0), MATCH('Project Information'!$C$4,Translations!$D$1:$ZZ$1,0)) | BB11: =INDEX(Translations!$D:$ZZ, MATCH(341,Translations!$A:$A,0), MATCH('Project Information'!$C$4,Translations!$D$1:$ZZ$1,0)) | BC11: =INDEX(Translations!$D:$ZZ, MATCH(83,Translations!$A:$A,0), MATCH('Project Information'!$C$4,Translations!$D$1:$ZZ$1,0)) | BD11: =IF(OR(TRIM("")="Evet",TRIM("")="Yes"),1,0) | BE11: 1 | BF11: =BD11*BE11 | BH11: =INDEX(Translations!$D:$ZZ, MATCH(306,Translations!$A:$A,0), MATCH('Project Information'!$C$4,Translations!$D$1:$ZZ$1,0)) | BI11: =INDEX(Translations!$D:$ZZ, MATCH(205,Translations!$A:$A,0), MATCH('Project Information'!$C$4,Translations!$D$1:$ZZ$1,0)) | BJ11: =INDEX(Translations!$D:$ZZ, MATCH(332,Translations!$A:$A,0), MATCH('Project Information'!$C$4,Translations!$D$1:$ZZ$1,0)) | BK11: =INDEX(Translations!$D:$ZZ, MATCH(76,Translations!$A:$A,0), MATCH('Project Information'!$C$4,Translations!$D$1:$ZZ$1,0)) | BL11: =MAX(N(Development!$G$17),0) | BM11: 0.25 | BN11: =BL11*BM11
A12: ='Project Definitions'!$D$12 | B12: =IF(AND('Module Selection'!$B12<>"Var",'Module Selection'!$B12<>"Include"),"",IF($A12="","",IFERROR(INDEX('Fixed Days'!$B:$P,MATCH('Project Information'!$C$11&"|"&IF(Scope!$J$9="S","SMALL",IF(Scope!$J$9="M","MEDIUM",IF(Scope!$J$9="L","LARGE","X-LARGE")))&"|"&$A12,'Fixed Days'!$AA:$AA,0),MATCH(B$1,'Fixed Days'!$B$3:$P$3,0)),0)*IFERROR(IF(OR(TRIM("")="Evet",TRIM("")="Yes"),MAX(N('Module Selection'!$C12),1),1),1)+IFERROR(SUMIFS($BF$2:$BF$700,$BB$2:$BB$700,$A12,$BC$2:$BC$700,B$1),0)+0)) | C12: =IF(AND('Module Selection'!$B12<>"Var",'Module Selection'!$B12<>"Include"),"",IF($A12="","",IFERROR(INDEX('Fixed Days'!$B:$P,MATCH('Project Information'!$C$11&"|"&IF(Scope!$J$9="S","SMALL",IF(Scope!$J$9="M","MEDIUM",IF(Scope!$J$9="L","LARGE","X-LARGE")))&"|"&$A12,'Fixed Days'!$AA:$AA,0),MATCH(C$1,'Fixed Days'!$B$3:$P$3,0)),0)*IFERROR(IF(OR(TRIM("")="Evet",TRIM("")="Yes"),MAX(N('Module Selection'!$C12),1),1),1)+IFERROR(SUMIFS($BF$2:$BF$700,$BB$2:$BB$700,$A12,$BC$2:$BC$700,C$1),0)+0)) | D12: =IF(AND('Module Selection'!$B12<>"Var",'Module Selection'!$B12<>"Include"),"",IF($A12="","",IFERROR(INDEX('Fixed Days'!$B:$P,MATCH('Project Information'!$C$11&"|"&IF(Scope!$J$9="S","SMALL",IF(Scope!$J$9="M","MEDIUM",IF(Scope!$J$9="L","LARGE","X-LARGE")))&"|"&$A12,'Fixed Days'!$AA:$AA,0),MATCH(D$1,'Fixed Days'!$B$3:$P$3,0)),0)*IFERROR(IF(OR(TRIM("")="Evet",TRIM("")="Yes"),MAX(N('Module Selection'!$C12),1),1),1)+IFERROR(SUMIFS($BF$2:$BF$700,$BB$2:$BB$700,$A12,$BC$2:$BC$700,D$1),0)+0)) | E12: =IF(AND('Module Selection'!$B12<>"Var",'Module Selection'!$B12<>"Include"),"",IF($A12="","",IFERROR(INDEX('Fixed Days'!$B:$P,MATCH('Project Information'!$C$11&"|"&IF(Scope!$J$9="S","SMALL",IF(Scope!$J$9="M","MEDIUM",IF(Scope!$J$9="L","LARGE","X-LARGE")))&"|"&$A12,'Fixed Days'!$AA:$AA,0),MATCH(E$1,'Fixed Days'!$B$3:$P$3,0)),0)*IFERROR(IF(OR(TRIM("")="Evet",TRIM("")="Yes"),MAX(N('Module Selection'!$C12),1),1),1)+IFERROR(SUMIFS($BF$2:$BF$700,$BB$2:$BB$700,$A12,$BC$2:$BC$700,E$1),0)+0)) | F12: =IF(AND('Module Selection'!$B12<>"Var",'Module Selection'!$B12<>"Include"),"",IF($A12="","",IFERROR(INDEX('Fixed Days'!$B:$P,MATCH('Project Information'!$C$11&"|"&IF(Scope!$J$9="S","SMALL",IF(Scope!$J$9="M","MEDIUM",IF(Scope!$J$9="L","LARGE","X-LARGE")))&"|"&$A12,'Fixed Days'!$AA:$AA,0),MATCH(F$1,'Fixed Days'!$B$3:$P$3,0)),0)*IFERROR(IF(OR(TRIM("")="Evet",TRIM("")="Yes"),MAX(N('Module Selection'!$C12),1),1),1)+IFERROR(SUMIFS($BF$2:$BF$700,$BB$2:$BB$700,$A12,$BC$2:$BC$700,F$1),0)+0)) | G12: =IF(AND('Module Selection'!$B12<>"Var",'Module Selection'!$B12<>"Include"),"",IF($A12="","",IFERROR(INDEX('Fixed Days'!$B:$P,MATCH('Project Information'!$C$11&"|"&IF(Scope!$J$9="S","SMALL",IF(Scope!$J$9="M","MEDIUM",IF(Scope!$J$9="L","LARGE","X-LARGE")))&"|"&$A12,'Fixed Days'!$AA:$AA,0),MATCH(G$1,'Fixed Days'!$B$3:$P$3,0)),0)*IFERROR(IF(OR(TRIM("")="Evet",TRIM("")="Yes"),MAX(N('Module Selection'!$C12),1),1),1)+IFERROR(SUMIFS($BF$2:$BF$700,$BB$2:$BB$700,$A12,$BC$2:$BC$700,G$1),0)+0)) | H12: =IF(AND('Module Selection'!$B12<>"Var",'Module Selection'!$B12<>"Include"),"",IF($A12="","",IFERROR(INDEX('Fixed Days'!$B:$P,MATCH('Project Information'!$C$11&"|"&IF(Scope!$J$9="S","SMALL",IF(Scope!$J$9="M","MEDIUM",IF(Scope!$J$9="L","LARGE","X-LARGE")))&"|"&$A12,'Fixed Days'!$AA:$AA,0),MATCH(H$1,'Fixed Days'!$B$3:$P$3,0)),0)*IFERROR(IF(OR(TRIM("")="Evet",TRIM("")="Yes"),MAX(N('Module Selection'!$C12),1),1),1)+IFERROR(SUMIFS($BF$2:$BF$700,$BB$2:$BB$700,$A12,$BC$2:$BC$700,H$1),0)+0)) | I12: =IF(AND('Module Selection'!$B12<>"Var",'Module Selection'!$B12<>"Include"),"",IF($A12="","",IFERROR(INDEX('Fixed Days'!$B:$P,MATCH('Project Information'!$C$11&"|"&IF(Scope!$J$9="S","SMALL",IF(Scope!$J$9="M","MEDIUM",IF(Scope!$J$9="L","LARGE","X-LARGE")))&"|"&$A12,'Fixed Days'!$AA:$AA,0),MATCH(I$1,'Fixed Days'!$B$3:$P$3,0)),0)*IFERROR(IF(OR(TRIM("")="Evet",TRIM("")="Yes"),MAX(N('Module Selection'!$C12),1),1),1)+IFERROR(SUMIFS($BF$2:$BF$700,$BB$2:$BB$700,$A12,$BC$2:$BC$700,I$1),0)+0)) | ... N12: =IF(AND('Module Selection'!$B12<>"Var",'Module Selection'!$B12<>"Include"),"",IF($A12="","",IFERROR(INDEX('Fixed Days'!$B:$P,MATCH('Project Information'!$C$11&"|"&IF(Scope!$J$9="S","SMALL",IF(Scope!$J$9="M","MEDIUM",IF(Scope!$J$9="L","LARGE","X-LARGE")))&"|"&$A12,'Fixed Days'!$AA:$AA,0),MATCH(N$1,'Fixed Days'!$B$3:$P$3,0)),0)*IFERROR(IF(OR(TRIM("")="Evet",TRIM("")="Yes"),MAX(N('Module Selection'!$C12),1),1),1)+IFERROR(SUMIFS($BF$2:$BF$700,$BB$2:$BB$700,$A12,$BC$2:$BC$700,N$1),0)+0)) | O12: =IF(AND('Module Selection'!$B12<>"Var",'Module Selection'!$B12<>"Include"),"",IF($A12="","",IFERROR(INDEX('Fixed Days'!$B:$P,MATCH('Project Information'!$C$11&"|"&IF(Scope!$J$9="S","SMALL",IF(Scope!$J$9="M","MEDIUM",IF(Scope!$J$9="L","LARGE","X-LARGE")))&"|"&$A12,'Fixed Days'!$AA:$AA,0),MATCH(O$1,'Fixed Days'!$B$3:$P$3,0)),0)*IFERROR(IF(OR(TRIM("")="Evet",TRIM("")="Yes"),MAX(N('Module Selection'!$C12),1),1),1)+IFERROR(SUMIFS($BF$2:$BF$700,$BB$2:$BB$700,$A12,$BC$2:$BC$700,O$1),0)+IFERROR(INDEX('Hypercare & Go Live Support'!$G:$G,MATCH($A12,'Hypercare & Go Live Support'!$A:$A,0)),0))) | P12: =IF(AND('Module Selection'!$B12<>"Var",'Module Selection'!$B12<>"Include"),"",IF($A12="","",IFERROR(INDEX('Fixed Days'!$B:$P,MATCH('Project Information'!$C$11&"|"&IF(Scope!$J$9="S","SMALL",IF(Scope!$J$9="M","MEDIUM",IF(Scope!$J$9="L","LARGE","X-LARGE")))&"|"&$A12,'Fixed Days'!$AA:$AA,0),MATCH(P$1,'Fixed Days'!$B$3:$P$3,0)),0)*IFERROR(IF(OR(TRIM("")="Evet",TRIM("")="Yes"),MAX(N('Module Selection'!$C12),1),1),1)+IFERROR(SUMIFS($BF$2:$BF$700,$BB$2:$BB$700,$A12,$BC$2:$BC$700,P$1),0)+IFERROR(INDEX('Hypercare & Go Live Support'!$F:$F,MATCH($A12,'Hypercare & Go Live Support'!$A:$A,0)),0))) | Q12: =SUM(B12:P12) | AZ12: =INDEX(Translations!$D:$ZZ, MATCH(305,Translations!$A:$A,0), MATCH('Project Information'!$C$4,Translations!$D$1:$ZZ$1,0)) | BA12: =INDEX(Translations!$D:$ZZ, MATCH(32,Translations!$A:$A,0), MATCH('Project Information'!$C$4,Translations!$D$1:$ZZ$1,0)) | BB12: =INDEX(Translations!$D:$ZZ, MATCH(338,Translations!$A:$A,0), MATCH('Project Information'!$C$4,Translations!$D$1:$ZZ$1,0)) | BC12: =INDEX(Translations!$D:$ZZ, MATCH(75,Translations!$A:$A,0), MATCH('Project Information'!$C$4,Translations!$D$1:$ZZ$1,0)) | BD12: =IF(OR(TRIM("")="Evet",TRIM("")="Yes"),1,0) | BE12: 6 | BF12: =BD12*BE12 | BH12: =INDEX(Translations!$D:$ZZ, MATCH(306,Translations!$A:$A,0), MATCH('Project Information'!$C$4,Translations!$D$1:$ZZ$1,0)) | BI12: =INDEX(Translations!$D:$ZZ, MATCH(205,Translations!$A:$A,0), MATCH('Project Information'!$C$4,Translations!$D$1:$ZZ$1,0)) | BJ12: =INDEX(Translations!$D:$ZZ, MATCH(332,Translations!$A:$A,0), MATCH('Project Information'!$C$4,Translations!$D$1:$ZZ$1,0)) | BK12: =INDEX(Translations!$D:$ZZ, MATCH(79,Translations!$A:$A,0), MATCH('Project Information'!$C$4,Translations!$D$1:$ZZ$1,0)) | BL12: =MAX(N(Development!$G$17),0) | BM12: 3 | BN12: =BL12*BM12
A13: ='Project Definitions'!$D$13 | B13: =IF(AND('Module Selection'!$B13<>"Var",'Module Selection'!$B13<>"Include"),"",IF($A13="","",IFERROR(INDEX('Fixed Days'!$B:$P,MATCH('Project Information'!$C$11&"|"&IF(Scope!$J$9="S","SMALL",IF(Scope!$J$9="M","MEDIUM",IF(Scope!$J$9="L","LARGE","X-LARGE")))&"|"&$A13,'Fixed Days'!$AA:$AA,0),MATCH(B$1,'Fixed Days'!$B$3:$P$3,0)),0)*IFERROR(IF(OR(TRIM("")="Evet",TRIM("")="Yes"),MAX(N('Module Selection'!$C13),1),1),1)+IFERROR(SUMIFS($BF$2:$BF$700,$BB$2:$BB$700,$A13,$BC$2:$BC$700,B$1),0)+0)) | C13: =IF(AND('Module Selection'!$B13<>"Var",'Module Selection'!$B13<>"Include"),"",IF($A13="","",IFERROR(INDEX('Fixed Days'!$B:$P,MATCH('Project Information'!$C$11&"|"&IF(Scope!$J$9="S","SMALL",IF(Scope!$J$9="M","MEDIUM",IF(Scope!$J$9="L","LARGE","X-LARGE")))&"|"&$A13,'Fixed Days'!$AA:$AA,0),MATCH(C$1,'Fixed Days'!$B$3:$P$3,0)),0)*IFERROR(IF(OR(TRIM("")="Evet",TRIM("")="Yes"),MAX(N('Module Selection'!$C13),1),1),1)+IFERROR(SUMIFS($BF$2:$BF$700,$BB$2:$BB$700,$A13,$BC$2:$BC$700,C$1),0)+0)) | D13: =IF(AND('Module Selection'!$B13<>"Var",'Module Selection'!$B13<>"Include"),"",IF($A13="","",IFERROR(INDEX('Fixed Days'!$B:$P,MATCH('Project Information'!$C$11&"|"&IF(Scope!$J$9="S","SMALL",IF(Scope!$J$9="M","MEDIUM",IF(Scope!$J$9="L","LARGE","X-LARGE")))&"|"&$A13,'Fixed Days'!$AA:$AA,0),MATCH(D$1,'Fixed Days'!$B$3:$P$3,0)),0)*IFERROR(IF(OR(TRIM("")="Evet",TRIM("")="Yes"),MAX(N('Module Selection'!$C13),1),1),1)+IFERROR(SUMIFS($BF$2:$BF$700,$BB$2:$BB$700,$A13,$BC$2:$BC$700,D$1),0)+0)) | E13: =IF(AND('Module Selection'!$B13<>"Var",'Module Selection'!$B13<>"Include"),"",IF($A13="","",IFERROR(INDEX('Fixed Days'!$B:$P,MATCH('Project Information'!$C$11&"|"&IF(Scope!$J$9="S","SMALL",IF(Scope!$J$9="M","MEDIUM",IF(Scope!$J$9="L","LARGE","X-LARGE")))&"|"&$A13,'Fixed Days'!$AA:$AA,0),MATCH(E$1,'Fixed Days'!$B$3:$P$3,0)),0)*IFERROR(IF(OR(TRIM("")="Evet",TRIM("")="Yes"),MAX(N('Module Selection'!$C13),1),1),1)+IFERROR(SUMIFS($BF$2:$BF$700,$BB$2:$BB$700,$A13,$BC$2:$BC$700,E$1),0)+0)) | F13: =IF(AND('Module Selection'!$B13<>"Var",'Module Selection'!$B13<>"Include"),"",IF($A13="","",IFERROR(INDEX('Fixed Days'!$B:$P,MATCH('Project Information'!$C$11&"|"&IF(Scope!$J$9="S","SMALL",IF(Scope!$J$9="M","MEDIUM",IF(Scope!$J$9="L","LARGE","X-LARGE")))&"|"&$A13,'Fixed Days'!$AA:$AA,0),MATCH(F$1,'Fixed Days'!$B$3:$P$3,0)),0)*IFERROR(IF(OR(TRIM("")="Evet",TRIM("")="Yes"),MAX(N('Module Selection'!$C13),1),1),1)+IFERROR(SUMIFS($BF$2:$BF$700,$BB$2:$BB$700,$A13,$BC$2:$BC$700,F$1),0)+0)) | G13: =IF(AND('Module Selection'!$B13<>"Var",'Module Selection'!$B13<>"Include"),"",IF($A13="","",IFERROR(INDEX('Fixed Days'!$B:$P,MATCH('Project Information'!$C$11&"|"&IF(Scope!$J$9="S","SMALL",IF(Scope!$J$9="M","MEDIUM",IF(Scope!$J$9="L","LARGE","X-LARGE")))&"|"&$A13,'Fixed Days'!$AA:$AA,0),MATCH(G$1,'Fixed Days'!$B$3:$P$3,0)),0)*IFERROR(IF(OR(TRIM("")="Evet",TRIM("")="Yes"),MAX(N('Module Selection'!$C13),1),1),1)+IFERROR(SUMIFS($BF$2:$BF$700,$BB$2:$BB$700,$A13,$BC$2:$BC$700,G$1),0)+0)) | H13: =IF(AND('Module Selection'!$B13<>"Var",'Module Selection'!$B13<>"Include"),"",IF($A13="","",IFERROR(INDEX('Fixed Days'!$B:$P,MATCH('Project Information'!$C$11&"|"&IF(Scope!$J$9="S","SMALL",IF(Scope!$J$9="M","MEDIUM",IF(Scope!$J$9="L","LARGE","X-LARGE")))&"|"&$A13,'Fixed Days'!$AA:$AA,0),MATCH(H$1,'Fixed Days'!$B$3:$P$3,0)),0)*IFERROR(IF(OR(TRIM("")="Evet",TRIM("")="Yes"),MAX(N('Module Selection'!$C13),1),1),1)+IFERROR(SUMIFS($BF$2:$BF$700,$BB$2:$BB$700,$A13,$BC$2:$BC$700,H$1),0)+0)) | I13: =IF(AND('Module Selection'!$B13<>"Var",'Module Selection'!$B13<>"Include"),"",IF($A13="","",IFERROR(INDEX('Fixed Days'!$B:$P,MATCH('Project Information'!$C$11&"|"&IF(Scope!$J$9="S","SMALL",IF(Scope!$J$9="M","MEDIUM",IF(Scope!$J$9="L","LARGE","X-LARGE")))&"|"&$A13,'Fixed Days'!$AA:$AA,0),MATCH(I$1,'Fixed Days'!$B$3:$P$3,0)),0)*IFERROR(IF(OR(TRIM("")="Evet",TRIM("")="Yes"),MAX(N('Module Selection'!$C13),1),1),1)+IFERROR(SUMIFS($BF$2:$BF$700,$BB$2:$BB$700,$A13,$BC$2:$BC$700,I$1),0)+0)) | ... N13: =IF(AND('Module Selection'!$B13<>"Var",'Module Selection'!$B13<>"Include"),"",IF($A13="","",IFERROR(INDEX('Fixed Days'!$B:$P,MATCH('Project Information'!$C$11&"|"&IF(Scope!$J$9="S","SMALL",IF(Scope!$J$9="M","MEDIUM",IF(Scope!$J$9="L","LARGE","X-LARGE")))&"|"&$A13,'Fixed Days'!$AA:$AA,0),MATCH(N$1,'Fixed Days'!$B$3:$P$3,0)),0)*IFERROR(IF(OR(TRIM("")="Evet",TRIM("")="Yes"),MAX(N('Module Selection'!$C13),1),1),1)+IFERROR(SUMIFS($BF$2:$BF$700,$BB$2:$BB$700,$A13,$BC$2:$BC$700,N$1),0)+0)) | O13: =IF(AND('Module Selection'!$B13<>"Var",'Module Selection'!$B13<>"Include"),"",IF($A13="","",IFERROR(INDEX('Fixed Days'!$B:$P,MATCH('Project Information'!$C$11&"|"&IF(Scope!$J$9="S","SMALL",IF(Scope!$J$9="M","MEDIUM",IF(Scope!$J$9="L","LARGE","X-LARGE")))&"|"&$A13,'Fixed Days'!$AA:$AA,0),MATCH(O$1,'Fixed Days'!$B$3:$P$3,0)),0)*IFERROR(IF(OR(TRIM("")="Evet",TRIM("")="Yes"),MAX(N('Module Selection'!$C13),1),1),1)+IFERROR(SUMIFS($BF$2:$BF$700,$BB$2:$BB$700,$A13,$BC$2:$BC$700,O$1),0)+IFERROR(INDEX('Hypercare & Go Live Support'!$G:$G,MATCH($A13,'Hypercare & Go Live Support'!$A:$A,0)),0))) | P13: =IF(AND('Module Selection'!$B13<>"Var",'Module Selection'!$B13<>"Include"),"",IF($A13="","",IFERROR(INDEX('Fixed Days'!$B:$P,MATCH('Project Information'!$C$11&"|"&IF(Scope!$J$9="S","SMALL",IF(Scope!$J$9="M","MEDIUM",IF(Scope!$J$9="L","LARGE","X-LARGE")))&"|"&$A13,'Fixed Days'!$AA:$AA,0),MATCH(P$1,'Fixed Days'!$B$3:$P$3,0)),0)*IFERROR(IF(OR(TRIM("")="Evet",TRIM("")="Yes"),MAX(N('Module Selection'!$C13),1),1),1)+IFERROR(SUMIFS($BF$2:$BF$700,$BB$2:$BB$700,$A13,$BC$2:$BC$700,P$1),0)+IFERROR(INDEX('Hypercare & Go Live Support'!$F:$F,MATCH($A13,'Hypercare & Go Live Support'!$A:$A,0)),0))) | Q13: =SUM(B13:P13) | AZ13: =INDEX(Translations!$D:$ZZ, MATCH(305,Translations!$A:$A,0), MATCH('Project Information'!$C$4,Translations!$D$1:$ZZ$1,0)) | BA13: =INDEX(Translations!$D:$ZZ, MATCH(32,Translations!$A:$A,0), MATCH('Project Information'!$C$4,Translations!$D$1:$ZZ$1,0)) | BB13: =INDEX(Translations!$D:$ZZ, MATCH(338,Translations!$A:$A,0), MATCH('Project Information'!$C$4,Translations!$D$1:$ZZ$1,0)) | BC13: =INDEX(Translations!$D:$ZZ, MATCH(76,Translations!$A:$A,0), MATCH('Project Information'!$C$4,Translations!$D$1:$ZZ$1,0)) | BD13: =IF(OR(TRIM("")="Evet",TRIM("")="Yes"),1,0) | BE13: 2 | BF13: =BD13*BE13 | BH13: =INDEX(Translations!$D:$ZZ, MATCH(306,Translations!$A:$A,0), MATCH('Project Information'!$C$4,Translations!$D$1:$ZZ$1,0)) | BI13: =INDEX(Translations!$D:$ZZ, MATCH(215,Translations!$A:$A,0), MATCH('Project Information'!$C$4,Translations!$D$1:$ZZ$1,0)) | BJ13: =INDEX(Translations!$D:$ZZ, MATCH(346,Translations!$A:$A,0), MATCH('Project Information'!$C$4,Translations!$D$1:$ZZ$1,0)) | BK13: =INDEX(Translations!$D:$ZZ, MATCH(78,Translations!$A:$A,0), MATCH('Project Information'!$C$4,Translations!$D$1:$ZZ$1,0)) | BL13: =IF(OR(TRIM(Development!$F$21)="Evet",TRIM(Development!$F$21)="Yes"),1,0) | BM13: 12 | BN13: =BL13*BM13
A14: ='Project Definitions'!$D$14 | B14: =IF(AND('Module Selection'!$B14<>"Var",'Module Selection'!$B14<>"Include"),"",IF($A14="","",IFERROR(INDEX('Fixed Days'!$B:$P,MATCH('Project Information'!$C$11&"|"&IF(Scope!$J$9="S","SMALL",IF(Scope!$J$9="M","MEDIUM",IF(Scope!$J$9="L","LARGE","X-LARGE")))&"|"&$A14,'Fixed Days'!$AA:$AA,0),MATCH(B$1,'Fixed Days'!$B$3:$P$3,0)),0)*IFERROR(IF(OR(TRIM("")="Evet",TRIM("")="Yes"),MAX(N('Module Selection'!$C14),1),1),1)+IFERROR(SUMIFS($BF$2:$BF$700,$BB$2:$BB$700,$A14,$BC$2:$BC$700,B$1),0)+0)) | C14: =IF(AND('Module Selection'!$B14<>"Var",'Module Selection'!$B14<>"Include"),"",IF($A14="","",IFERROR(INDEX('Fixed Days'!$B:$P,MATCH('Project Information'!$C$11&"|"&IF(Scope!$J$9="S","SMALL",IF(Scope!$J$9="M","MEDIUM",IF(Scope!$J$9="L","LARGE","X-LARGE")))&"|"&$A14,'Fixed Days'!$AA:$AA,0),MATCH(C$1,'Fixed Days'!$B$3:$P$3,0)),0)*IFERROR(IF(OR(TRIM("")="Evet",TRIM("")="Yes"),MAX(N('Module Selection'!$C14),1),1),1)+IFERROR(SUMIFS($BF$2:$BF$700,$BB$2:$BB$700,$A14,$BC$2:$BC$700,C$1),0)+0)) | D14: =IF(AND('Module Selection'!$B14<>"Var",'Module Selection'!$B14<>"Include"),"",IF($A14="","",IFERROR(INDEX('Fixed Days'!$B:$P,MATCH('Project Information'!$C$11&"|"&IF(Scope!$J$9="S","SMALL",IF(Scope!$J$9="M","MEDIUM",IF(Scope!$J$9="L","LARGE","X-LARGE")))&"|"&$A14,'Fixed Days'!$AA:$AA,0),MATCH(D$1,'Fixed Days'!$B$3:$P$3,0)),0)*IFERROR(IF(OR(TRIM("")="Evet",TRIM("")="Yes"),MAX(N('Module Selection'!$C14),1),1),1)+IFERROR(SUMIFS($BF$2:$BF$700,$BB$2:$BB$700,$A14,$BC$2:$BC$700,D$1),0)+0)) | E14: =IF(AND('Module Selection'!$B14<>"Var",'Module Selection'!$B14<>"Include"),"",IF($A14="","",IFERROR(INDEX('Fixed Days'!$B:$P,MATCH('Project Information'!$C$11&"|"&IF(Scope!$J$9="S","SMALL",IF(Scope!$J$9="M","MEDIUM",IF(Scope!$J$9="L","LARGE","X-LARGE")))&"|"&$A14,'Fixed Days'!$AA:$AA,0),MATCH(E$1,'Fixed Days'!$B$3:$P$3,0)),0)*IFERROR(IF(OR(TRIM("")="Evet",TRIM("")="Yes"),MAX(N('Module Selection'!$C14),1),1),1)+IFERROR(SUMIFS($BF$2:$BF$700,$BB$2:$BB$700,$A14,$BC$2:$BC$700,E$1),0)+0)) | F14: =IF(AND('Module Selection'!$B14<>"Var",'Module Selection'!$B14<>"Include"),"",IF($A14="","",IFERROR(INDEX('Fixed Days'!$B:$P,MATCH('Project Information'!$C$11&"|"&IF(Scope!$J$9="S","SMALL",IF(Scope!$J$9="M","MEDIUM",IF(Scope!$J$9="L","LARGE","X-LARGE")))&"|"&$A14,'Fixed Days'!$AA:$AA,0),MATCH(F$1,'Fixed Days'!$B$3:$P$3,0)),0)*IFERROR(IF(OR(TRIM("")="Evet",TRIM("")="Yes"),MAX(N('Module Selection'!$C14),1),1),1)+IFERROR(SUMIFS($BF$2:$BF$700,$BB$2:$BB$700,$A14,$BC$2:$BC$700,F$1),0)+0)) | G14: =IF(AND('Module Selection'!$B14<>"Var",'Module Selection'!$B14<>"Include"),"",IF($A14="","",IFERROR(INDEX('Fixed Days'!$B:$P,MATCH('Project Information'!$C$11&"|"&IF(Scope!$J$9="S","SMALL",IF(Scope!$J$9="M","MEDIUM",IF(Scope!$J$9="L","LARGE","X-LARGE")))&"|"&$A14,'Fixed Days'!$AA:$AA,0),MATCH(G$1,'Fixed Days'!$B$3:$P$3,0)),0)*IFERROR(IF(OR(TRIM("")="Evet",TRIM("")="Yes"),MAX(N('Module Selection'!$C14),1),1),1)+IFERROR(SUMIFS($BF$2:$BF$700,$BB$2:$BB$700,$A14,$BC$2:$BC$700,G$1),0)+0)) | H14: =IF(AND('Module Selection'!$B14<>"Var",'Module Selection'!$B14<>"Include"),"",IF($A14="","",IFERROR(INDEX('Fixed Days'!$B:$P,MATCH('Project Information'!$C$11&"|"&IF(Scope!$J$9="S","SMALL",IF(Scope!$J$9="M","MEDIUM",IF(Scope!$J$9="L","LARGE","X-LARGE")))&"|"&$A14,'Fixed Days'!$AA:$AA,0),MATCH(H$1,'Fixed Days'!$B$3:$P$3,0)),0)*IFERROR(IF(OR(TRIM("")="Evet",TRIM("")="Yes"),MAX(N('Module Selection'!$C14),1),1),1)+IFERROR(SUMIFS($BF$2:$BF$700,$BB$2:$BB$700,$A14,$BC$2:$BC$700,H$1),0)+0)) | I14: =IF(AND('Module Selection'!$B14<>"Var",'Module Selection'!$B14<>"Include"),"",IF($A14="","",IFERROR(INDEX('Fixed Days'!$B:$P,MATCH('Project Information'!$C$11&"|"&IF(Scope!$J$9="S","SMALL",IF(Scope!$J$9="M","MEDIUM",IF(Scope!$J$9="L","LARGE","X-LARGE")))&"|"&$A14,'Fixed Days'!$AA:$AA,0),MATCH(I$1,'Fixed Days'!$B$3:$P$3,0)),0)*IFERROR(IF(OR(TRIM("")="Evet",TRIM("")="Yes"),MAX(N('Module Selection'!$C14),1),1),1)+IFERROR(SUMIFS($BF$2:$BF$700,$BB$2:$BB$700,$A14,$BC$2:$BC$700,I$1),0)+0)) | ... N14: =IF(AND('Module Selection'!$B14<>"Var",'Module Selection'!$B14<>"Include"),"",IF($A14="","",IFERROR(INDEX('Fixed Days'!$B:$P,MATCH('Project Information'!$C$11&"|"&IF(Scope!$J$9="S","SMALL",IF(Scope!$J$9="M","MEDIUM",IF(Scope!$J$9="L","LARGE","X-LARGE")))&"|"&$A14,'Fixed Days'!$AA:$AA,0),MATCH(N$1,'Fixed Days'!$B$3:$P$3,0)),0)*IFERROR(IF(OR(TRIM("")="Evet",TRIM("")="Yes"),MAX(N('Module Selection'!$C14),1),1),1)+IFERROR(SUMIFS($BF$2:$BF$700,$BB$2:$BB$700,$A14,$BC$2:$BC$700,N$1),0)+0)) | O14: =IF(AND('Module Selection'!$B14<>"Var",'Module Selection'!$B14<>"Include"),"",IF($A14="","",IFERROR(INDEX('Fixed Days'!$B:$P,MATCH('Project Information'!$C$11&"|"&IF(Scope!$J$9="S","SMALL",IF(Scope!$J$9="M","MEDIUM",IF(Scope!$J$9="L","LARGE","X-LARGE")))&"|"&$A14,'Fixed Days'!$AA:$AA,0),MATCH(O$1,'Fixed Days'!$B$3:$P$3,0)),0)*IFERROR(IF(OR(TRIM("")="Evet",TRIM("")="Yes"),MAX(N('Module Selection'!$C14),1),1),1)+IFERROR(SUMIFS($BF$2:$BF$700,$BB$2:$BB$700,$A14,$BC$2:$BC$700,O$1),0)+IFERROR(INDEX('Hypercare & Go Live Support'!$G:$G,MATCH($A14,'Hypercare & Go Live Support'!$A:$A,0)),0))) | P14: =IF(AND('Module Selection'!$B14<>"Var",'Module Selection'!$B14<>"Include"),"",IF($A14="","",IFERROR(INDEX('Fixed Days'!$B:$P,MATCH('Project Information'!$C$11&"|"&IF(Scope!$J$9="S","SMALL",IF(Scope!$J$9="M","MEDIUM",IF(Scope!$J$9="L","LARGE","X-LARGE")))&"|"&$A14,'Fixed Days'!$AA:$AA,0),MATCH(P$1,'Fixed Days'!$B$3:$P$3,0)),0)*IFERROR(IF(OR(TRIM("")="Evet",TRIM("")="Yes"),MAX(N('Module Selection'!$C14),1),1),1)+IFERROR(SUMIFS($BF$2:$BF$700,$BB$2:$BB$700,$A14,$BC$2:$BC$700,P$1),0)+IFERROR(INDEX('Hypercare & Go Live Support'!$F:$F,MATCH($A14,'Hypercare & Go Live Support'!$A:$A,0)),0))) | Q14: =SUM(B14:P14) | AZ14: =INDEX(Translations!$D:$ZZ, MATCH(305,Translations!$A:$A,0), MATCH('Project Information'!$C$4,Translations!$D$1:$ZZ$1,0)) | BA14: =INDEX(Translations!$D:$ZZ, MATCH(32,Translations!$A:$A,0), MATCH('Project Information'!$C$4,Translations!$D$1:$ZZ$1,0)) | BB14: =INDEX(Translations!$D:$ZZ, MATCH(338,Translations!$A:$A,0), MATCH('Project Information'!$C$4,Translations!$D$1:$ZZ$1,0)) | BC14: =INDEX(Translations!$D:$ZZ, MATCH(79,Translations!$A:$A,0), MATCH('Project Information'!$C$4,Translations!$D$1:$ZZ$1,0)) | BD14: =IF(OR(TRIM("")="Evet",TRIM("")="Yes"),1,0) | BE14: 1 | BF14: =BD14*BE14 | BH14: =INDEX(Translations!$D:$ZZ, MATCH(306,Translations!$A:$A,0), MATCH('Project Information'!$C$4,Translations!$D$1:$ZZ$1,0)) | BI14: =INDEX(Translations!$D:$ZZ, MATCH(215,Translations!$A:$A,0), MATCH('Project Information'!$C$4,Translations!$D$1:$ZZ$1,0)) | BJ14: =INDEX(Translations!$D:$ZZ, MATCH(343,Translations!$A:$A,0), MATCH('Project Information'!$C$4,Translations!$D$1:$ZZ$1,0)) | BK14: =INDEX(Translations!$D:$ZZ, MATCH(75,Translations!$A:$A,0), MATCH('Project Information'!$C$4,Translations!$D$1:$ZZ$1,0)) | BL14: =IF(OR(TRIM(Development!$F$21)="Evet",TRIM(Development!$F$21)="Yes"),1,0) | BM14: 4 | BN14: =BL14*BM14
